Workbook

Sheet Totals
A1: measuredWorksTotal
A2: buildingWorksEstimate
A3: totalInclRisk
A4: totalInclInflation
A5: totalInclAdjustments
A6: grandTotal

Sheet Hidden Data
O2: SPEC LEVEL
A3: BCIS Q DATE | C3: SECTOR | E3: REGION | G3: COST STAGE | K3: Complexity Rating | M3: SITE TYPE | O3: Low
A4: Q1 | C4: Residential | E4: London | G4: Cost plan | I4: Yes | M4: Brownfield | O4: Medium
A5: Q2 | C5: Student Accommodation | E5: South East | G5: Tender | I5: No | M5: Greenfield | O5: High
A6: Q3 | C6: Care Homes | E6: South West | G6: Contract Sum | O6: COMPLEXITY RATING
A7: Q4 | C7: Offices | E7: East of England | G7: Final Account | O7: 1
C8: Retail | E8: East Midlands | O8: 2
C9: Hotels | E9: West Midlands | O9: 3
C10: Leisure Facilities | E10: North West | O10: 4
C11: Warehouses | E11: North East | O11: 5
C12: Civils | E12: Yorkshire and the Humber | K12: USD
C13: Schools | E13: Scotland | K13: GBP
C14: Universities | E14: Wales | K14: EURO
C15: Hospitals | E15: Northern Ireland
C16: Medical Centres
C17: Laboratories
C18: Heritage
C19: Data Centres

Sheet Project Information - 1
A1: Key Data
A2: Project Name * | B2: Elm Court Residential
A3: Project Number * | B3: DEMO-2026-001
A4: Report date * | B4: 46093
A5: Base Date * | B5: 46093
A6: BCIS Q Date * | B6: Q2
A7: Sector * | B7: Residential
A8: Location * | B8: London
A9: Currency * | B9: GBP
A10: Programme (weeks) | B10: 52
A11: Project Type - New Build * | B11: Yes
A12: Project Type - Horizontal extension* | B12: No
A13: Project Type - Vertical extension* | B13: No
A14: Project Type - Refurbishment* | B14: No
A15: Spec Level | B15: Low
A16: Cost Stage* | B16: Cost plan
A17: Inflation adjusted* | B17: Yes
A18: Region adjusted* | B18: Yes
A19: Prelims included?* | B19: Yes
A20: Prof fees included?* | B20: No
A21: Site Type* | B21: Brownfield
A22: Access Constraints | B22: Restricted site access via single road frontage
A23: Complexity Rating | B23: 3
A24: Nr of Storeys * | B24: 4
A25: Basement * | B25: Yes
A26: Occupied? * | B26: No
A29: Costplan Document
A30: Reference for Costplan Budget Document * | B30: Sample Cost Plan - Elm Court Residential, Rev 01 | C30: Costplan document to include date and revision.
A32: Tendering Contractors
A33: Contractor 1 (SELECTED CONTRACTOR) * | B33: Ridgeway Construction
A34: Contractor 2 | B34: Brightstone Builders
A35: Contractor 3 | B35: Kestrel Contractors
A36: Contractor 4 | B36: INSERT CONTRACTOR 4
A37: Contractor 5 | B37: INSERT CONTRACTOR 5
A38: Contractor 6 | B38: INSERT CONTRACTOR 6
A39: Contractor 7 | B39: INSERT CONTRACTOR 7
A42: Benchmark Projects
A43: Benchmark 1 | B43: INSERT BENCHMARK NAME
A44: Benchmark 2 | B44: INSERT BENCHMARK NAME

Sheet Project Information - 2
A1: Name | B1: Qty | C1: Unit | D1: Comments
A2: GIFA * | B2: 1001 | C2: m2
A12: SECTOR
A13: Residential
A14: flats | B14: 18 | C14: nr
A15: houses | B15: 4 | C15: nr
A16: total plots | B16: 22 | C16: nr
A18: Student Accommodation
A19: Care Homes
A20: Offices
A21: Retail
A23: Hotels
A24: Keys | B24: 7 | C24: nr
A25: FoH Area | B25: 951 | C25: m2
A26: BoH Area | B26: 50 | C26: m2
A28: Leisure Facilities
A29: Warehouses
A30: Civils
A31: Schools
A32: Universities
A33: Hospitals
A34: Medical Centres
A35: Laboratories
A36: Heritage
A37: Data Centres

Sheet Project Information - 3
A1: Code | B1: Element | C1: Qty | D1: Unit | E1: Comments
A2: 0.1 | B2: Demolition and alterations | C2: 503 | D2: m2 | E2: GIFA of buildings to be demolished
B3: Groundworks (cut and fill) | C3: 0 | D3: m2 | E3: Site Area
B4: Ground Remediation Works | C4: 0 | D4: m2 | E4: Site Area
A5: =INDEX(SUMMARY!$A$8:$A$52,MATCH(B5,SUMMARY!$B$8:$B$52,0)) -> 1.1 | B5: Substructure | C5: 393 | D5: m2
A6: =INDEX(SUMMARY!$A$5:$A$52,MATCH(B6,SUMMARY!$B$5:$B$52,0)) -> 2.1 | B6: Frame | C6: 960 | D6: m2
A7: =INDEX(SUMMARY!$A$5:$A$52,MATCH(B7,SUMMARY!$B$5:$B$52,0)) -> 2.2 | B7: Upper Floors | C7: 686 | D7: m2
A8: =INDEX(SUMMARY!$A$5:$A$52,MATCH(B8,SUMMARY!$B$5:$B$52,0)) -> 2.3 | B8: Roof | C8: 271 | D8: m2
A9: =INDEX(SUMMARY!$A$5:$A$52,MATCH(B9,SUMMARY!$B$5:$B$52,0)) -> 2.4 | B9: Stairs and Ramps | C9: 8 | D9: no
A10: =INDEX(SUMMARY!$A$5:$A$52,MATCH(B10,SUMMARY!$B$5:$B$52,0)) -> 2.5 | B10: External Walls | C10: 581 | D10: m2
A11: =INDEX(SUMMARY!$A$5:$A$52,MATCH(B11,SUMMARY!$B$5:$B$52,0)) -> 2.6 | B11: Windows & External Doors | C11: 203 | D11: m2
A12: =INDEX(SUMMARY!$A$5:$A$52,MATCH(B12,SUMMARY!$B$5:$B$52,0)) -> 2.7 | B12: Internal Walls and Partitions | C12: 902 | D12: m2
A13: =INDEX(SUMMARY!$A$5:$A$52,MATCH(B13,SUMMARY!$B$5:$B$52,0)) -> 2.8 | B13: Internal Doors | C13: 77 | D13: no/leaf
A14: =INDEX(SUMMARY!$A$5:$A$52,MATCH(B14,SUMMARY!$B$5:$B$52,0)) -> 3.1 | B14: Wall finishes | C14: 3183 | D14: m2
A15: =INDEX(SUMMARY!$A$5:$A$52,MATCH(B15,SUMMARY!$B$5:$B$52,0)) -> 3.2 | B15: Floor finishes | C15: 907 | D15: m2
A16: =INDEX(SUMMARY!$A$5:$A$52,MATCH(B16,SUMMARY!$B$5:$B$52,0)) -> 3.3 | B16: Ceiling finishes | C16: 881 | D16: m2
A17: =SUMMARY!$A$23 -> 4.1 | B17: Fittings Furnishings and Equipment | C17: 1 | D17: m2
A18: =INDEX(SUMMARY!$A$5:$A$52,MATCH(B18,SUMMARY!$B$5:$B$52,0)) -> 5.1 | B18: Sanitary installations | C18: 1 | D18: m2
A19: =INDEX(SUMMARY!$A$5:$A$52,MATCH(B19,SUMMARY!$B$5:$B$52,0)) -> 5.2 | B19: Services Equipment | C19: 1 | D19: m2
A20: =INDEX(SUMMARY!$A$5:$A$52,MATCH(B20,SUMMARY!$B$5:$B$52,0)) -> 5.3 | B20: Electrical Installations | C20: 1 | D20: m2
A21: =INDEX(SUMMARY!$A$5:$A$52,MATCH(B21,SUMMARY!$B$5:$B$52,0)) -> 5.4 | B21: Mechanical Installations | C21: 1 | D21: m2
A22: =INDEX(SUMMARY!$A$5:$A$52,MATCH(B22,SUMMARY!$B$5:$B$52,0)) -> 5.5 | B22: Lift and conveyor installations | C22: 1 | D22: nr
A23: =INDEX(SUMMARY!$A$5:$A$52,MATCH(B23,SUMMARY!$B$5:$B$52,0)) -> 5.6 | B23: Fire and lightning protection | C23: 1 | D23: m2
A24: =INDEX(SUMMARY!$A$5:$A$52,MATCH(B24,SUMMARY!$B$5:$B$52,0)) -> 5.7 | B24: Communication, security and control systems | C24: 1 | D24: m2
A25: =INDEX(SUMMARY!$A$5:$A$52,MATCH(B25,SUMMARY!$B$5:$B$52,0)) -> 5.8 | B25: Specialist installations | C25: 1 | D25: m2
A26: =INDEX(SUMMARY!$A$5:$A$52,MATCH(B26,SUMMARY!$B$5:$B$52,0)) -> 5.9 | B26: BWIC with services | C26: 1 | D26: m2
A27: =INDEX(SUMMARY!$A$5:$A$52,MATCH(B27,SUMMARY!$B$5:$B$52,0)) -> 5.1 | B27: Testing and commissioning of services | C27: 1 | D27: m2
A28: =INDEX(SUMMARY!$A$36:$A$52,MATCH(B28,SUMMARY!$B$36:$B$52,0)) -> 6.1 | B28: Prefabricated buildings and building units | C28: 1000 | D28: m2
A29: =INDEX(SUMMARY!$A$5:$A$52,MATCH(B29,SUMMARY!$B$5:$B$52,0)) -> 7.1 | B29: Minor demolition and alteration works | C29: 1000 | D29: m2
A30: =INDEX(SUMMARY!$A$5:$A$52,MATCH(B30,SUMMARY!$B$5:$B$52,0)) -> 7.2 | B30: repairs to existing services | C30: 1000 | D30: m2
A31: =INDEX(SUMMARY!$A$5:$A$52,MATCH(B31,SUMMARY!$B$5:$B$52,0)) -> 7.3 | B31: Damp proof courses / fungus and beetle eradication | C31: 1000 | D31: m2
A32: =INDEX(SUMMARY!$A$5:$A$52,MATCH(B32,SUMMARY!$B$5:$B$52,0)) -> 7.4 | B32: Façade retention | C32: 1000 | D32: m2
A33: =INDEX(SUMMARY!$A$5:$A$52,MATCH(B33,SUMMARY!$B$5:$B$52,0)) -> 7.5 | B33: Cleaning existing surfaces | C33: 1000 | D33: m2
A34: =INDEX(SUMMARY!$A$5:$A$52,MATCH(B34,SUMMARY!$B$5:$B$52,0)) -> 7.6 | B34: Renovation works | C34: 1000 | D34: m2
A35: =INDEX(SUMMARY!$A$5:$A$52,MATCH(B35,SUMMARY!$B$5:$B$52,0)) -> 8.1 | B35: Site preparation works | C35: 1000 | D35: m2
A36: =INDEX(SUMMARY!$A$5:$A$52,MATCH(B36,SUMMARY!$B$5:$B$52,0)) -> 8.2 | B36: Roads, paths, pavings and surfacings | C36: 1000 | D36: m2
A37: =INDEX(SUMMARY!$A$5:$A$52,MATCH(B37,SUMMARY!$B$5:$B$52,0)) -> 8.3 | B37: Soft landscapes, planting and irrigation systems | C37: 1000 | D37: m2
A38: =INDEX(SUMMARY!$A$5:$A$52,MATCH(B38,SUMMARY!$B$5:$B$52,0)) -> 8.4 | B38: Fencing, railings and walls | C38: 1000 | D38: m2
A39: =INDEX(SUMMARY!$A$5:$A$52,MATCH(B39,SUMMARY!$B$5:$B$52,0)) -> 8.5 | B39: External fixtures | C39: 1000 | D39: m2
A40: =INDEX(SUMMARY!$A$5:$A$52,MATCH(B40,SUMMARY!$B$5:$B$52,0)) -> 8.6 | B40: External drainage | C40: 1000 | D40: m2
... A42: =INDEX(SUMMARY!$A$5:$A$52,MATCH(B42,SUMMARY!$B$5:$B$52,0)) -> 8.8 | B42: Minor building works and anciliary builidngs | C42: 1000 | D42: m2

Sheet SUMMARY
E3: ='Project Information - 1'!B30 -> Sample Cost Plan - Elm Court Residential, Rev 01 | H3: Average Tender | K3: ='Project Information - 1'!B33 -> Ridgeway Construction | N3: ='Project Information - 1'!B34 -> Brightstone Builders | Q3: ='Project Information - 1'!B35 -> Kestrel Contractors | T3: ='Project Information - 1'!B36 -> INSERT CONTRACTOR 4 | W3: ='Project Information - 1'!B37 -> INSERT CONTRACTOR 5 | Z3: ='Project Information - 1'!B38 -> INSERT CONTRACTOR 6 | AC3: ='Project Information - 1'!B39 -> INSERT CONTRACTOR 7 | AF3: ='Project Information - 1'!B43 -> INSERT BENCHMARK NAME | AI3: ='Project Information - 1'!B44 -> INSERT BENCHMARK NAME | AL3: Limit 1 | AN3: Limit 2
A4: Code | B4: Element | C4: EUQ | D4: Unit | E4: EUR | F4: Total | H4: EUR | I4: Total | K4: EUR | L4: Total | N4: EUR | O4: Total | Q4: EUR | R4: Total | T4: EUR | U4: Total | W4: EUR | X4: Total | Z4: EUR | AA4: Total | AC4: EUR | AD4: Total | AF4: EUR | AG4: Total | AI4: EUR | AJ4: Total | AL4: Lower bound | AM4: Upper Bound | AN4: Lower bound | AO4: Upper Bound
A5: 0 | B5: Facilitating Works | F5: =SUBTOTAL(9,F6:F6) -> 430551.5 | I5: =SUBTOTAL(9,I6:I6) -> 270028 | L5: =SUBTOTAL(9,L6:L6) -> 430551.5 | O5: =SUBTOTAL(9,O6:O6) -> 195746 | R5: =SUBTOTAL(9,R6:R6) -> 183786.5 | U5: =SUBTOTAL(9,U6:U6) -> 198451.5 | X5: =SUBTOTAL(9,X6:X6) -> 0 | AA5: =SUBTOTAL(9,AA6:AA6) -> 0 | AD5: =SUBTOTAL(9,AD6:AD6) -> 0 | AG5: =SUBTOTAL(9,AG6) -> 0 | AJ5: =SUBTOTAL(9,AJ6) -> 0
A6: 0.1 | B6: Demolition and alterations | C6: ='Project Information - 3'!$C$2 -> 503 | D6: m2 | E6: =SUM(F6)/$C6 -> 855.9672 | F6: ='0.1 Demolition & alterations'!F54 -> 430551.5 | H6: =SUM(I6)/$C6 -> 536.83499 | I6: =AVERAGE(L6,O6,R6) -> 270028 | L6: ='0.1 Demolition & alterations'!F54 -> 430551.5 | O6: ='0.1 Demolition & alterations'!K54 -> 195746 | R6: ='0.1 Demolition & alterations'!P54 -> 183786.5 | U6: ='0.1 Demolition & alterations'!U54 -> 198451.5
A7: 1 | B7: Substructure | F7: =SUBTOTAL(9,F8:F8) -> 153205 | I7: =SUBTOTAL(9,I8:I8) -> 130593 | L7: =SUBTOTAL(9,L8:L8) -> 108987 | O7: =SUBTOTAL(9,O8:O8) -> 172205 | R7: =SUBTOTAL(9,R8:R8) -> 110587 | U7: =SUBTOTAL(9,U8:U8) -> 0 | X7: =SUBTOTAL(9,X8:X8) -> 0 | AA7: =SUBTOTAL(9,AA8:AA8) -> 0 | AD7: =SUBTOTAL(9,AD8:AD8) -> 0 | AG7: =SUBTOTAL(9,AG8:AG8) -> 0 | AJ7: =SUBTOTAL(9,AJ8:AJ8) -> 0
A8: 1.1 | B8: Substructure | C8: ='Project Information - 3'!$C$5 -> 393 | D8: m2 | E8: =SUM(F8)/$C8 -> 389.83461 | F8: ='1.1 Substructure'!F54 -> 153205 | H8: =SUM(I8)/$C8 -> 332.29771 | I8: =AVERAGE(L8,O8,R8) -> 130593 | K8: =SUM(L8)/$C8 -> 277.32061 | L8: ='1.1 Substructure'!K54 -> 108987 | N8: =SUM(O8)/$C8 -> 438.18066 | O8: ='1.1 Substructure'!P54 -> 172205 | Q8: =SUM(R8)/$C8 -> 281.39186 | R8: ='1.1 Substructure'!U54 -> 110587 | T8: =SUM(U8)/$C8 -> 0 | U8: ='1.1 Substructure'!Z54 -> 0 | W8: =SUM(X8)/$C8 -> 0 | X8: ='1.1 Substructure'!AE54 -> 0 | Z8: =SUM(AA8)/$C8 -> 0 | AA8: ='1.1 Substructure'!AJ54 -> 0 | AC8: =SUM(AD8)/$C8 -> 0 | AD8: ='1.1 Substructure'!AO54 -> 0 | AF8: =SUM(AG8)/$C8 -> 0 | AI8: =SUM(AJ8)/$C8 -> 0
A9: 2 | B9: Superstructure | F9: =SUM(F10:F17) -> 1051375 | I9: =SUM(I10:I17) -> 1051375 | L9: =SUM(L10:L17) -> 1051375 | O9: =SUM(O10:O17) -> 1051375 | R9: =SUM(R10:R17) -> 1051375 | U9: =SUM(U10:U17) -> 0 | X9: =SUM(X10:X17) -> 0 | AA9: =SUM(AA10:AA17) -> 0 | AD9: =SUM(AD10:AD17) -> 0 | AG9: =SUM(AG10:AG14) -> 0 | AI9: =AJ9/'Project Information - 1'!$G$3 -> #DIV/0! | AJ9: =SUM(AJ10:AJ14) -> 0
A10: 2.1 | B10: Frame | C10: ='Project Information - 3'!$C$6 -> 960 | D10: m2 | E10: =SUM(F10)/$C10 -> 491.64062 | F10: ='2.1 Frame'!F54 -> 471975 | H10: =SUM(I10)/$C10 -> 491.64062 | I10: =AVERAGE(L10,O10,R10) -> 471975 | K10: =SUM(L10)/$C10 -> 491.64062 | L10: ='2.1 Frame'!K54 -> 471975 | N10: =SUM(O10)/$C10 -> 491.64062 | O10: ='2.1 Frame'!P54 -> 471975 | Q10: =SUM(R10)/$C10 -> 491.64062 | R10: ='2.1 Frame'!U54 -> 471975 | T10: =SUM(U10)/$C10 -> 0 | U10: ='2.1 Frame'!Z54 -> 0 | W10: =SUM(X10)/$C10 -> 0 | X10: ='2.1 Frame'!AE54 -> 0 | Z10: =SUM(AA10)/$C10 -> 0 | AA10: ='2.1 Frame'!AJ54 -> 0 | AC10: =SUM(AD10)/$C10 -> 0 | AD10: ='2.1 Frame'!AO54 -> 0 | AF10: =SUM(AG10)/$C10 -> 0 | AI10: =SUM(AJ10)/$C10 -> 0
A11: 2.2 | B11: Upper floors | C11: ='Project Information - 3'!$C$7 -> 686 | D11: m2 | E11: =SUM(F11)/$C11 -> 525.12391 | F11: ='2.2 Upper floors'!F54 -> 360235 | H11: =SUM(I11)/$C11 -> 525.12391 | I11: =AVERAGE(L11,O11,R11) -> 360235 | K11: =SUM(L11)/$C11 -> 525.12391 | L11: ='2.2 Upper floors'!K54 -> 360235 | N11: =SUM(O11)/$C11 -> 525.12391 | O11: ='2.2 Upper floors'!P54 -> 360235 | Q11: =SUM(R11)/$C11 -> 525.12391 | R11: ='2.2 Upper floors'!U54 -> 360235 | T11: =SUM(U11)/$C11 -> 0 | U11: ='2.2 Upper floors'!Z54 -> 0 | W11: =SUM(X11)/$C11 -> 0 | X11: ='2.2 Upper floors'!AE54 -> 0 | Z11: =SUM(AA11)/$C11 -> 0 | AA11: ='2.2 Upper floors'!AJ54 -> 0 | AC11: =SUM(AD11)/$C11 -> 0 | AD11: ='2.2 Upper floors'!AO54 -> 0 | AF11: =SUM(AG11)/$C11 -> 0 | AI11: =SUM(AJ11)/$C11 -> 0
A12: 2.3 | B12: Roof | C12: ='Project Information - 3'!$C$8 -> 271 | D12: m2 | E12: =SUM(F12)/$C12 -> 184.50185 | F12: ='2.3 Roof'!F54 -> 50000 | H12: =SUM(I12)/$C12 -> 184.50185 | I12: =AVERAGE(L12,O12,R12) -> 50000 | K12: =SUM(L12)/$C12 -> 184.50185 | L12: ='2.3 Roof'!K54 -> 50000 | N12: =SUM(O12)/$C12 -> 184.50185 | O12: ='2.3 Roof'!P54 -> 50000 | Q12: =SUM(R12)/$C12 -> 184.50185 | R12: ='2.3 Roof'!U54 -> 50000 | T12: =SUM(U12)/$C12 -> 0 | U12: ='2.3 Roof'!Z54 -> 0 | W12: =SUM(X12)/$C12 -> 0 | X12: ='2.3 Roof'!AE54 -> 0 | Z12: =SUM(AA12)/$C12 -> 0 | AA12: ='2.3 Roof'!AJ54 -> 0 | AC12: =SUM(AD12)/$C12 -> 0 | AD12: ='2.3 Roof'!AO54 -> 0 | AF12: =SUM(AG12)/$C12 -> 0 | AI12: =SUM(AJ12)/$C12 -> 0
A13: 2.4 | B13: Stairs and Ramps | C13: ='Project Information - 3'!$C$9 -> 8 | D13: no | E13: =SUM(F13)/$C13 -> 2500 | F13: ='2.4 Stairs and Ramps'!F54 -> 20000 | H13: =SUM(I13)/$C13 -> 2500 | I13: =AVERAGE(L13,O13,R13) -> 20000 | K13: =SUM(L13)/$C13 -> 2500 | L13: ='2.4 Stairs and Ramps'!K54 -> 20000 | N13: =SUM(O13)/$C13 -> 2500 | O13: ='2.4 Stairs and Ramps'!P54 -> 20000 | Q13: =SUM(R13)/$C13 -> 2500 | R13: ='2.4 Stairs and Ramps'!U54 -> 20000 | T13: =SUM(U13)/$C13 -> 0 | U13: ='2.4 Stairs and Ramps'!Z54 -> 0 | W13: =SUM(X13)/$C13 -> 0 | X13: ='2.4 Stairs and Ramps'!AE54 -> 0 | Z13: =SUM(AA13)/$C13 -> 0 | AA13: ='2.4 Stairs and Ramps'!AJ54 -> 0 | AC13: =SUM(AD13)/$C13 -> 0 | AD13: ='2.4 Stairs and Ramps'!AO54 -> 0 | AF13: =SUM(AG13)/$C13 -> 0 | AI13: =SUM(AJ13)/$C13 -> 0
A14: 2.5 | B14: External walls | C14: ='Project Information - 3'!$C$10 -> 581 | D14: m2 | E14: =SUM(F14)/$C14 -> 33.562823 | F14: ='2.5 External walls'!F55 -> 19500 | H14: =SUM(I14)/$C14 -> 33.562823 | I14: =AVERAGE(L14,O14,R14) -> 19500 | K14: =SUM(L14)/$C14 -> 33.562823 | L14: ='2.5 External walls'!K55 -> 19500 | N14: =SUM(O14)/$C14 -> 33.562823 | O14: ='2.5 External walls'!P55 -> 19500 | Q14: =SUM(R14)/$C14 -> 33.562823 | R14: ='2.5 External walls'!U55 -> 19500 | T14: =SUM(U14)/$C14 -> 0 | U14: ='2.5 External walls'!Z55 -> 0 | W14: =SUM(X14)/$C14 -> 0 | X14: ='2.5 External walls'!AE55 -> 0 | Z14: =SUM(AA14)/$C14 -> 0 | AA14: ='2.5 External walls'!AJ55 -> 0 | AC14: =SUM(AD14)/$C14 -> 0 | AD14: ='2.5 External walls'!AO55 -> 0 | AF14: =SUM(AG14)/$C14 -> 0 | AI14: =SUM(AJ14)/$C14 -> 0
A15: 2.6 | B15: Windows & external Doors | C15: ='Project Information - 3'!$C$11 -> 203 | D15: m2 | E15: =SUM(F15)/$C15 -> 87.684729 | F15: ='2.6 Windows & external Doors'!F54 -> 17800 | H15: =SUM(I15)/$C15 -> 87.684729 | I15: =AVERAGE(L15,O15,R15) -> 17800 | K15: =SUM(L15)/$C15 -> 87.684729 | L15: ='2.6 Windows & external Doors'!K54 -> 17800 | N15: =SUM(O15)/$C15 -> 87.684729 | O15: ='2.6 Windows & external Doors'!P54 -> 17800 | Q15: =SUM(R15)/$C15 -> 87.684729 | R15: ='2.6 Windows & external Doors'!U54 -> 17800 | T15: =SUM(U15)/$C15 -> 0 | U15: ='2.6 Windows & external Doors'!Z54 -> 0 | W15: =SUM(X15)/$C15 -> 0 | X15: ='2.6 Windows & external Doors'!AE54 -> 0 | Z15: =SUM(AA15)/$C15 -> 0 | AA15: ='2.6 Windows & external Doors'!AJ54 -> 0 | AC15: =SUM(AD15)/$C15 -> 0 | AD15: ='2.6 Windows & external Doors'!AO54 -> 0 | AF15: =SUM(AG15)/$C15 -> 0 | AI15: =SUM(AJ15)/$C15 -> 0
A16: 2.7 | B16: Internal Walls and Partitions | C16: ='Project Information - 3'!$C$13 -> 77 | D16: m2 | E16: =SUM(F16)/$C16 -> 236.36364 | F16: ='2.7 Internal Walls & Partitions'!F54 -> 18200 | H16: =SUM(I16)/$C16 -> 236.36364 | I16: =AVERAGE(L16,O16,R16) -> 18200 | K16: =SUM(L16)/$C16 -> 236.36364 | L16: ='2.7 Internal Walls & Partitions'!K54 -> 18200 | N16: =SUM(O16)/$C16 -> 236.36364 | O16: ='2.7 Internal Walls & Partitions'!P54 -> 18200 | Q16: =SUM(R16)/$C16 -> 236.36364 | R16: ='2.7 Internal Walls & Partitions'!U54 -> 18200 | T16: =SUM(U16)/$C16 -> 0 | U16: ='2.7 Internal Walls & Partitions'!Z54 -> 0 | W16: =SUM(X16)/$C16 -> 0 | X16: ='2.7 Internal Walls & Partitions'!AE54 -> 0 | Z16: =SUM(AA16)/$C16 -> 0 | AA16: ='2.7 Internal Walls & Partitions'!AJ54 -> 0 | AC16: =SUM(AD16)/$C16 -> 0 | AD16: ='2.7 Internal Walls & Partitions'!AO54 -> 0 | AF16: =SUM(AG16)/$C16 -> 0 | AI16: =SUM(AJ16)/$C16 -> 0
A17: 2.8 | B17: Internal Doors | C17: ='Project Information - 3'!$C$14 -> 3183 | D17: m2 | E17: =SUM(F17)/$C17 -> 29.426642 | F17: ='2.8 Internal Doors'!F54 -> 93665 | H17: =SUM(I17)/$C17 -> 29.426642 | I17: =AVERAGE(L17,O17,R17) -> 93665 | K17: =SUM(L17)/$C17 -> 29.426642 | L17: ='2.8 Internal Doors'!K54 -> 93665 | N17: =SUM(O17)/$C17 -> 29.426642 | O17: ='2.8 Internal Doors'!P54 -> 93665 | Q17: =SUM(R17)/$C17 -> 29.426642 | R17: ='2.8 Internal Doors'!U54 -> 93665 | T17: =SUM(U17)/$C17 -> 0 | U17: ='2.8 Internal Doors'!Z54 -> 0 | W17: =SUM(X17)/$C17 -> 0 | X17: ='2.8 Internal Doors'!AE54 -> 0 | Z17: =SUM(AA17)/$C17 -> 0 | AA17: ='2.8 Internal Doors'!AJ54 -> 0 | AC17: =SUM(AD17)/$C17 -> 0 | AD17: ='2.8 Internal Doors'!AO54 -> 0 | AF17: =SUM(AG17)/$C17 -> 0 | AI17: =SUM(AJ17)/$C17 -> 0
A18: 3 | B18: Internal Finishes | F18: =SUM(F19:F21) -> 670405 | I18: =SUM(I19:I21) -> 713096.67 | L18: =SUM(L19:L21) -> 641355 | O18: =SUM(O19:O21) -> 770680 | R18: =SUM(R19:R21) -> 727255 | U18: =SUM(U19:U20) -> 0 | X18: =SUM(X19:X20) -> 0 | AA18: =SUM(AA19:AA20) -> 0 | AD18: =SUM(AD19:AD20) -> 0 | AG18: =SUM(AG19:AG20) -> 0 | AJ18: =SUM(AJ19:AJ20) -> 0
A19: 3.1 | B19: Wall finishes | C19: ='Project Information - 3'!$C$14 -> 3183 | D19: m2 | E19: =SUM(F19)/$C19 -> 51.460886 | F19: ='3.1 Wall Finishes'!F54 -> 163800 | H19: =SUM(I19)/$C19 -> 51.460886 | I19: =AVERAGE(L19,O19,R19) -> 163800 | K19: =SUM(L19)/$C19 -> 51.460886 | L19: ='3.1 Wall Finishes'!K54 -> 163800 | N19: =SUM(O19)/$C19 -> 51.460886 | O19: ='3.1 Wall Finishes'!P54 -> 163800 | Q19: =SUM(R19)/$C19 -> 51.460886 | R19: ='3.1 Wall Finishes'!U54 -> 163800 | T19: =SUM(U19)/$C19 -> 0 | U19: ='3.1 Wall Finishes'!Z54 -> 0 | W19: =SUM(X19)/$C19 -> 0 | X19: ='3.1 Wall Finishes'!AE54 -> 0 | Z19: =SUM(AA19)/$C19 -> 0 | AA19: ='3.1 Wall Finishes'!AJ54 -> 0 | AC19: =SUM(AD19)/$C19 -> 0 | AD19: ='3.1 Wall Finishes'!AO54 -> 0 | AF19: =SUM(AG19)/$C19 -> 0 | AL19: =$I19*(1-#REF!) -> #REF! | AM19: =$I19*(1+#REF!) -> #REF! | AN19: =$I19*(1-#REF!) -> #REF! | AO19: =$I19*(1+#REF!) -> #REF!
A20: 3.2 | B20: Floor finishes | C20: ='Project Information - 3'!$C$15 -> 907 | D20: m2 | E20: =SUM(F20)/$C20 -> 89.255788 | F20: ='3.2 Floor Finishes'!F54 -> 80955 | H20: =SUM(I20)/$C20 -> 89.237413 | I20: =AVERAGE(L20,O20,R20) -> 80938.333 | K20: =SUM(L20)/$C20 -> 89.807056 | L20: ='3.2 Floor Finishes'!K54 -> 81455 | N20: =SUM(O20)/$C20 -> 88.814774 | O20: ='3.2 Floor Finishes'!P54 -> 80555 | Q20: =SUM(R20)/$C20 -> 89.090408 | R20: ='3.2 Floor Finishes'!U54 -> 80805 | T20: =SUM(U20)/$C20 -> 0 | U20: ='3.2 Floor Finishes'!Z54 -> 0 | W20: =SUM(X20)/$C20 -> 0 | X20: ='3.2 Floor Finishes'!AE54 -> 0 | Z20: =SUM(AA20)/$C20 -> 0 | AA20: ='3.2 Floor Finishes'!AJ54 -> 0 | AC20: =SUM(AD20)/$C20 -> 0 | AD20: ='3.2 Floor Finishes'!AO54 -> 0 | AF20: =SUM(AG20)/$C20 -> 0 | AL20: =$I20*(1-#REF!) -> #REF! | AM20: =$I20*(1+#REF!) -> #REF! | AN20: =$I20*(1-#REF!) -> #REF! | AO20: =$I20*(1+#REF!) -> #REF!
A21: 3.3 | B21: Ceiling finishes | C21: ='Project Information - 3'!$C$16 -> 881 | D21: m2 | E21: =SUM(F21)/$C21 -> 483.14415 | F21: ='3.3 Ceiling finishes'!F54 -> 425650 | H21: =SUM(I21)/$C21 -> 531.62126 | I21: =AVERAGE(L21,O21,R21) -> 468358.33 | K21: =SUM(L21)/$C21 -> 449.60272 | L21: ='3.3 Ceiling finishes'!K54 -> 396100 | N21: =SUM(O21)/$C21 -> 597.41771 | O21: ='3.3 Ceiling finishes'!P54 -> 526325 | Q21: =SUM(R21)/$C21 -> 547.84336 | R21: ='3.3 Ceiling finishes'!U54 -> 482650 | T21: =SUM(U21)/$C21 -> 0 | U21: ='3.3 Ceiling finishes'!Z54 -> 0 | W21: =SUM(X21)/$C21 -> 0 | X21: ='3.3 Ceiling finishes'!AE54 -> 0 | Z21: =SUM(AA21)/$C21 -> 0 | AA21: ='3.3 Ceiling finishes'!AJ54 -> 0 | AC21: =SUM(AD21)/$C21 -> 0 | AD21: ='3.3 Ceiling finishes'!AO54 -> 0 | AF21: =SUM(AG21)/$C21 -> 0
A22: 4 | B22: Fittings, Furnishings & Equipment | F22: =SUM(F23) -> 67365 | I22: =SUM(I23) -> 67365 | L22: =SUM(L23) -> 67365 | O22: =SUM(O23) -> 67365 | R22: =SUM(R23) -> 67365 | U22: =SUM(U23) -> 0 | X22: =SUM(X23) -> 0 | AA22: =SUM(AA23) -> 0 | AD22: =SUM(AD23) -> 0 | AG22: =SUM(AG23) -> 0 | AJ22: =SUM(AJ23) -> 0
A23: 4.1 | B23: Fittings, furnishings and equipment | C23: ='Project Information - 3'!$C$17 -> 1 | D23: m2 | E23: =SUM(F23)/$C23 -> 67365 | F23: ='4.1 FF&E'!F54 -> 67365 | H23: =SUM(I23)/$C23 -> 67365 | I23: =AVERAGE(L23,O23,R23) -> 67365 | K23: =SUM(L23)/$C23 -> 67365 | L23: ='4.1 FF&E'!K54 -> 67365 | N23: =SUM(O23)/$C23 -> 67365 | O23: ='4.1 FF&E'!P54 -> 67365 | Q23: =SUM(R23)/$C23 -> 67365 | R23: ='4.1 FF&E'!U54 -> 67365 | T23: =SUM(U23)/$C23 -> 0 | U23: ='4.1 FF&E'!Z54 -> 0 | W23: =SUM(X23)/$C23 -> 0 | X23: ='4.1 FF&E'!AE54 -> 0 | Z23: =SUM(AA23)/$C23 -> 0 | AA23: ='4.1 FF&E'!AJ54 -> 0 | AC23: =SUM(AD23)/$C23 -> 0 | AD23: ='4.1 FF&E'!AO54 -> 0 | AF23: ='4.1 FF&E'!AR54 -> 0
A24: 5 | B24: Services | F24: =SUBTOTAL(9,F25:F27) -> 108430 | I24: =SUBTOTAL(9,I25:I27) -> 108430 | L24: =SUBTOTAL(9,L25:L27) -> 108430 | O24: =SUBTOTAL(9,O25:O27) -> 108430 | R24: 491679 | S24: =T24/'Project Information - 1'!$G$3 -> #DIV/0! | U24: 491679 | X24: 491679 | AA24: 491679 | AD24: 491679 | AG24: =SUBTOTAL(9,AG25:AG27) -> 0 | AJ24: =SUBTOTAL(9,AJ25:AJ27) -> 0
A25: 5.1 | B25: Sanitary installations | C25: ='Project Information - 3'!$C$18 -> 1 | D25: m2 | E25: =SUM(F25)/$C25 -> 69230 | F25: ='5.1 Sanitary installations'!F54 -> 69230 | H25: =SUM(I25)/$C25 -> 69230 | I25: =AVERAGE(L25,O25,R25) -> 69230 | K25: =SUM(L25)/$C25 -> 69230 | L25: ='5.1 Sanitary installations'!K54 -> 69230 | N25: =SUM(O25)/$C25 -> 69230 | O25: ='5.1 Sanitary installations'!P54 -> 69230 | Q25: =SUM(R25)/$C25 -> 69230 | R25: ='5.1 Sanitary installations'!U54 -> 69230 | T25: =SUM(U25)/$C25 -> 0 | U25: ='5.1 Sanitary installations'!Z54 -> 0 | W25: =SUM(X25)/$C25 -> 0 | X25: ='5.1 Sanitary installations'!AE54 -> 0 | Z25: =SUM(AA25)/$C25 -> 0 | AA25: ='5.1 Sanitary installations'!AJ54 -> 0 | AC25: =SUM(AD25)/$C25 -> 0 | AD25: ='5.1 Sanitary installations'!AO54 -> 0 | AF25: =SUM(AG25)/$C25 -> 0
A26: 5.2 | B26: Services equipment | C26: ='Project Information - 3'!$C$19 -> 1 | D26: m2 | E26: =SUM(F26)/$C26 -> 21600 | F26: ='5.2 Services equipment'!F54 -> 21600 | H26: =SUM(I26)/$C26 -> 21600 | I26: =AVERAGE(L26,O26,R26) -> 21600 | K26: =SUM(L26)/$C26 -> 21600 | L26: ='5.2 Services equipment'!K54 -> 21600 | N26: =SUM(O26)/$C26 -> 21600 | O26: ='5.2 Services equipment'!P54 -> 21600 | Q26: =SUM(R26)/$C26 -> 21600 | R26: ='5.2 Services equipment'!U54 -> 21600 | T26: =SUM(U26)/$C26 -> 0 | U26: ='5.2 Services equipment'!Z54 -> 0 | W26: =SUM(X26)/$C26 -> 0 | X26: ='5.2 Services equipment'!AE54 -> 0 | Z26: =SUM(AA26)/$C26 -> 0 | AA26: ='5.2 Services equipment'!AJ54 -> 0 | AC26: =SUM(AD26)/$C26 -> 0 | AD26: ='5.2 Services equipment'!AO54 -> 0 | AF26: =SUM(AG26)/$C26 -> 0
A27: 5.3 | B27: Electrical Installations | C27: ='Project Information - 3'!$C$20 -> 1 | D27: m2 | E27: =SUM(F27)/$C27 -> 17600 | F27: ='5.3 Electrical Installations'!F54 -> 17600 | H27: =SUM(I27)/$C27 -> 17600 | I27: =AVERAGE(L27,O27,R27) -> 17600 | K27: =SUM(L27)/$C27 -> 17600 | L27: ='5.3 Electrical Installations'!K54 -> 17600 | N27: =SUM(O27)/$C27 -> 17600 | O27: ='5.3 Electrical Installations'!P54 -> 17600 | Q27: =SUM(R27)/$C27 -> 17600 | R27: ='5.3 Electrical Installations'!U54 -> 17600 | T27: =SUM(U27)/$C27 -> 0 | U27: ='5.3 Electrical Installations'!Z54 -> 0 | W27: =SUM(X27)/$C27 -> 0 | X27: ='5.3 Electrical Installations'!AE54 -> 0 | Z27: =SUM(AA27)/$C27 -> 0 | AA27: ='5.3 Electrical Installations'!AJ54 -> 0 | AC27: =SUM(AD27)/$C27 -> 0 | AD27: ='5.3 Electrical Installations'!AO54 -> 0 | AF27: =SUM(AG27)/$C27 -> 0
A28: 5.4 | B28: Mechanical Installations | C28: ='Project Information - 3'!$C$21 -> 1 | D28: m2 | E28: =SUM(F28)/$C28 -> 18500 | F28: ='5.4 Mechanical Installations'!F54 -> 18500 | H28: =SUM(I28)/$C28 -> 18500 | I28: =AVERAGE(L28,O28,R28) -> 18500 | K28: =SUM(L28)/$C28 -> 18500 | L28: ='5.4 Mechanical Installations'!K54 -> 18500 | N28: =SUM(O28)/$C28 -> 18500 | O28: ='5.4 Mechanical Installations'!P54 -> 18500 | Q28: =SUM(R28)/$C28 -> 18500 | R28: ='5.4 Mechanical Installations'!U54 -> 18500 | T28: =SUM(U28)/$C28 -> 0 | U28: ='5.4 Mechanical Installations'!Z54 -> 0 | W28: =SUM(X28)/$C28 -> 0 | X28: ='5.4 Mechanical Installations'!AE54 -> 0 | Z28: =SUM(AA28)/$C28 -> 0 | AA28: ='5.4 Mechanical Installations'!AJ54 -> 0 | AC28: =SUM(AD28)/$C28 -> 0 | AD28: ='5.4 Mechanical Installations'!AO54 -> 0 | AF28: =SUM(AG28)/$C28 -> 0
A29: 5.5 | B29: Lift and conveyor installations | C29: ='Project Information - 3'!$C$22 -> 1 | D29: ='Project Information - 1'!H45 -> 0 | E29: =SUM(F29)/$C29 -> 11000 | F29: ='5.5 Lift & conveyor'!F54 -> 11000 | H29: =SUM(I29)/$C29 -> 11000 | I29: =AVERAGE(L29,O29,R29) -> 11000 | K29: =SUM(L29)/$C29 -> 11000 | L29: ='5.5 Lift & conveyor'!K54 -> 11000 | N29: =SUM(O29)/$C29 -> 11000 | O29: ='5.5 Lift & conveyor'!P54 -> 11000 | Q29: =SUM(R29)/$C29 -> 11000 | R29: ='5.5 Lift & conveyor'!U54 -> 11000 | T29: =SUM(U29)/$C29 -> 0 | U29: ='5.5 Lift & conveyor'!Z54 -> 0 | W29: =SUM(X29)/$C29 -> 0 | X29: ='5.5 Lift & conveyor'!AE54 -> 0 | Z29: =SUM(AA29)/$C29 -> 0 | AA29: ='5.5 Lift & conveyor'!AJ54 -> 0 | AC29: =SUM(AD29)/$C29 -> 0 | AD29: ='5.5 Lift & conveyor'!AO54 -> 0 | AF29: =SUM(AG29)/$C29 -> 0
A30: 5.6 | B30: Fire and lightning protection | C30: ='Project Information - 3'!$C$23 -> 1 | D30: m2 | E30: =SUM(F30)/$C30 -> 16400 | F30: ='5.6 Fire & lightning protection'!F54 -> 16400 | H30: =SUM(I30)/$C30 -> 16400 | I30: =AVERAGE(L30,O30,R30) -> 16400 | K30: =SUM(L30)/$C30 -> 16400 | L30: ='5.6 Fire & lightning protection'!K54 -> 16400 | N30: =SUM(O30)/$C30 -> 16400 | O30: ='5.6 Fire & lightning protection'!P54 -> 16400 | Q30: =SUM(R30)/$C30 -> 16400 | R30: ='5.6 Fire & lightning protection'!U54 -> 16400 | T30: =SUM(U30)/$C30 -> 0 | U30: ='5.6 Fire & lightning protection'!Z54 -> 0 | W30: =SUM(X30)/$C30 -> 0 | X30: ='5.6 Fire & lightning protection'!AE54 -> 0 | Z30: =SUM(AA30)/$C30 -> 0 | AA30: ='5.6 Fire & lightning protection'!AJ54 -> 0 | AC30: =SUM(AD30)/$C30 -> 0 | AD30: ='5.6 Fire & lightning protection'!AO54 -> 0 | AF30: =SUM(AG30)/$C30 -> 0
A31: 5.7 | B31: Communication, security and control systems | C31: ='Project Information - 3'!$C$24 -> 1 | D31: m2 | E31: =SUM(F31)/$C31 -> 20000 | F31: ='5.7 Communication security'!F54 -> 20000 | H31: =SUM(I31)/$C31 -> 20000 | I31: =AVERAGE(L31,O31,R31) -> 20000 | K31: =SUM(L31)/$C31 -> 20000 | L31: ='5.7 Communication security'!K54 -> 20000 | N31: =SUM(O31)/$C31 -> 20000 | O31: ='5.7 Communication security'!P54 -> 20000 | Q31: =SUM(R31)/$C31 -> 20000 | R31: ='5.7 Communication security'!U54 -> 20000 | T31: =SUM(U31)/$C31 -> 20000 | U31: ='5.7 Communication security'!Z54 -> 20000 | W31: =SUM(X31)/$C31 -> 30000 | X31: ='5.7 Communication security'!AE54 -> 30000 | Z31: =SUM(AA31)/$C31 -> 27500 | AA31: ='5.7 Communication security'!AJ54 -> 27500 | AC31: =SUM(AD31)/$C31 -> 50000 | AD31: ='5.7 Communication security'!AO54 -> 50000 | AF31: =SUM(AG31)/$C31 -> 0
A32: 5.8 | B32: Specialist installations | C32: ='Project Information - 3'!$C$25 -> 1 | D32: m2 | E32: =SUM(F32)/$C32 -> 20000 | F32: ='5.8 Specialist installations'!F54 -> 20000 | H32: =SUM(I32)/$C32 -> 20000 | I32: =AVERAGE(L32,O32,R32) -> 20000 | K32: =SUM(L32)/$C32 -> 20000 | L32: ='5.8 Specialist installations'!K54 -> 20000 | N32: =SUM(O32)/$C32 -> 20000 | O32: ='5.8 Specialist installations'!P54 -> 20000 | Q32: =SUM(R32)/$C32 -> 20000 | R32: ='5.8 Specialist installations'!U54 -> 20000 | T32: =SUM(U32)/$C32 -> 20000 | U32: ='5.8 Specialist installations'!Z54 -> 20000 | W32: =SUM(X32)/$C32 -> 30000 | X32: ='5.8 Specialist installations'!AE54 -> 30000 | Z32: =SUM(AA32)/$C32 -> 27500 | AA32: ='5.8 Specialist installations'!AJ54 -> 27500 | AC32: =SUM(AD32)/$C32 -> 50000 | AD32: ='5.8 Specialist installations'!AO54 -> 50000 | AF32: =SUM(AG32)/$C32 -> 0
A33: 5.9 | B33: BWIC with services | C33: ='Project Information - 3'!$C$26 -> 1 | D33: m2 | E33: =SUM(F33)/$C33 -> 20000 | F33: ='5.9 BWIC with services'!F54 -> 20000 | H33: =SUM(I33)/$C33 -> 20000 | I33: =AVERAGE(L33,O33,R33) -> 20000 | K33: =SUM(L33)/$C33 -> 20000 | L33: ='5.9 BWIC with services'!K54 -> 20000 | N33: =SUM(O33)/$C33 -> 20000 | O33: ='5.9 BWIC with services'!P54 -> 20000 | Q33: =SUM(R33)/$C33 -> 20000 | R33: ='5.9 BWIC with services'!U54 -> 20000 | T33: =SUM(U33)/$C33 -> 20000 | U33: ='5.9 BWIC with services'!Z54 -> 20000 | W33: =SUM(X33)/$C33 -> 30000 | X33: ='5.9 BWIC with services'!AE54 -> 30000 | Z33: =SUM(AA33)/$C33 -> 27500 | AA33: ='5.9 BWIC with services'!AJ54 -> 27500 | AC33: =SUM(AD33)/$C33 -> 50000 | AD33: ='5.9 BWIC with services'!AO54 -> 50000 | AF33: =SUM(AG33)/$C33 -> 0
A34: 5.1 | B34: Testing and commissioning of services | C34: ='Project Information - 3'!$C$27 -> 1 | D34: m2 | E34: =SUM(F34)/$C34 -> 20000 | F34: ='5.10 Testing & Commissioning'!F54 -> 20000 | H34: =SUM(I34)/$C34 -> 20000 | I34: =AVERAGE(L34,O34,R34) -> 20000 | K34: =SUM(L34)/$C34 -> 20000 | L34: ='5.10 Testing & Commissioning'!K54 -> 20000 | N34: =SUM(O34)/$C34 -> 20000 | O34: ='5.10 Testing & Commissioning'!P54 -> 20000 | Q34: =SUM(R34)/$C34 -> 20000 | R34: ='5.10 Testing & Commissioning'!U54 -> 20000 | T34: =SUM(U34)/$C34 -> 20000 | U34: ='5.10 Testing & Commissioning'!Z54 -> 20000 | W34: =SUM(X34)/$C34 -> 30000 | X34: ='5.10 Testing & Commissioning'!AE54 -> 30000 | Z34: =SUM(AA34)/$C34 -> 27500 | AA34: ='5.10 Testing & Commissioning'!AJ54 -> 27500 | AC34: =SUM(AD34)/$C34 -> 50000 | AD34: ='5.10 Testing & Commissioning'!AO54 -> 50000 | AF34: =SUM(AG34)/$C34 -> 0
A35: 6 | B35: Prefabricated buildings and building units | F35: =SUM(F36:F44) -> 500000 | I35: =SUM(I36:I44) -> 500000 | L35: =SUM(L36:L44) -> 500000 | O35: =SUM(O36:O44) -> 500000 | R35: =SUM(R36:R44) -> 1283358 | S35: =T35/'Project Information - 1'!$G$3 -> #DIV/0! | U35: =SUM(U36:U44) -> 1283358 | X35: =SUM(X36:X44) -> 1433358 | AA35: =SUM(AA36:AA44) -> 1395858 | AD35: =SUM(AD36:AD44) -> 1733358 | AG35: =SUM(AG36:AG44) -> 0 | AJ35: =SUM(AJ36:AJ44) -> 0
A36: 6.1 | B36: Prefabricated buildings and building units | C36: ='Project Information - 3'!$C$28 -> 1000 | D36: m2 | E36: =SUM(F36)/$C36 -> 20 | F36: ='6.1 Prefab buildings & units'!F54 -> 20000 | H36: =SUM(I36)/$C36 -> 20 | I36: =AVERAGE(L36,O36,R36) -> 20000 | K36: =SUM(L36)/$C36 -> 20 | L36: ='6.1 Prefab buildings & units'!K54 -> 20000 | N36: =SUM(O36)/$C36 -> 20 | O36: ='6.1 Prefab buildings & units'!P54 -> 20000 | Q36: =SUM(R36)/$C36 -> 20 | R36: ='6.1 Prefab buildings & units'!U54 -> 20000 | T36: =SUM(U36)/$C36 -> 20 | U36: ='6.1 Prefab buildings & units'!Z54 -> 20000 | W36: =SUM(X36)/$C36 -> 30 | X36: ='6.1 Prefab buildings & units'!AE54 -> 30000 | Z36: =SUM(AA36)/$C36 -> 27.5 | AA36: ='6.1 Prefab buildings & units'!AJ54 -> 27500 | AC36: =SUM(AD36)/$C36 -> 50 | AD36: ='6.1 Prefab buildings & units'!AO54 -> 50000 | AF36: =SUM(AG36)/$C36 -> 0
A37: 7 | B37: Work to existing buildings | F37: =SUM(F38:F46) -> 260000 | I37: =SUM(I38:I46) -> 260000 | L37: =SUM(L38:L46) -> 260000 | O37: =SUM(O38:O46) -> 260000 | R37: =SUM(R38:R46) -> 651679 | U37: =SUM(U38:U46) -> 651679 | X37: =SUM(X38:X46) -> 731679 | AA37: =SUM(AA38:AA46) -> 711679 | AD37: =SUM(AD38:AD46) -> 891679 | AG37: =SUM(AG38:AG46) -> 0 | AJ37: =SUM(AJ38:AJ46) -> 0
A38: 7.1 | B38: Minor demolition and alteration works | C38: ='Project Information - 3'!$C$29 -> 1000 | D38: m2 | E38: =SUM(F38)/$C38 -> 20 | F38: ='7.1 Minor demolition'!F54 -> 20000 | H38: =SUM(I38)/$C38 -> 20 | I38: =AVERAGE(L38,O38,R38) -> 20000 | K38: =SUM(L38)/$C38 -> 20 | L38: ='7.1 Minor demolition'!K54 -> 20000 | N38: =SUM(O38)/$C38 -> 20 | O38: ='7.1 Minor demolition'!P54 -> 20000 | Q38: =SUM(R38)/$C38 -> 20 | R38: ='7.1 Minor demolition'!U54 -> 20000 | T38: =SUM(U38)/$C38 -> 20 | U38: ='7.1 Minor demolition'!Z54 -> 20000 | W38: =SUM(X38)/$C38 -> 30 | X38: ='7.1 Minor demolition'!AE54 -> 30000 | Z38: =SUM(AA38)/$C38 -> 27.5 | AA38: ='7.1 Minor demolition'!AJ54 -> 27500 | AC38: =SUM(AD38)/$C38 -> 50 | AD38: ='7.1 Minor demolition'!AO54 -> 50000 | AF38: =SUM(AG38)/$C38 -> 0
A39: 7.2 | B39: repairs to existing services | C39: ='Project Information - 3'!$C$30 -> 1000 | D39: m2 | E39: =SUM(F39)/$C39 -> 20 | F39: ='7.2 Repairs to existing'!F54 -> 20000 | H39: =SUM(I39)/$C39 -> 20 | I39: =AVERAGE(L39,O39,R39) -> 20000 | K39: =SUM(L39)/$C39 -> 20 | L39: ='7.2 Repairs to existing'!K54 -> 20000 | N39: =SUM(O39)/$C39 -> 20 | O39: ='7.2 Repairs to existing'!P54 -> 20000 | Q39: =SUM(R39)/$C39 -> 20 | R39: ='7.2 Repairs to existing'!U54 -> 20000 | T39: =SUM(U39)/$C39 -> 20 | U39: ='7.2 Repairs to existing'!Z54 -> 20000 | W39: =SUM(X39)/$C39 -> 30 | X39: ='7.2 Repairs to existing'!AE54 -> 30000 | Z39: =SUM(AA39)/$C39 -> 27.5 | AA39: ='7.2 Repairs to existing'!AJ54 -> 27500 | AC39: =SUM(AD39)/$C39 -> 50 | AD39: ='7.2 Repairs to existing'!AO54 -> 50000 | AF39: =SUM(AG39)/$C39 -> 0
A40: 7.3 | B40: Damp proof courses / fungus and beetle eradication | C40: ='Project Information - 3'!$C$31 -> 1000 | D40: m2 | E40: =SUM(F40)/$C40 -> 20 | F40: ='7.3 Damp proof courses'!F54 -> 20000 | H40: =SUM(I40)/$C40 -> 20 | I40: =AVERAGE(L40,O40,R40) -> 20000 | K40: =SUM(L40)/$C40 -> 20 | L40: ='7.3 Damp proof courses'!K54 -> 20000 | N40: =SUM(O40)/$C40 -> 20 | O40: ='7.3 Damp proof courses'!P54 -> 20000 | Q40: =SUM(R40)/$C40 -> 20 | R40: ='7.3 Damp proof courses'!U54 -> 20000 | T40: =SUM(U40)/$C40 -> 20 | U40: ='7.3 Damp proof courses'!Z54 -> 20000 | W40: =SUM(X40)/$C40 -> 30 | X40: ='7.3 Damp proof courses'!AE54 -> 30000 | Z40: =SUM(AA40)/$C40 -> 27.5 | AA40: ='7.3 Damp proof courses'!AJ54 -> 27500 | AC40: =SUM(AD40)/$C40 -> 50 | AD40: ='7.3 Damp proof courses'!AO54 -> 50000 | AF40: =SUM(AG40)/$C40 -> 0
A41: 7.4 | B41: Façade retention | C41: ='Project Information - 3'!$C$32 -> 1000 | D41: m2 | E41: =SUM(F41)/$C41 -> 20 | F41: ='7.4 Facade retention'!F54 -> 20000 | H41: =SUM(I41)/$C41 -> 20 | I41: =AVERAGE(L41,O41,R41) -> 20000 | K41: =SUM(L41)/$C41 -> 20 | L41: ='7.4 Facade retention'!K54 -> 20000 | N41: =SUM(O41)/$C41 -> 20 | O41: ='7.4 Facade retention'!P54 -> 20000 | Q41: =SUM(R41)/$C41 -> 20 | R41: ='7.4 Facade retention'!U54 -> 20000 | T41: =SUM(U41)/$C41 -> 20 | U41: ='7.4 Facade retention'!Z54 -> 20000 | W41: =SUM(X41)/$C41 -> 30 | X41: ='7.4 Facade retention'!AE54 -> 30000 | Z41: =SUM(AA41)/$C41 -> 27.5 | AA41: ='7.4 Facade retention'!AJ54 -> 27500 | AC41: =SUM(AD41)/$C41 -> 50 | AD41: ='7.4 Facade retention'!AO54 -> 50000 | AF41: =SUM(AG41)/$C41 -> 0
A42: 7.5 | B42: Cleaning existing surfaces | C42: ='Project Information - 3'!$C$33 -> 1000 | D42: m2 | E42: =SUM(F42)/$C42 -> 20 | F42: ='7.5 Cleaning existing surfaces'!F54 -> 20000 | H42: =SUM(I42)/$C42 -> 20 | I42: =AVERAGE(L42,O42,R42) -> 20000 | K42: =SUM(L42)/$C42 -> 20 | L42: ='7.5 Cleaning existing surfaces'!K54 -> 20000 | N42: =SUM(O42)/$C42 -> 20 | O42: ='7.5 Cleaning existing surfaces'!P54 -> 20000 | Q42: =SUM(R42)/$C42 -> 20 | R42: ='7.5 Cleaning existing surfaces'!U54 -> 20000 | T42: =SUM(U42)/$C42 -> 20 | U42: ='7.5 Cleaning existing surfaces'!Z54 -> 20000 | W42: =SUM(X42)/$C42 -> 30 | X42: ='7.5 Cleaning existing surfaces'!AE54 -> 30000 | Z42: =SUM(AA42)/$C42 -> 27.5 | AA42: ='7.5 Cleaning existing surfaces'!AJ54 -> 27500 | AC42: =SUM(AD42)/$C42 -> 50 | AD42: ='7.5 Cleaning existing surfaces'!AO54 -> 50000 | AF42: =SUM(AG42)/$C42 -> 0
A43: 7.6 | B43: Renovation works | C43: ='Project Information - 3'!$C$34 -> 1000 | D43: m2 | E43: =SUM(F43)/$C43 -> 20 | F43: ='7.6 Renovation works'!F54 -> 20000 | H43: =SUM(I43)/$C43 -> 20 | I43: =AVERAGE(L43,O43,R43) -> 20000 | K43: =SUM(L43)/$C43 -> 20 | L43: ='7.6 Renovation works'!K54 -> 20000 | N43: =SUM(O43)/$C43 -> 20 | O43: ='7.6 Renovation works'!P54 -> 20000 | Q43: =SUM(R43)/$C43 -> 20 | R43: ='7.6 Renovation works'!U54 -> 20000 | T43: =SUM(U43)/$C43 -> 20 | U43: ='7.6 Renovation works'!Z54 -> 20000 | W43: =SUM(X43)/$C43 -> 30 | X43: ='7.6 Renovation works'!AE54 -> 30000 | Z43: =SUM(AA43)/$C43 -> 27.5 | AA43: ='7.6 Renovation works'!AJ54 -> 27500 | AC43: =SUM(AD43)/$C43 -> 50 | AD43: ='7.6 Renovation works'!AO54 -> 50000 | AF43: =SUM(AG43)/$C43 -> 0
A44: 8 | B44: External Works | F44: =SUBTOTAL(9,F45:F49) -> 100000 | I44: =SUBTOTAL(9,I45:I49) -> 100000 | L44: =SUBTOTAL(9,L45:L49) -> 100000 | O44: =SUBTOTAL(9,O45:O49) -> 100000 | R44: 491679 | U44: 491679 | X44: 491679 | AA44: 491679 | AD44: 491679 | AG44: =SUBTOTAL(9,AG45:AG49) -> 0 | AJ44: =SUBTOTAL(9,AJ45:AJ49) -> 0
A45: 8.1 | B45: Site preparation works | C45: ='Project Information - 3'!$C$35 -> 1000 | D45: m2 | E45: =SUM(F45)/$C45 -> 20 | F45: ='8.1 Site preparation works'!F54 -> 20000 | H45: =SUM(I45)/$C45 -> 20 | I45: =AVERAGE(L45,O45,R45) -> 20000 | K45: =SUM(L45)/$C45 -> 20 | L45: ='8.1 Site preparation works'!K54 -> 20000 | N45: =SUM(O45)/$C45 -> 20 | O45: ='8.1 Site preparation works'!P54 -> 20000 | Q45: =SUM(R45)/$C45 -> 20 | R45: ='8.1 Site preparation works'!U54 -> 20000 | T45: =SUM(U45)/$C45 -> 20 | U45: ='8.1 Site preparation works'!Z54 -> 20000 | W45: =SUM(X45)/$C45 -> 30 | X45: ='8.1 Site preparation works'!AE54 -> 30000 | Z45: =SUM(AA45)/$C45 -> 27.5 | AA45: ='8.1 Site preparation works'!AJ54 -> 27500 | AC45: =SUM(AD45)/$C45 -> 50 | AD45: ='8.1 Site preparation works'!AO54 -> 50000 | AF45: =SUM(AG45)/$C45 -> 0
A46: 8.2 | B46: Roads, paths, pavings and surfacings | C46: ='Project Information - 3'!$C$36 -> 1000 | D46: m2 | E46: =SUM(F46)/$C46 -> 20 | F46: ='8.2 Roads paths pavings'!F54 -> 20000 | H46: =SUM(I46)/$C46 -> 20 | I46: =AVERAGE(L46,O46,R46) -> 20000 | K46: =SUM(L46)/$C46 -> 20 | L46: ='8.2 Roads paths pavings'!K54 -> 20000 | N46: =SUM(O46)/$C46 -> 20 | O46: ='8.2 Roads paths pavings'!P54 -> 20000 | Q46: =SUM(R46)/$C46 -> 20 | R46: ='8.2 Roads paths pavings'!U54 -> 20000 | T46: =SUM(U46)/$C46 -> 20 | U46: ='8.2 Roads paths pavings'!Z54 -> 20000 | W46: =SUM(X46)/$C46 -> 30 | X46: ='8.2 Roads paths pavings'!AE54 -> 30000 | Z46: =SUM(AA46)/$C46 -> 27.5 | AA46: ='8.2 Roads paths pavings'!AJ54 -> 27500 | AC46: =SUM(AD46)/$C46 -> 50 | AD46: ='8.2 Roads paths pavings'!AO54 -> 50000 | AF46: =SUM(AG46)/$C46 -> 0
A47: 8.3 | B47: Soft landscapes, planting and irrigation systems | C47: ='Project Information - 3'!$C$37 -> 1000 | D47: m2 | E47: =SUM(F47)/$C47 -> 20 | F47: ='8.3 Soft landscapes planting'!F54 -> 20000 | H47: =SUM(I47)/$C47 -> 20 | I47: =AVERAGE(L47,O47,R47) -> 20000 | K47: =SUM(L47)/$C47 -> 20 | L47: ='8.3 Soft landscapes planting'!K54 -> 20000 | N47: =SUM(O47)/$C47 -> 20 | O47: ='8.3 Soft landscapes planting'!P54 -> 20000 | Q47: =SUM(R47)/$C47 -> 20 | R47: ='8.3 Soft landscapes planting'!U54 -> 20000 | T47: =SUM(U47)/$C47 -> 20 | U47: ='8.3 Soft landscapes planting'!Z54 -> 20000 | W47: =SUM(X47)/$C47 -> 30 | X47: ='8.3 Soft landscapes planting'!AE54 -> 30000 | Z47: =SUM(AA47)/$C47 -> 27.5 | AA47: ='8.3 Soft landscapes planting'!AJ54 -> 27500 | AC47: =SUM(AD47)/$C47 -> 50 | AD47: ='8.3 Soft landscapes planting'!AO54 -> 50000 | AF47: =SUM(AG47)/$C47 -> 0
A48: 8.4 | B48: Fencing, railings and walls | C48: ='Project Information - 3'!$C$38 -> 1000 | D48: m2 | E48: =SUM(F48)/$C48 -> 20 | F48: ='8.4 Fencing railings & walls'!F54 -> 20000 | H48: =SUM(I48)/$C48 -> 20 | I48: =AVERAGE(L48,O48,R48) -> 20000 | K48: =SUM(L48)/$C48 -> 20 | L48: ='8.4 Fencing railings & walls'!K54 -> 20000 | N48: =SUM(O48)/$C48 -> 20 | O48: ='8.4 Fencing railings & walls'!P54 -> 20000 | Q48: =SUM(R48)/$C48 -> 20 | R48: ='8.4 Fencing railings & walls'!U54 -> 20000 | T48: =SUM(U48)/$C48 -> 20 | U48: ='8.4 Fencing railings & walls'!Z54 -> 20000 | W48: =SUM(X48)/$C48 -> 30 | X48: ='8.4 Fencing railings & walls'!AE54 -> 30000 | Z48: =SUM(AA48)/$C48 -> 27.5 | AA48: ='8.4 Fencing railings & walls'!AJ54 -> 27500 | AC48: =SUM(AD48)/$C48 -> 50 | AD48: ='8.4 Fencing railings & walls'!AO54 -> 50000 | AF48: =SUM(AG48)/$C48 -> 0
A49: 8.5 | B49: External fixtures | C49: ='Project Information - 3'!$C$39 -> 1000 | D49: m2 | E49: =SUM(F49)/$C49 -> 20 | F49: ='8.5 External fixtures'!F54 -> 20000 | H49: =SUM(I49)/$C49 -> 20 | I49: =AVERAGE(L49,O49,R49) -> 20000 | K49: =SUM(L49)/$C49 -> 20 | L49: ='8.5 External fixtures'!K54 -> 20000 | N49: =SUM(O49)/$C49 -> 20 | O49: ='8.5 External fixtures'!P54 -> 20000 | Q49: =SUM(R49)/$C49 -> 20 | R49: ='8.5 External fixtures'!U54 -> 20000 | T49: =SUM(U49)/$C49 -> 20 | U49: ='8.5 External fixtures'!Z54 -> 20000 | W49: =SUM(X49)/$C49 -> 30 | X49: ='8.5 External fixtures'!AE54 -> 30000 | Z49: =SUM(AA49)/$C49 -> 27.5 | AA49: ='8.5 External fixtures'!AJ54 -> 27500 | AC49: =SUM(AD49)/$C49 -> 50 | AD49: ='8.5 External fixtures'!AO54 -> 50000 | AF49: =SUM(AG49)/$C49 -> 0
A50: 8.6 | B50: External drainage | C50: ='Project Information - 3'!$C$40 -> 1000 | D50: m2 | E50: =SUM(F50)/$C50 -> 20 | F50: ='8.6 External drainage'!F54 -> 20000 | H50: =SUM(I50)/$C50 -> 20 | I50: =AVERAGE(L50,O50,R50) -> 20000 | K50: =SUM(L50)/$C50 -> 20 | L50: ='8.6 External drainage'!K54 -> 20000 | N50: =SUM(O50)/$C50 -> 20 | O50: ='8.6 External drainage'!U54 -> 20000 | Q50: =SUM(R50)/$C50 -> 20 | R50: ='8.6 External drainage'!U54 -> 20000 | T50: =SUM(U50)/$C50 -> 20 | U50: ='8.6 External drainage'!Z54 -> 20000 | W50: =SUM(X50)/$C50 -> 30 | X50: ='8.6 External drainage'!AE54 -> 30000 | Z50: =SUM(AA50)/$C50 -> 27.5 | AA50: ='8.6 External drainage'!AJ54 -> 27500 | AC50: =SUM(AD50)/$C50 -> 50 | AD50: ='8.6 External drainage'!AO54 -> 50000 | AF50: =SUM(AG50)/$C50 -> 0
A51: 8.7 | B51: External services | C51: ='Project Information - 3'!$C$41 -> 1000 | D51: m2 | E51: =SUM(F51)/$C51 -> 20 | F51: ='8.7 External services'!F54 -> 20000 | H51: =SUM(I51)/$C51 -> 20 | I51: =AVERAGE(L51,O51,R51) -> 20000 | K51: =SUM(L51)/$C51 -> 20 | L51: ='8.7 External services'!K54 -> 20000 | N51: =SUM(O51)/$C51 -> 20 | O51: ='8.7 External services'!P54 -> 20000 | Q51: =SUM(R51)/$C51 -> 20 | R51: ='8.7 External services'!U54 -> 20000 | T51: =SUM(U51)/$C51 -> 20 | U51: ='8.7 External services'!Z54 -> 20000 | W51: =SUM(X51)/$C51 -> 30 | X51: ='8.7 External services'!AE54 -> 30000 | Z51: =SUM(AA51)/$C51 -> 27.5 | AA51: ='8.7 External services'!AJ54 -> 27500 | AC51: =SUM(AD51)/$C51 -> 50 | AD51: ='8.7 External services'!AO54 -> 50000 | AF51: =SUM(AG51)/$C51 -> 0
A52: 8.8 | B52: Minor building works and anciliary builidngs | C52: ='Project Information - 3'!$C$42 -> 1000 | D52: m2 | E52: =SUM(F52)/$C52 -> 20 | F52: ='8.8 Minor building & ancillary'!F54 -> 20000 | H52: =SUM(I52)/$C52 -> 20 | I52: =AVERAGE(L52,O52,R52) -> 20000 | K52: =SUM(L52)/$C52 -> 20 | L52: ='8.8 Minor building & ancillary'!K54 -> 20000 | N52: =SUM(O52)/$C52 -> 20 | O52: ='8.8 Minor building & ancillary'!P54 -> 20000 | Q52: =SUM(R52)/$C52 -> 20 | R52: ='8.8 Minor building & ancillary'!U54 -> 20000 | T52: =SUM(U52)/$C52 -> 20 | U52: ='8.8 Minor building & ancillary'!Z54 -> 20000 | W52: =SUM(X52)/$C52 -> 30 | X52: ='8.8 Minor building & ancillary'!AE54 -> 30000 | Z52: =SUM(AA52)/$C52 -> 27.5 | AA52: ='8.8 Minor building & ancillary'!AJ54 -> 27500 | AC52: =SUM(AD52)/$C52 -> 50 | AD52: ='8.8 Minor building & ancillary'!AO54 -> 50000 | AF52: =SUM(AG52)/$C52 -> 0
B54: SUB-TOTAL: MEASURED WORKS | E54: =SUM(F54)/'Project Information - 2'!$B$2 -> 2511.455 | F54: =F5+F7+F9+F18+F24+F44 -> 2513966.5 | H54: =SUM(I54)/'Project Information - 2'!$B$2 -> 2371.1515 | I54: =I5+I7+I9+I18+I24+I44 -> 2373522.7 | K54: =SUM(L54)/'Project Information - 2'!$B$2 -> 2438.2602 | L54: =L5+L7+L9+L18+L24+L44 -> 2440698.5 | N54: =SUM(O54)/'Project Information - 2'!$B$2 -> 2396.04 | O54: =O5+O7+O9+O18+O24+O44 -> 2398436 | Q54: =SUM(R54)/'Project Information - 2'!$B$2 -> 3053.3082 | R54: =R5+R7+R9+R18+R24+R44 -> 3056361.5 | T54: =SUM(U54)/'Project Information - 2'!$B$2 -> 1180.6289 | U54: =U5+U7+U9+U18+U24+U44 -> 1181809.5 | W54: =SUM(X54)/'Project Information - 2'!$B$2 -> 982.37562 | X54: =X5+X7+X9+X18+X24+X44 -> 983358 | Z54: =SUM(AA54)/'Project Information - 2'!$B$2 -> 982.37562 | AA54: =AA5+AA7+AA9+AA18+AA24+AA44 -> 983358 | AC54: =SUM(AD54)/'Project Information - 2'!$B$2 -> 982.37562 | AD54: =AD5+AD7+AD9+AD18+AD24+AD44 -> 983358 | AF54: =SUM(AG54)/'Project Information - 2'!$B$2 -> 0 | AG54: =AG5+AG7+AG9+AG18+AG24+AG44 -> 0 | AI54: =SUM(AJ54)/'Project Information - 2'!$B$2 -> 0 | AJ54: =AJ5+AJ7+AJ9+AJ18+AJ24+AJ44 -> 0
A55: 9 | B55: Main contractor's preliminaries | E55: =F55/F54 -> 0.0079555555 | F55: ='9.0 Contractor''s preliminaries'!F54 -> 20000 | H55: =I55/I54 -> 0.0084262941 | I55: =AVERAGE(L55,O55,R55) -> 20000 | K55: =L55/L54 -> 0.0081943755 | L55: ='9.0 Contractor''s preliminaries'!K54 -> 20000 | N55: =O55/O54 -> 0.0083387674 | O55: ='9.0 Contractor''s preliminaries'!P54 -> 20000 | Q55: =R55/R54 -> 0.0065437285 | R55: ='10.0 Contractor''s overheads'!U54 -> 20000 | T55: =U55/U54 -> 0.016923201 | U55: ='9.0 Contractor''s preliminaries'!Z54 -> 20000 | W55: =X55/X54 -> 0.030507709 | X55: ='9.0 Contractor''s preliminaries'!AE54 -> 30000 | Z55: =AA55/AA54 -> 0.0279654 | AA55: ='9.0 Contractor''s preliminaries'!AJ54 -> 27500 | AC55: =AD55/AD54 -> 0.050846182 | AD55: ='9.0 Contractor''s preliminaries'!AO54 -> 50000 | AF55: =AG55/AG54 -> #DIV/0! | AG55: =5273075.5+342469.52+20000+120000-12000 -> 5743545 | AI55: =AJ55/AJ54 -> #DIV/0! | AJ55: =3749000+287000 -> 4036000
A56: 10 | B56: Main contractor's overheads & profit | E56: =F56/$F$54 -> 0.0079555555 | F56: ='10.0 Contractor''s overheads'!F54 -> 20000 | H56: =I56/$F$54 -> 0.0079555555 | I56: =AVERAGE(L56,O56,R56) -> 20000 | K56: =L56/$F$54 -> 0.0079555555 | L56: ='10.0 Contractor''s overheads'!K54 -> 20000 | N56: =O56/$F$54 -> 0.0079555555 | O56: ='10.0 Contractor''s overheads'!P54 -> 20000 | Q56: =R56/$F$54 -> 0.0079555555 | R56: ='10.0 Contractor''s overheads'!U54 -> 20000 | T56: =U56/$F$54 -> 0.0079555555 | U56: ='10.0 Contractor''s overheads'!Z54 -> 20000 | W56: =X56/$F$54 -> 0.011933333 | X56: ='10.0 Contractor''s overheads'!AE54 -> 30000 | Z56: =AA56/$F$54 -> 0.010938889 | AA56: ='10.0 Contractor''s overheads'!AJ54 -> 27500 | AC56: =AD56/$F$54 -> 0.019888889 | AD56: ='10.0 Contractor''s overheads'!AO54 -> 50000 | AF56: =AG56/$F$54 -> 0.83833995 | AG56: 2107558.5 | AI56: =AJ56/$F$54 -> 0.52745333 | AJ56: 1326000 | AL56: =AG56/SUM(AG54:AG55) -> 0.36694385
B58: SUB-TOTAL: BUILDING WORKS ESTIMATE | E58: =SUM(F58)/'Project Information - 2'!$B$2 -> 2551.4151 | F58: =SUM(F54:F56) -> 2553966.5 | H58: =SUM(I58)/'Project Information - 2'!$B$2 -> 2411.1116 | I58: =SUM(I54:I56) -> 2413522.7 | K58: =SUM(L58)/'Project Information - 2'!$B$2 -> 2478.2203 | L58: =SUM(L54:L56) -> 2480698.5 | N58: =SUM(O58)/'Project Information - 2'!$B$2 -> 2436 | O58: =SUM(O54:O56) -> 2438436 | Q58: =SUM(R58)/'Project Information - 2'!$B$2 -> 3093.2682 | R58: =SUM(R54:R56) -> 3096361.5 | T58: =SUM(U58)/'Project Information - 2'!$B$2 -> 1220.5889 | U58: =SUM(U54:U56) -> 1221809.5 | W58: =SUM(X58)/'Project Information - 2'!$B$2 -> 1042.3157 | X58: =SUM(X54:X56) -> 1043358 | Z58: =SUM(AA58)/'Project Information - 2'!$B$2 -> 1037.3207 | AA58: =SUM(AA54:AA56) -> 1038358 | AC58: =SUM(AD58)/'Project Information - 2'!$B$2 -> 1082.2757 | AD58: =SUM(AD54:AD56) -> 1083358 | AF58: =SUM(AG58)/'Project Information - 2'!$B$2 -> 7843.2603 | AG58: =SUM(AG54:AG56) -> 7851103.6 | AI58: =SUM(AJ58)/'Project Information - 2'!$B$2 -> 5356.6434 | AJ58: =SUM(AJ54:AJ56) -> 5362000
A59: 11 | B59: Project / design team fees
A60: 11.1 | B60: Consultant fees | E60: =F60/F$58 -> 0.19577391 | F60: ='11.1 Consultant fees'!F54 -> 500000 | H60: =I60/I58 -> 0.0082866427 | I60: =AVERAGE(L60,O60,R60) -> 20000 | K60: =L60/$L$58 -> 0.0080622454 | L60: ='11.1 Consultant fees'!K54 -> 20000 | N60: =O60/$L$58 -> 0.0080622454 | O60: ='11.1 Consultant fees'!P54 -> 20000 | Q60: =R60/$L$58 -> 0.0080622454 | R60: ='11.1 Consultant fees'!U54 -> 20000 | T60: =U60/$L$58 -> 0.0080622454 | U60: ='11.1 Consultant fees'!Z54 -> 20000 | W60: =X60/$L$58 -> 0.012093368 | X60: ='11.1 Consultant fees'!AE54 -> 30000 | Z60: =AA60/$L$58 -> 0.011085587 | AA60: ='11.1 Consultant fees'!AJ54 -> 27500 | AC60: =AD60/$L$58 -> 0.020155613 | AD60: ='11.1 Consultant fees'!AO54 -> 50000 | AF60: =AG60/$L$58 -> 0 | AI60: =AJ60/$L$58 -> 0
A61: 11.2 | B61: Main contrator's pre-construction fees | E61: =F61/F$58 -> 0.0078309563 | F61: ='11.2 Contractor''s pre-con fees'!F54 -> 20000 | H61: =I61/I58 -> 0.0082866427 | I61: =AVERAGE(L61,O61,R61) -> 20000 | K61: =L61/$L$58 -> 0.0080622454 | L61: ='11.2 Contractor''s pre-con fees'!K54 -> 20000 | N61: =O61/$L$58 -> 0.0080622454 | O61: ='11.2 Contractor''s pre-con fees'!P54 -> 20000 | Q61: =R61/$L$58 -> 0.0080622454 | R61: ='11.2 Contractor''s pre-con fees'!U54 -> 20000 | T61: =U61/$L$58 -> 0.0080622454 | U61: ='11.2 Contractor''s pre-con fees'!Z54 -> 20000 | W61: =X61/$L$58 -> 0.012093368 | X61: ='11.2 Contractor''s pre-con fees'!AE54 -> 30000 | Z61: =AA61/$L$58 -> 0.011085587 | AA61: ='11.2 Contractor''s pre-con fees'!AJ54 -> 27500 | AC61: =AD61/$L$58 -> 0.020155613 | AD61: ='11.2 Contractor''s pre-con fees'!AO54 -> 50000 | AF61: =AG61/$L$58 -> 0 | AI61: =AJ61/$L$58 -> 0
A62: 11.3 | B62: Main contrator's design fees | E62: =F62/F$58 -> 0.0078309563 | F62: ='11.3 Contractor''s design fees'!F54 -> 20000 | H62: =I62/I58 -> 0.0082866427 | I62: =AVERAGE(L62,O62,R62) -> 20000 | K62: =L62/$L$58 -> 0.0080622454 | L62: ='11.3 Contractor''s design fees'!K54 -> 20000 | N62: =O62/$L$58 -> 0.0080622454 | O62: ='11.3 Contractor''s design fees'!P54 -> 20000 | Q62: =R62/$L$58 -> 0.0080622454 | R62: ='11.3 Contractor''s design fees'!U54 -> 20000 | T62: =U62/$L$58 -> 0.0080622454 | U62: ='11.3 Contractor''s design fees'!Z54 -> 20000 | W62: =X62/$L$58 -> 0.012093368 | X62: ='11.3 Contractor''s design fees'!AE54 -> 30000 | Z62: =AA62/$L$58 -> 0.011085587 | AA62: ='11.3 Contractor''s design fees'!AJ54 -> 27500 | AC62: =AD62/$L$58 -> 0.020155613 | AD62: ='11.3 Contractor''s design fees'!AO54 -> 50000 | AF62: =AG62/$L$58 -> 0 | AI62: =AJ62/$L$58 -> 0
A63: 12 | B63: Other development costs | C63: Excluded from Comparison
B65: SUB-TOTAL: BUILDING WORKS ESTIMATE | E65: =SUM(F65)/'Project Information - 2'!$B$2 -> 539.46054 | F65: =SUM(F60:F62) -> 540000 | H65: =SUM(I65)/'Project Information - 2'!$B$2 -> 59.94006 | I65: =SUM(I60:I62) -> 60000 | K65: =SUM(L65)/'Project Information - 2'!$B$2 -> 59.94006 | L65: =SUM(L60:L62) -> 60000 | N65: =SUM(O65)/'Project Information - 2'!$B$2 -> 59.94006 | O65: =SUM(O60:O62) -> 60000 | Q65: =SUM(R65)/'Project Information - 2'!$B$2 -> 59.94006 | R65: =SUM(R60:R62) -> 60000 | T65: =SUM(U65)/'Project Information - 2'!$B$2 -> 59.94006 | U65: =SUM(U60:U62) -> 60000 | W65: =SUM(X65)/'Project Information - 2'!$B$2 -> 89.91009 | X65: =SUM(X60:X62) -> 90000 | Z65: =SUM(AA65)/'Project Information - 2'!$B$2 -> 82.417582 | AA65: =SUM(AA60:AA62) -> 82500 | AC65: =SUM(AD65)/'Project Information - 2'!$B$2 -> 149.85015 | AD65: =SUM(AD60:AD62) -> 150000 | AF65: =SUM(AG65)/'Project Information - 2'!$B$2 -> 0 | AG65: =SUM(AG60:AG62) -> 0 | AI65: =SUM(AJ65)/'Project Information - 2'!$B$2 -> 0 | AJ65: =SUM(AJ60:AJ62) -> 0
A66: 13 | B66: Risks
A67: 13.1 | B67: Design development risks | E67: =F67/F58 -> 0.0078309563 | F67: ='13.1 Design development risks'!F54 -> 20000 | H67: =I67/I65 -> 0.33333333 | I67: =AVERAGE(L67,O67,R67) -> 20000 | K67: =L67/L58 -> 0.0080622454 | L67: ='13.1 Design development risks'!K54 -> 20000 | N67: =O67/O58 -> 0.0082019786 | O67: ='13.1 Design development risks'!P54 -> 20000 | Q67: =R67/R58 -> 0.0064591941 | R67: ='13.1 Design development risks'!U54 -> 20000 | T67: =U67/U58 -> 0.016369164 | U67: ='13.1 Design development risks'!Z54 -> 20000 | W67: =X67/X58 -> 0.028753314 | X67: ='13.1 Design development risks'!AE54 -> 30000 | Z67: =AA67/AA58 -> 0.026484122 | AA67: ='13.1 Design development risks'!AJ54 -> 27500 | AC67: =AD67/AD58 -> 0.046152795 | AD67: ='13.1 Design development risks'!AO54 -> 50000 | AF67: =AG67/AG58 -> 0.045308535 | AG67: 355722 | AI67: =AJ67/AJ58 -> 0.096046251 | AJ67: 515000
A68: 13.2 | B68: Construction risks | E68: =F68/SUM(F58,F67) -> 0.0077701089 | F68: ='13.2 Construction risks'!F54 -> 20000 | H68: =I68/I65 -> 0.33333333 | I68: =AVERAGE(L68,O68,R68) -> 20000 | K68: =L68/SUM(L58,L67) -> 0.0079977654 | L68: ='13.2 Construction risks'!K54 -> 20000 | N68: =O68/SUM(O58,O67) -> 0.0081352535 | O68: ='13.2 Construction risks'!P54 -> 20000 | Q68: =R68/SUM(R58,R67) -> 0.0064177407 | R68: ='13.2 Construction risks'!U54 -> 20000 | T68: =U68/SUM(U58,U67) -> 0.01610553 | U68: ='13.2 Construction risks'!Z54 -> 20000 | W68: =X68/SUM(X58,X67) -> 0.027949668 | X68: ='13.2 Construction risks'!AE54 -> 30000 | Z68: =AA68/SUM(AA58,AA67) -> 0.02580081 | AA68: ='13.2 Construction risks'!AJ54 -> 27500 | AC68: =AD68/SUM(AD58,AD67) -> 0.044116687 | AD68: ='13.2 Construction risks'!AO54 -> 50000 | AF68: =AG68/SUM(AG58:AG67) -> 0.050278369 | AG68: 412625.8 | AJ68: Excluded
B69: BUILDING WORKS ESTIMATE Including Risk | E69: =SUM(F69)/'Project Information - 2'!$B$2 -> 3670.2962 | F69: =SUM(F58:F68) -> 3673966.5 | H69: =SUM(I69)/'Project Information - 2'!$B$2 -> 2570.9517 | I69: =SUM(I58:I68) -> 2573522.7 | K69: =SUM(L69)/'Project Information - 2'!$B$2 -> 2638.0604 | L69: =SUM(L58:L68) -> 2640698.5 | N69: =SUM(O69)/'Project Information - 2'!$B$2 -> 2595.8402 | O69: =SUM(O58:O68) -> 2598436 | Q69: =SUM(R69)/'Project Information - 2'!$B$2 -> 3253.1084 | R69: =SUM(R58:R68) -> 3256361.5 | T69: =SUM(U69)/'Project Information - 2'!$B$2 -> 1380.4291 | U69: =SUM(U58:U68) -> 1381809.5 | W69: =SUM(X69)/'Project Information - 2'!$B$2 -> 1282.0759 | X69: =SUM(X58:X68) -> 1283358 | Z69: =SUM(AA69)/'Project Information - 2'!$B$2 -> 1257.1009 | AA69: =SUM(AA58:AA68) -> 1258358 | AC69: =SUM(AD69)/'Project Information - 2'!$B$2 -> 1481.8761 | AD69: =SUM(AD58:AD68) -> 1483358 | AF69: =SUM(AG69)/'Project Information - 2'!$B$2 -> 8610.8405 | AG69: =SUM(AG58:AG68) -> 8619451.4 | AI69: =SUM(AJ69)/'Project Information - 2'!$B$2 -> 5871.1289 | AJ69: =SUM(AJ58:AJ68) -> 5877000
A70: 14 | B70: Inflation
A71: 14.1 | B71: Tender Inflation | C71: 1 | D71: item | E71: ='14.1 Tender Inflation'!$C$11/100 -> 0.024390244 | F71: =E71*F69 -> 89608.939 | H71: =SUM(I71)/$C71 -> 69069.073 | I71: =AVERAGE(L71,O71,R71) -> 69069.073 | K71: ='14.1 Tender Inflation'!$C$11/100 -> 0.024390244 | L71: =K71*L69 -> 64407.28 | N71: ='14.1 Tender Inflation'!$C$11/100 -> 0.024390244 | O71: =N71*O69 -> 63376.488 | Q71: ='14.1 Tender Inflation'!$C$11/100 -> 0.024390244 | R71: =Q71*R69 -> 79423.451 | T71: ='14.1 Tender Inflation'!$C$11/100 -> 0.024390244 | U71: =T71*U69 -> 33702.671 | W71: ='14.1 Tender Inflation'!$C$11/100 -> 0.024390244 | X71: =W71*X69 -> 31301.415 | Z71: ='14.1 Tender Inflation'!$C$11/100 -> 0.024390244 | AA71: =Z71*AA69 -> 30691.659 | AC71: ='14.1 Tender Inflation'!$C$11/100 -> 0.024390244 | AD71: =AC71*AD69 -> 36179.463 | AF71: ='14.1 Tender Inflation'!$C$11/100 -> 0.024390244 | AG71: =(AF71/100)*AG69 -> 2102.3052 | AI71: ='14.1 Tender Inflation'!$C$11/100 -> 0.024390244 | AJ71: =(AI71/100)*AJ69 -> 1433.4146
A72: 14.2 | B72: Construction inflation | C72: 1 | D72: item | E72: ='14.2 Construction Inflation'!$C$11/100 -> 0.011904762 | F72: =E72*F69 -> 43737.696 | H72: =SUM(I72)/$C72 -> 33712.286 | I72: =AVERAGE(L72,O72,R72) -> 33712.286 | K72: ='14.2 Construction Inflation'!$C$11/100 -> 0.011904762 | L72: =K72*L69 -> 31436.887 | N72: ='14.2 Construction Inflation'!$C$11/100 -> 0.011904762 | O72: =N72*O69 -> 30933.762 | Q72: ='14.2 Construction Inflation'!$C$11/100 -> 0.011904762 | R72: =Q72*R69 -> 38766.208 | T72: ='14.2 Construction Inflation'!$C$11/100 -> 0.011904762 | U72: =T72*U69 -> 16450.113 | W72: ='14.2 Construction Inflation'!$C$11/100 -> 0.011904762 | X72: =W72*X69 -> 15278.071 | Z72: ='14.2 Construction Inflation'!$C$11/100 -> 0.011904762 | AA72: =Z72*AA69 -> 14980.452 | AC72: ='14.2 Construction Inflation'!$C$11/100 -> 0.011904762 | AD72: =AC72*AD69 -> 17659.024 | AF72: =SUM(AG72)/$C72 -> 539035.3 | AG72: 539035.3 | AI72: =SUM(AJ72)/$C72 -> 432000 | AJ72: =691000-259000 -> 432000
B73: BUILDING WORKS ESTIMATE Including Inflation & Risk | E73: =SUM(F73)/'Project Information - 2'!$B$2 -> 3803.5096 | F73: =SUM(F69:F72) -> 3807313.1 | H73: =SUM(I73)/'Project Information - 2'!$B$2 -> 2639.9518 | I73: =SUM(I69:I71) -> 2642591.7 | K73: =SUM(L73)/'Project Information - 2'!$B$2 -> 2702.4034 | L73: =SUM(L69:L71) -> 2705105.8 | N73: =SUM(O73)/'Project Information - 2'!$B$2 -> 2659.1533 | O73: =SUM(O69:O71) -> 2661812.5 | Q73: =SUM(R73)/'Project Information - 2'!$B$2 -> 3332.4525 | R73: =SUM(R69:R71) -> 3335785 | T73: =SUM(U73)/'Project Information - 2'!$B$2 -> 1414.0981 | U73: =SUM(U69:U71) -> 1415512.2 | W73: =SUM(X73)/'Project Information - 2'!$B$2 -> 1313.3461 | X73: =SUM(X69:X71) -> 1314659.4 | Z73: =SUM(AA73)/'Project Information - 2'!$B$2 -> 1287.7619 | AA73: =SUM(AA69:AA71) -> 1289049.7 | AC73: =SUM(AD73)/'Project Information - 2'!$B$2 -> 1518.0194 | AD73: =SUM(AD69:AD71) -> 1519537.5 | AF73: =SUM(AG73)/'Project Information - 2'!$B$2 -> 8612.9407 | AG73: =SUM(AG69:AG71) -> 8621553.7 | AI73: =SUM(AJ73)/'Project Information - 2'!$B$2 -> 5872.5609 | AJ73: =SUM(AJ69:AJ71) -> 5878433.4
A74: 15 | B74: Adjustments and Equalisations
B75: Adjustments | F75: =Adjustments!G54 -> 8500 | I75: =AVERAGE(L75,O75,R75) -> 0 | L75: =Adjustments!L54 -> 0 | O75: =Adjustments!Q54 -> 0 | R75: =Adjustments!V54 -> 0 | U75: =Adjustments!AA54 -> 0 | X75: =Adjustments!AF54 -> 0 | AA75: =Adjustments!AK54 -> 0 | AD75: =Adjustments!AP54 -> 0
B76: Equalisations
B78: TOTAL: TENDER SUM - Final Adjusted | E78: =SUM(F78)/'Project Information - 2'!$B$2 -> 3812.0011 | F78: =SUM(F73:F77) -> 3815813.1 | H78: =SUM(I78)/'Project Information - 2'!$B$2 -> 2639.9518 | I78: =SUM(I73:I77) -> 2642591.7 | K78: =SUM(L78)/'Project Information - 2'!$B$2 -> 2702.4034 | L78: =SUM(L73:L77) -> 2705105.8 | N78: =SUM(O78)/'Project Information - 2'!$B$2 -> 2659.1533 | O78: =SUM(O73:O77) -> 2661812.5 | Q78: =SUM(R78)/'Project Information - 2'!$B$2 -> 3332.4525 | R78: =SUM(R73:R77) -> 3335785 | T78: =SUM(U78)/'Project Information - 2'!$B$2 -> 1414.0981 | U78: =SUM(U73:U77) -> 1415512.2 | W78: =SUM(X78)/'Project Information - 2'!$B$2 -> 1313.3461 | X78: =SUM(X73:X77) -> 1314659.4 | Z78: =SUM(AA78)/'Project Information - 2'!$B$2 -> 1287.7619 | AA78: =SUM(AA73:AA77) -> 1289049.7 | AC78: =SUM(AD78)/'Project Information - 2'!$B$2 -> 1518.0194 | AD78: =SUM(AD73:AD77) -> 1519537.5 | AF78: =SUM(AG78)/'Project Information - 2'!$B$2 -> 8612.9407 | AG78: =SUM(AG73:AG77) -> 8621553.7 | AI78: =SUM(AJ78)/'Project Information - 2'!$B$2 -> 5872.5609 | AJ78: =SUM(AJ73:AJ77) -> 5878433.4
B79: TOTAL: TENDER SUM - Final Adjusted | E79: =SUM(F79)/'Project Information - 2'!$B$2 -> 3812.1878 | F79: =ROUNDUP(F78,-3) -> 3816000 | H79: =SUM(I79)/'Project Information - 2'!$B$2 -> 2640.3596 | I79: =ROUNDUP(I78,-3) -> 2643000 | K79: =SUM(L79)/'Project Information - 2'!$B$2 -> 2703.2967 | L79: =ROUNDUP(L78,-3) -> 2706000 | N79: =SUM(O79)/'Project Information - 2'!$B$2 -> 2659.3407 | O79: =ROUNDUP(O78,-3) -> 2662000 | Q79: =SUM(R79)/'Project Information - 2'!$B$2 -> 3332.6673 | R79: =ROUNDUP(R78,-3) -> 3336000 | T79: =SUM(U79)/'Project Information - 2'!$B$2 -> 1414.5854 | U79: =ROUNDUP(U78,-3) -> 1416000 | W79: =SUM(X79)/'Project Information - 2'!$B$2 -> 1313.6863 | X79: =ROUNDUP(X78,-3) -> 1315000 | Z79: =SUM(AA79)/'Project Information - 2'!$B$2 -> 1288.7113 | AA79: =ROUNDUP(AA78,-3) -> 1290000 | AC79: =SUM(AD79)/'Project Information - 2'!$B$2 -> 1518.4815 | AD79: =ROUNDUP(AD78,-3) -> 1520000 | AF79: =SUM(AG79)/'Project Information - 2'!$B$2 -> 8613.3866 | AG79: =ROUNDUP(AG78,-3) -> 8622000 | AI79: =SUM(AJ79)/'Project Information - 2'!$B$2 -> 5873.1269 | AJ79: =ROUNDUP(AJ78,-3) -> 5879000
A81: ` | B81: VARIANCE FROM COSTPLAN | I81: =I79-$F$79 -> -1173000 | L81: =L79-$F$79 -> -1110000 | O81: =O79-$F$79 -> -1154000 | R81: =R79-$F$79 -> -480000 | U81: =U79-$F$79 -> -2400000 | X81: =X79-$F$79 -> -2501000 | AA81: =AA79-$F$79 -> -2526000 | AD81: =AD79-$F$79 -> -2296000

Sheet Adjustments
E3: =SUMMARY!E3 -> Sample Cost Plan - Elm Court Residential, Rev 01 | J3: =SUMMARY!K3 -> Ridgeway Construction | O3: =SUMMARY!N3 -> Brightstone Builders | T3: =SUMMARY!Q3 -> Kestrel Contractors | Y3: =SUMMARY!T3 -> INSERT CONTRACTOR 4 | AD3: =SUMMARY!W3 -> INSERT CONTRACTOR 5 | AI3: =SUMMARY!Z3 -> INSERT CONTRACTOR 6 | AN3: =SUMMARY!AC3 -> INSERT CONTRACTOR 7
A4: 3.1 | C4: {=MID(CELL("filename",B3),FIND("]",CELL("filename",B3))+1,255)} -> Adjustments | D4: Qty | E4: Unit | F4: Rate | G4: Total | I4: Qty | J4: Unit | K4: Rate | L4: Total | N4: Qty | O4: Unit | P4: Rate | Q4: Total | S4: Qty | T4: Unit | U4: Rate | V4: Total | X4: Qty | Y4: Unit | Z4: Rate | AA4: Total | AC4: Qty | AD4: Unit | AE4: Rate | AF4: Total | AH4: Qty | AI4: Unit | AJ4: Rate | AK4: Total | AM4: Qty | AN4: Unit | AO4: Rate | AP4: Total
B5: =IF(C5>0,IF(D5>0,MAX($B$3:B4)+1," ")," ") | G5: =IF(ISBLANK(D5),"",D5*F5) | L5: =IF(ISBLANK(I5),"",I5*K5) | Q5: =IF(ISBLANK(N5),"",N5*P5) | V5: =IF(ISBLANK(S5),"",S5*U5) | AA5: =IF(ISBLANK(X5),"",X5*Z5) | AF5: =IF(ISBLANK(AC5),"",AC5*AE5) | AK5: =IF(ISBLANK(AH5),"",AH5*AJ5) | AP5: =IF(ISBLANK(AM5),"",AM5*AO5)
A6: =IF(C6<>"",$A$4,"") -> 3.1 | B6: =IF(C6>0,IF(D6>0,MAX($B$3:B5)+1," ")," ") | C6: =C4 -> Adjustments | G6: =IF(ISBLANK(D6),"",D6*F6) | L6: =IF(ISBLANK(I6),"",I6*K6) | Q6: =IF(ISBLANK(N6),"",N6*P6) | V6: =IF(ISBLANK(S6),"",S6*U6) | AA6: =IF(ISBLANK(X6),"",X6*Z6) | AF6: =IF(ISBLANK(AC6),"",AC6*AE6) | AK6: =IF(ISBLANK(AH6),"",AH6*AJ6) | AP6: =IF(ISBLANK(AM6),"",AM6*AO6)
A7: =IF(C7<>"",$A$4,"") | B7: =IF(C7>0,IF(D7>0,MAX($B$3:B6)+1," ")," ") | G7: =IF(ISBLANK(D7),"",D7*F7) | L7: =IF(ISBLANK(I7),"",I7*K7) | Q7: =IF(ISBLANK(N7),"",N7*P7) | V7: =IF(ISBLANK(S7),"",S7*U7) | AA7: =IF(ISBLANK(X7),"",X7*Z7) | AF7: =IF(ISBLANK(AC7),"",AC7*AE7) | AK7: =IF(ISBLANK(AH7),"",AH7*AJ7) | AP7: =IF(ISBLANK(AM7),"",AM7*AO7)
A8: =IF(C8<>"",$A$4,"") -> 3.1 | B8: =IF(C8>0,IF(D8>0,MAX($B$5:B7)+1," ")," ") -> 1 | C8: Party wall works allowance | D8: 1 | E8: item | F8: 8500 | G8: =F8*D8 -> 8500 | J8: m2 | K8: 0 | L8: =K8*I8 -> 0 | O8: m2 | P8: 0 | Q8: =P8*N8 -> 0 | T8: m2 | U8: 0 | V8: =U8*S8 -> 0 | Y8: m2 | Z8: 0 | AA8: =Z8*X8 -> 0 | AD8: m2 | AE8: 0 | AF8: =AE8*AC8 -> 0 | AI8: m2 | AJ8: 0 | AK8: =AJ8*AH8 -> 0 | AN8: m2 | AO8: 0 | AP8: =AO8*AM8 -> 0
A9: =IF(C9<>"",$A$4,"")
A10: =IF(C10<>"",$A$4,"") -> 3.1 | B10: =IF(C10>0,IF(D10>0,MAX($B$5:B9)+1," ")," ") | C10: Adjustment 2 | E10: m2 | F10: 0 | G10: =F10*D10 -> 0 | J10: m2 | K10: 0 | L10: =K10*I10 -> 0 | O10: m2 | P10: 0 | Q10: =P10*N10 -> 0 | T10: m2 | U10: 0 | V10: =U10*S10 -> 0 | Y10: m2 | Z10: 0 | AA10: =Z10*X10 -> 0 | AD10: m2 | AE10: 0 | AF10: =AE10*AC10 -> 0 | AI10: m2 | AJ10: 0 | AK10: =AJ10*AH10 -> 0 | AN10: m2 | AO10: 0 | AP10: =AO10*AM10 -> 0
A11: =IF(C11<>"",$A$4,"")
A12: =IF(C12<>"",$A$4,"") -> 3.1 | B12: =IF(C12>0,IF(D12>0,MAX($B$5:B11)+1," ")," ") | C12: Adjustment 3 | E12: m2 | F12: 0 | G12: =F12*D12 -> 0 | J12: m2 | K12: 0 | L12: =K12*I12 -> 0 | O12: m2 | P12: 0 | Q12: =P12*N12 -> 0 | T12: m2 | U12: 0 | V12: =U12*S12 -> 0 | Y12: m2 | Z12: 0 | AA12: =Z12*X12 -> 0 | AD12: m2 | AE12: 0 | AF12: =AE12*AC12 -> 0 | AI12: m2 | AJ12: 0 | AK12: =AJ12*AH12 -> 0 | AN12: m2 | AO12: 0 | AP12: =AO12*AM12 -> 0
A13: =IF(C13<>"",$A$4,"")
A14: =IF(C14<>"",$A$4,"") -> 3.1 | B14: =IF(C14>0,IF(D14>0,MAX($B$5:B13)+1," ")," ") | C14: Adjustment 4 | E14: m2 | F14: 0 | G14: =F14*D14 -> 0 | J14: m2 | K14: 0 | L14: =K14*I14 -> 0 | O14: m2 | P14: 0 | Q14: =P14*N14 -> 0 | T14: m2 | U14: 0 | V14: =U14*S14 -> 0 | Y14: m2 | Z14: 0 | AA14: =Z14*X14 -> 0 | AD14: m2 | AE14: 0 | AF14: =AE14*AC14 -> 0 | AI14: m2 | AJ14: 0 | AK14: =AJ14*AH14 -> 0 | AN14: m2 | AO14: 0 | AP14: =AO14*AM14 -> 0
A15: =IF(C15<>"",$A$4,"") | B15: =IF(C15>0,IF(D15>0,MAX($B$3:B14)+1," ")," ") | G15: =IF(ISBLANK(D15),"",D15*F15) | L15: =IF(ISBLANK(I15),"",I15*K15) | Q15: =IF(ISBLANK(N15),"",N15*P15) | V15: =IF(ISBLANK(S15),"",S15*U15) | AA15: =IF(ISBLANK(X15),"",X15*Z15) | AF15: =IF(ISBLANK(AC15),"",AC15*AE15) | AK15: =IF(ISBLANK(AH15),"",AH15*AJ15) | AP15: =IF(ISBLANK(AM15),"",AM15*AO15)
A16: =IF(C16<>"",$A$4,"") -> 3.1 | B16: =IF(C16>0,IF(D16>0,MAX($B$5:B15)+1," ")," ") | C16: Adjustment 1 | E16: m2 | F16: 0 | G16: =F16*D16 -> 0 | J16: m2 | K16: 0 | L16: =K16*I16 -> 0 | O16: m2 | P16: 0 | Q16: =P16*N16 -> 0 | T16: m2 | U16: 0 | V16: =U16*S16 -> 0 | Y16: m2 | Z16: 0 | AA16: =Z16*X16 -> 0 | AD16: m2 | AE16: 0 | AF16: =AE16*AC16 -> 0 | AI16: m2 | AJ16: 0 | AK16: =AJ16*AH16 -> 0 | AN16: m2 | AO16: 0 | AP16: =AO16*AM16 -> 0
A17: =IF(C17<>"",$A$4,"")
A18: =IF(C18<>"",$A$4,"") -> 3.1 | B18: =IF(C18>0,IF(D18>0,MAX($B$5:B17)+1," ")," ") | C18: Adjustment 2 | E18: m2 | F18: 0 | G18: =F18*D18 -> 0 | J18: m2 | K18: 0 | L18: =K18*I18 -> 0 | O18: m2 | P18: 0 | Q18: =P18*N18 -> 0 | T18: m2 | U18: 0 | V18: =U18*S18 -> 0 | Y18: m2 | Z18: 0 | AA18: =Z18*X18 -> 0 | AD18: m2 | AE18: 0 | AF18: =AE18*AC18 -> 0 | AI18: m2 | AJ18: 0 | AK18: =AJ18*AH18 -> 0 | AN18: m2 | AO18: 0 | AP18: =AO18*AM18 -> 0
A19: =IF(C19<>"",$A$4,"")
A20: =IF(C20<>"",$A$4,"") -> 3.1 | B20: =IF(C20>0,IF(D20>0,MAX($B$5:B19)+1," ")," ") | C20: Adjustment 3 | E20: m2 | F20: 0 | G20: =F20*D20 -> 0 | J20: m2 | K20: 0 | L20: =K20*I20 -> 0 | O20: m2 | P20: 0 | Q20: =P20*N20 -> 0 | T20: m2 | U20: 0 | V20: =U20*S20 -> 0 | Y20: m2 | Z20: 0 | AA20: =Z20*X20 -> 0 | AD20: m2 | AE20: 0 | AF20: =AE20*AC20 -> 0 | AI20: m2 | AJ20: 0 | AK20: =AJ20*AH20 -> 0 | AN20: m2 | AO20: 0 | AP20: =AO20*AM20 -> 0
A21: =IF(C21<>"",$A$4,"")
A22: =IF(C22<>"",$A$4,"") -> 3.1 | B22: =IF(C22>0,IF(D22>0,MAX($B$5:B21)+1," ")," ") | C22: Adjustment 4 | E22: m2 | F22: 0 | G22: =F22*D22 -> 0 | J22: m2 | K22: 0 | L22: =K22*I22 -> 0 | O22: m2 | P22: 0 | Q22: =P22*N22 -> 0 | T22: m2 | U22: 0 | V22: =U22*S22 -> 0 | Y22: m2 | Z22: 0 | AA22: =Z22*X22 -> 0 | AD22: m2 | AE22: 0 | AF22: =AE22*AC22 -> 0 | AI22: m2 | AJ22: 0 | AK22: =AJ22*AH22 -> 0 | AN22: m2 | AO22: 0 | AP22: =AO22*AM22 -> 0
A23: =IF(C23<>"",$A$4,"") | B23: =IF(C23>0,IF(D23>0,MAX($B$3:B22)+1," ")," ") | G23: =IF(ISBLANK(D23),"",D23*F23) | L23: =IF(ISBLANK(I23),"",I23*K23) | Q23: =IF(ISBLANK(N23),"",N23*P23) | V23: =IF(ISBLANK(S23),"",S23*U23) | AA23: =IF(ISBLANK(X23),"",X23*Z23) | AF23: =IF(ISBLANK(AC23),"",AC23*AE23) | AK23: =IF(ISBLANK(AH23),"",AH23*AJ23) | AP23: =IF(ISBLANK(AM23),"",AM23*AO23)
A24: =IF(C24<>"",$A$4,"") -> 3.1 | B24: =IF(C24>0,IF(D24>0,MAX($B$5:B23)+1," ")," ") | C24: Adjustment 1 | E24: m2 | F24: 0 | G24: =F24*D24 -> 0 | J24: m2 | K24: 0 | L24: =K24*I24 -> 0 | O24: m2 | P24: 0 | Q24: =P24*N24 -> 0 | T24: m2 | U24: 0 | V24: =U24*S24 -> 0 | Y24: m2 | Z24: 0 | AA24: =Z24*X24 -> 0 | AD24: m2 | AE24: 0 | AF24: =AE24*AC24 -> 0 | AI24: m2 | AJ24: 0 | AK24: =AJ24*AH24 -> 0 | AN24: m2 | AO24: 0 | AP24: =AO24*AM24 -> 0
A25: =IF(C25<>"",$A$4,"")
A26: =IF(C26<>"",$A$4,"") -> 3.1 | B26: =IF(C26>0,IF(D26>0,MAX($B$5:B25)+1," ")," ") | C26: Adjustment 2 | E26: m2 | F26: 0 | G26: =F26*D26 -> 0 | J26: m2 | K26: 0 | L26: =K26*I26 -> 0 | O26: m2 | P26: 0 | Q26: =P26*N26 -> 0 | T26: m2 | U26: 0 | V26: =U26*S26 -> 0 | Y26: m2 | Z26: 0 | AA26: =Z26*X26 -> 0 | AD26: m2 | AE26: 0 | AF26: =AE26*AC26 -> 0 | AI26: m2 | AJ26: 0 | AK26: =AJ26*AH26 -> 0 | AN26: m2 | AO26: 0 | AP26: =AO26*AM26 -> 0
A27: =IF(C27<>"",$A$4,"")
A28: =IF(C28<>"",$A$4,"") -> 3.1 | B28: =IF(C28>0,IF(D28>0,MAX($B$5:B27)+1," ")," ") | C28: Adjustment 3 | E28: m2 | F28: 0 | G28: =F28*D28 -> 0 | J28: m2 | K28: 0 | L28: =K28*I28 -> 0 | O28: m2 | P28: 0 | Q28: =P28*N28 -> 0 | T28: m2 | U28: 0 | V28: =U28*S28 -> 0 | Y28: m2 | Z28: 0 | AA28: =Z28*X28 -> 0 | AD28: m2 | AE28: 0 | AF28: =AE28*AC28 -> 0 | AI28: m2 | AJ28: 0 | AK28: =AJ28*AH28 -> 0 | AN28: m2 | AO28: 0 | AP28: =AO28*AM28 -> 0
A29: =IF(C29<>"",$A$4,"")
A30: =IF(C30<>"",$A$4,"") -> 3.1 | B30: =IF(C30>0,IF(D30>0,MAX($B$5:B29)+1," ")," ") | C30: Adjustment 4 | E30: m2 | F30: 0 | G30: =F30*D30 -> 0 | J30: m2 | K30: 0 | L30: =K30*I30 -> 0 | O30: m2 | P30: 0 | Q30: =P30*N30 -> 0 | T30: m2 | U30: 0 | V30: =U30*S30 -> 0 | Y30: m2 | Z30: 0 | AA30: =Z30*X30 -> 0 | AD30: m2 | AE30: 0 | AF30: =AE30*AC30 -> 0 | AI30: m2 | AJ30: 0 | AK30: =AJ30*AH30 -> 0 | AN30: m2 | AO30: 0 | AP30: =AO30*AM30 -> 0
A31: =IF(C31<>"",$A$4,"") | B31: =IF(C31>0,IF(D31>0,MAX($B$3:B30)+1," ")," ") | G31: =IF(ISBLANK(D31),"",D31*F31) | L31: =IF(ISBLANK(I31),"",I31*K31) | Q31: =IF(ISBLANK(N31),"",N31*P31) | V31: =IF(ISBLANK(S31),"",S31*U31) | AA31: =IF(ISBLANK(X31),"",X31*Z31) | AF31: =IF(ISBLANK(AC31),"",AC31*AE31) | AK31: =IF(ISBLANK(AH31),"",AH31*AJ31) | AP31: =IF(ISBLANK(AM31),"",AM31*AO31)
A32: =IF(C32<>"",$A$4,"") -> 3.1 | B32: =IF(C32>0,IF(D32>0,MAX($B$5:B31)+1," ")," ") | C32: Adjustment 1 | E32: m2 | F32: 0 | G32: =F32*D32 -> 0 | J32: m2 | K32: 0 | L32: =K32*I32 -> 0 | O32: m2 | P32: 0 | Q32: =P32*N32 -> 0 | T32: m2 | U32: 0 | V32: =U32*S32 -> 0 | Y32: m2 | Z32: 0 | AA32: =Z32*X32 -> 0 | AD32: m2 | AE32: 0 | AF32: =AE32*AC32 -> 0 | AI32: m2 | AJ32: 0 | AK32: =AJ32*AH32 -> 0 | AN32: m2 | AO32: 0 | AP32: =AO32*AM32 -> 0
A33: =IF(C33<>"",$A$4,"")
A34: =IF(C34<>"",$A$4,"") -> 3.1 | B34: =IF(C34>0,IF(D34>0,MAX($B$5:B33)+1," ")," ") | C34: Adjustment 2 | E34: m2 | F34: 0 | G34: =F34*D34 -> 0 | J34: m2 | K34: 0 | L34: =K34*I34 -> 0 | O34: m2 | P34: 0 | Q34: =P34*N34 -> 0 | T34: m2 | U34: 0 | V34: =U34*S34 -> 0 | Y34: m2 | Z34: 0 | AA34: =Z34*X34 -> 0 | AD34: m2 | AE34: 0 | AF34: =AE34*AC34 -> 0 | AI34: m2 | AJ34: 0 | AK34: =AJ34*AH34 -> 0 | AN34: m2 | AO34: 0 | AP34: =AO34*AM34 -> 0
A35: =IF(C35<>"",$A$4,"")
A36: =IF(C36<>"",$A$4,"") -> 3.1 | B36: =IF(C36>0,IF(D36>0,MAX($B$5:B35)+1," ")," ") | C36: Adjustment 3 | E36: m2 | F36: 0 | G36: =F36*D36 -> 0 | J36: m2 | K36: 0 | L36: =K36*I36 -> 0 | O36: m2 | P36: 0 | Q36: =P36*N36 -> 0 | T36: m2 | U36: 0 | V36: =U36*S36 -> 0 | Y36: m2 | Z36: 0 | AA36: =Z36*X36 -> 0 | AD36: m2 | AE36: 0 | AF36: =AE36*AC36 -> 0 | AI36: m2 | AJ36: 0 | AK36: =AJ36*AH36 -> 0 | AN36: m2 | AO36: 0 | AP36: =AO36*AM36 -> 0
A37: =IF(C37<>"",$A$4,"")
A38: =IF(C38<>"",$A$4,"") -> 3.1 | B38: =IF(C38>0,IF(D38>0,MAX($B$5:B37)+1," ")," ") | C38: Adjustment 4 | E38: m2 | F38: 0 | G38: =F38*D38 -> 0 | J38: m2 | K38: 0 | L38: =K38*I38 -> 0 | O38: m2 | P38: 0 | Q38: =P38*N38 -> 0 | T38: m2 | U38: 0 | V38: =U38*S38 -> 0 | Y38: m2 | Z38: 0 | AA38: =Z38*X38 -> 0 | AD38: m2 | AE38: 0 | AF38: =AE38*AC38 -> 0 | AI38: m2 | AJ38: 0 | AK38: =AJ38*AH38 -> 0 | AN38: m2 | AO38: 0 | AP38: =AO38*AM38 -> 0
A39: =IF(C39<>"",$A$4,"") | B39: =IF(C39>0,IF(D39>0,MAX($B$3:B38)+1," ")," ") | G39: =IF(ISBLANK(D39),"",D39*F39) | L39: =IF(ISBLANK(I39),"",I39*K39) | Q39: =IF(ISBLANK(N39),"",N39*P39) | V39: =IF(ISBLANK(S39),"",S39*U39) | AA39: =IF(ISBLANK(X39),"",X39*Z39) | AF39: =IF(ISBLANK(AC39),"",AC39*AE39) | AK39: =IF(ISBLANK(AH39),"",AH39*AJ39) | AP39: =IF(ISBLANK(AM39),"",AM39*AO39)
A40: =IF(C40<>"",$A$4,"") -> 3.1 | B40: =IF(C40>0,IF(D40>0,MAX($B$5:B39)+1," ")," ") | C40: Adjustment 1 | E40: m2 | F40: 0 | G40: =F40*D40 -> 0 | J40: m2 | K40: 0 | L40: =K40*I40 -> 0 | O40: m2 | P40: 0 | Q40: =P40*N40 -> 0 | T40: m2 | U40: 0 | V40: =U40*S40 -> 0 | Y40: m2 | Z40: 0 | AA40: =Z40*X40 -> 0 | AD40: m2 | AE40: 0 | AF40: =AE40*AC40 -> 0 | AI40: m2 | AJ40: 0 | AK40: =AJ40*AH40 -> 0 | AN40: m2 | AO40: 0 | AP40: =AO40*AM40 -> 0
A41: =IF(C41<>"",$A$4,"")
A42: =IF(C42<>"",$A$4,"") -> 3.1 | B42: =IF(C42>0,IF(D42>0,MAX($B$5:B41)+1," ")," ") | C42: Adjustment 2 | E42: m2 | F42: 0 | G42: =F42*D42 -> 0 | J42: m2 | K42: 0 | L42: =K42*I42 -> 0 | O42: m2 | P42: 0 | Q42: =P42*N42 -> 0 | T42: m2 | U42: 0 | V42: =U42*S42 -> 0 | Y42: m2 | Z42: 0 | AA42: =Z42*X42 -> 0 | AD42: m2 | AE42: 0 | AF42: =AE42*AC42 -> 0 | AI42: m2 | AJ42: 0 | AK42: =AJ42*AH42 -> 0 | AN42: m2 | AO42: 0 | AP42: =AO42*AM42 -> 0
A43: =IF(C43<>"",$A$4,"")
A44: =IF(C44<>"",$A$4,"") -> 3.1 | B44: =IF(C44>0,IF(D44>0,MAX($B$5:B43)+1," ")," ") | C44: Adjustment 3 | E44: m2 | F44: 0 | G44: =F44*D44 -> 0 | J44: m2 | K44: 0 | L44: =K44*I44 -> 0 | O44: m2 | P44: 0 | Q44: =P44*N44 -> 0 | T44: m2 | U44: 0 | V44: =U44*S44 -> 0 | Y44: m2 | Z44: 0 | AA44: =Z44*X44 -> 0 | AD44: m2 | AE44: 0 | AF44: =AE44*AC44 -> 0 | AI44: m2 | AJ44: 0 | AK44: =AJ44*AH44 -> 0 | AN44: m2 | AO44: 0 | AP44: =AO44*AM44 -> 0
A45: =IF(C45<>"",$A$4,"")
A46: =IF(C46<>"",$A$4,"") -> 3.1 | B46: =IF(C46>0,IF(D46>0,MAX($B$5:B45)+1," ")," ") | C46: Adjustment 4 | E46: m2 | F46: 0 | G46: =F46*D46 -> 0 | J46: m2 | K46: 0 | L46: =K46*I46 -> 0 | O46: m2 | P46: 0 | Q46: =P46*N46 -> 0 | T46: m2 | U46: 0 | V46: =U46*S46 -> 0 | Y46: m2 | Z46: 0 | AA46: =Z46*X46 -> 0 | AD46: m2 | AE46: 0 | AF46: =AE46*AC46 -> 0 | AI46: m2 | AJ46: 0 | AK46: =AJ46*AH46 -> 0 | AN46: m2 | AO46: 0 | AP46: =AO46*AM46 -> 0
A48: =IF(C48<>"",$A$4,"") -> 3.1 | B48: =IF(C48>0,IF(D48>0,MAX($B$5:B30)+1," ")," ") | C48: Any other works (contractor to specify) | G48: =IF(ISBLANK(D48),"",D48*F48) | L48: =IF(ISBLANK(I48),"",I48*K48) | Q48: =IF(ISBLANK(N48),"",N48*P48) | V48: =IF(ISBLANK(S48),"",S48*U48) | AA48: =IF(ISBLANK(X48),"",X48*Z48) | AF48: =IF(ISBLANK(AC48),"",AC48*AE48) | AK48: =IF(ISBLANK(AH48),"",AH48*AJ48) | AP48: =IF(ISBLANK(AM48),"",AM48*AO48)
A49: =IF(C49<>"",$A$4,"") -> 3.1 | B49: =IF(C49>0,IF(D49>0,MAX($B$5:B48)+1," ")," ") -> 2 | C49: ……………………………………………. | D49: 1 | E49: item | G49: =IF(ISBLANK(D49),"",D49*F49) -> 0 | I49: 1 | J49: item | L49: =IF(ISBLANK(I49),"",I49*K49) -> 0 | N49: 1 | O49: item | Q49: =IF(ISBLANK(N49),"",N49*P49) -> 0 | S49: 1 | T49: item | V49: =IF(ISBLANK(S49),"",S49*U49) -> 0 | X49: 1 | Y49: item | AA49: =IF(ISBLANK(X49),"",X49*Z49) -> 0 | AC49: 1 | AD49: item | AF49: =IF(ISBLANK(AC49),"",AC49*AE49) -> 0 | AH49: 1 | AI49: item | AK49: =IF(ISBLANK(AH49),"",AH49*AJ49) -> 0 | AM49: 1 | AN49: item | AP49: =IF(ISBLANK(AM49),"",AM49*AO49) -> 0
A50: =IF(C50<>"",$A$4,"") -> 3.1 | B50: =IF(C50>0,IF(D50>0,MAX($B$5:B49)+1," ")," ") -> 3 | C50: ……………………………………………. | D50: 1 | E50: Item | G50: =IF(ISBLANK(D50),"",D50*F50) -> 0 | I50: 1 | J50: Item | L50: =IF(ISBLANK(I50),"",I50*K50) -> 0 | N50: 1 | O50: Item | Q50: =IF(ISBLANK(N50),"",N50*P50) -> 0 | S50: 1 | T50: Item | V50: =IF(ISBLANK(S50),"",S50*U50) -> 0 | X50: 1 | Y50: Item | AA50: =IF(ISBLANK(X50),"",X50*Z50) -> 0 | AC50: 1 | AD50: Item | AF50: =IF(ISBLANK(AC50),"",AC50*AE50) -> 0 | AH50: 1 | AI50: Item | AK50: =IF(ISBLANK(AH50),"",AH50*AJ50) -> 0 | AM50: 1 | AN50: Item | AP50: =IF(ISBLANK(AM50),"",AM50*AO50) -> 0
A51: =IF(C51<>"",$A$4,"") -> 3.1 | B51: =IF(C51>0,IF(D51>0,MAX($B$5:B50)+1," ")," ") -> 4 | C51: ……………………………………………. | D51: 1 | E51: Item | G51: =IF(ISBLANK(D51),"",D51*F51) -> 0 | I51: 1 | J51: Item | L51: =IF(ISBLANK(I51),"",I51*K51) -> 0 | N51: 1 | O51: Item | Q51: =IF(ISBLANK(N51),"",N51*P51) -> 0 | S51: 1 | T51: Item | V51: =IF(ISBLANK(S51),"",S51*U51) -> 0 | X51: 1 | Y51: Item | AA51: =IF(ISBLANK(X51),"",X51*Z51) -> 0 | AC51: 1 | AD51: Item | AF51: =IF(ISBLANK(AC51),"",AC51*AE51) -> 0 | AH51: 1 | AI51: Item | AK51: =IF(ISBLANK(AH51),"",AH51*AJ51) -> 0 | AM51: 1 | AN51: Item | AP51: =IF(ISBLANK(AM51),"",AM51*AO51) -> 0
A52: =IF(C52<>"",$A$4,"") -> 3.1 | B52: =IF(C52>0,IF(D52>0,MAX($B$3:B49)+1," ")," ") -> 3 | C52: ……………………………………………. | D52: 1 | E52: Item | G52: =IF(ISBLANK(D52),"",D52*F52) -> 0 | I52: 1 | J52: Item | L52: =IF(ISBLANK(I52),"",I52*K52) -> 0 | N52: 1 | O52: Item | Q52: =IF(ISBLANK(N52),"",N52*P52) -> 0 | S52: 1 | T52: Item | V52: =IF(ISBLANK(S52),"",S52*U52) -> 0 | X52: 1 | Y52: Item | AA52: =IF(ISBLANK(X52),"",X52*Z52) -> 0 | AC52: 1 | AD52: Item | AF52: =IF(ISBLANK(AC52),"",AC52*AE52) -> 0 | AH52: 1 | AI52: Item | AK52: =IF(ISBLANK(AH52),"",AH52*AJ52) -> 0 | AM52: 1 | AN52: Item | AP52: =IF(ISBLANK(AM52),"",AM52*AO52) -> 0
A53: =IF(C53<>"",$A$4,"") | B53: =IF(C53>0,IF(D53>0,MAX($B$3:B30)+1," ")," ") | G53: =IF(ISBLANK(D53),"",D53*F53) | L53: =IF(ISBLANK(I53),"",I53*K53) | Q53: =IF(ISBLANK(N53),"",N53*P53) | V53: =IF(ISBLANK(S53),"",S53*U53) | AA53: =IF(ISBLANK(X53),"",X53*Z53) | AF53: =IF(ISBLANK(AC53),"",AC53*AE53) | AK53: =IF(ISBLANK(AH53),"",AH53*AJ53) | AP53: =IF(ISBLANK(AM53),"",AM53*AO53)
F54: Total | G54: =SUM(G5:G53) -> 8500 | K54: Total | L54: =SUM(L5:L53) -> 0 | P54: Total | Q54: =SUM(Q5:Q53) -> 0 | U54: Total | V54: =SUM(V5:V53) -> 0 | Z54: Total | AA54: =SUM(AA5:AA53) -> 0 | AE54: Total | AF54: =SUM(AF5:AF53) -> 0 | AJ54: Total | AK54: =SUM(AK5:AK53) -> 0 | AO54: Total | AP54: =SUM(AP5:AP53) -> 0

Sheet Frame - Proj 1
A2: Project 01 - Breakdown
B4: Order of Cost Estimate - Rev 00 | D4: Frame
C5: Qty | D5: Unit | E5: Rate | F5: Total
A6: =IF(B6>0,IF(C6>0,MAX($A$3:A5)+1," ")," ") | F6: =IF(ISBLANK(C6),"",C6*E6)
B7: Frame | F7: =IF(ISBLANK(C7),"",C7*E7)
F8: =IF(ISBLANK(C8),"",C8*E8)
A9: =IF(B9>0,IF(C9>0,MAX($A$3:A8)+1," ")," ") -> 1 | B9: Allowance for structural modifications to Glulam beams | C9: 1 | D9: Item | F9: =IF(ISBLANK(C9),"",C9*E9) -> 0
A10: =IF(B10>0,IF(C10>0,MAX($A$3:A9)+1," ")," ") -> 2 | B10: Extra over for varnishing | C10: 1 | D10: item | F10: =IF(ISBLANK(C10),"",C10*E10) -> 0
A11: =IF(B11>0,IF(C11>0,MAX($A$4:A9)+1," ")," ") | F11: =IF(ISBLANK(C11),"",C11*E11)
E12: Total | F12: =SUM(F6:F11) -> 0

Sheet 0.1 Demolition & alterations
B1: Return to ELEMENT INDEX
B2: Return to SUMMARY
C3: =SUMMARY!E3 -> Sample Cost Plan - Elm Court Residential, Rev 01 | H3: =SUMMARY!K3 -> Ridgeway Construction | M3: =SUMMARY!N3 -> Brightstone Builders | R3: =SUMMARY!Q3 -> Kestrel Contractors | W3: =SUMMARY!T3 -> INSERT CONTRACTOR 4 | AB3: =SUMMARY!W3 -> INSERT CONTRACTOR 5 | AG3: =SUMMARY!Z3 -> INSERT CONTRACTOR 6 | AL3: =SUMMARY!AC3 -> INSERT CONTRACTOR 7
B4: {=MID(CELL("filename",A3),FIND("]",CELL("filename",A3))+1,255)} -> 0.1 Demolition & alterations | C4: Qty | D4: Unit | E4: Rate | F4: Total | H4: Qty | I4: Unit | J4: Rate | K4: Total | M4: Qty | N4: Unit | O4: Rate | P4: Total | R4: Qty | S4: Unit | T4: Rate | U4: Total | W4: Qty | X4: Unit | Y4: Rate | Z4: Total | AB4: Qty | AC4: Unit | AD4: Rate | AE4: Total | AG4: Qty | AH4: Unit | AI4: Rate | AJ4: Total | AL4: Qty | AM4: Unit | AN4: Rate | AO4: Total
A5: =IF(B5>0,IF(C5>0,MAX($A$3:A4)+1," ")," ") | F5: =IF(ISBLANK(C5),"",C5*E5) | K5: =IF(ISBLANK(H5),"",H5*J5) | P5: =IF(ISBLANK(M5),"",M5*O5) | U5: =IF(ISBLANK(R5),"",R5*T5) | Z5: =IF(ISBLANK(W5),"",W5*Y5) | AE5: =IF(ISBLANK(AB5),"",AB5*AD5) | AJ5: =IF(ISBLANK(AG5),"",AG5*AI5) | AO5: =IF(ISBLANK(AL5),"",AL5*AN5)
A6: =IF(B6>0,IF(C6>0,MAX($A$3:A5)+1," ")," ") | B6: =B4 -> 0.1 Demolition & alterations | F6: =IF(ISBLANK(C6),"",C6*E6) | K6: =IF(ISBLANK(H6),"",H6*J6) | P6: =IF(ISBLANK(M6),"",M6*O6) | U6: =IF(ISBLANK(R6),"",R6*T6) | Z6: =IF(ISBLANK(W6),"",W6*Y6) | AE6: =IF(ISBLANK(AB6),"",AB6*AD6) | AJ6: =IF(ISBLANK(AG6),"",AG6*AI6) | AO6: =IF(ISBLANK(AL6),"",AL6*AN6)
A7: =IF(B7>0,IF(C7>0,MAX($A$3:A6)+1," ")," ") | F7: =IF(ISBLANK(C7),"",C7*E7) | K7: =IF(ISBLANK(H7),"",H7*J7) | P7: =IF(ISBLANK(M7),"",M7*O7) | U7: =IF(ISBLANK(R7),"",R7*T7) | Z7: =IF(ISBLANK(W7),"",W7*Y7) | AE7: =IF(ISBLANK(AB7),"",AB7*AD7) | AJ7: =IF(ISBLANK(AG7),"",AG7*AI7) | AO7: =IF(ISBLANK(AL7),"",AL7*AN7)
A8: =IF(B8>0,IF(C8>0,MAX($A$5:A7)+1," ")," ") -> 1 | B8: Site Clearance | C8: 1001 | D8: m2 | E8: 1.5 | F8: =IF(ISBLANK(C8),"",C8*E8) -> 1501.5 | H8: 1001 | I8: m2 | J8: 1 | K8: =IF(ISBLANK(H8),"",H8*J8) -> 1001 | M8: 1001 | N8: m2 | O8: 1.5 | P8: =IF(ISBLANK(M8),"",M8*O8) -> 1501.5 | R8: 1001 | S8: m2 | T8: 1.5 | U8: =IF(ISBLANK(R8),"",R8*T8) -> 1501.5 | X8: m2 | Z8: =IF(ISBLANK(W8),"",W8*Y8) | AC8: m2 | AE8: =IF(ISBLANK(AB8),"",AB8*AD8) | AH8: m2 | AJ8: =IF(ISBLANK(AG8),"",AG8*AI8) | AM8: m2 | AO8: =IF(ISBLANK(AL8),"",AL8*AN8)
A9: =IF(B9>0,IF(C9>0,MAX($A$5:A8)+1," ")," ")
A10: =IF(B10>0,IF(C10>0,MAX($A$5:A9)+1," ")," ") -> 2 | B10: Asbestos Removal | C10: 1001 | D10: m2 | E10: 25 | F10: =IF(ISBLANK(C10),"",C10*E10) -> 25025 | H10: 1001 | I10: m2 | J10: 20 | K10: =IF(ISBLANK(H10),"",H10*J10) -> 20020 | M10: 1001 | N10: m2 | O10: 35 | P10: =IF(ISBLANK(M10),"",M10*O10) -> 35035 | R10: 1001 | S10: m2 | T10: 50 | U10: =IF(ISBLANK(R10),"",R10*T10) -> 50050 | X10: m2 | Z10: =IF(ISBLANK(W10),"",W10*Y10) | AC10: m2 | AE10: =IF(ISBLANK(AB10),"",AB10*AD10) | AH10: m2 | AJ10: =IF(ISBLANK(AG10),"",AG10*AI10) | AM10: m2 | AO10: =IF(ISBLANK(AL10),"",AL10*AN10)
A11: =IF(B11>0,IF(C11>0,MAX($A$5:A10)+1," ")," ")
A12: =IF(B12>0,IF(C12>0,MAX($A$5:A11)+1," ")," ") -> 3 | B12: Soft Strip out of the existing building | C12: 1001 | D12: m2 | E12: 100 | F12: =IF(ISBLANK(C12),"",C12*E12) -> 100100 | H12: 1001 | I12: m2 | J12: 100 | K12: =IF(ISBLANK(H12),"",H12*J12) -> 100100 | M12: 1001 | N12: m2 | O12: 75 | P12: =IF(ISBLANK(M12),"",M12*O12) -> 75075 | R12: 1001 | S12: m2 | T12: 75 | U12: =IF(ISBLANK(R12),"",R12*T12) -> 75075 | X12: m2 | Z12: =IF(ISBLANK(W12),"",W12*Y12) | AC12: m2 | AE12: =IF(ISBLANK(AB12),"",AB12*AD12) | AH12: m2 | AJ12: =IF(ISBLANK(AG12),"",AG12*AI12) | AM12: m2 | AO12: =IF(ISBLANK(AL12),"",AL12*AN12)
A13: =IF(B13>0,IF(C13>0,MAX($A$5:A12)+1," ")," ")
A14: =IF(B14>0,IF(C14>0,MAX($A$5:A13)+1," ")," ") -> 4 | B14: Allowance for proping | C14: 10 | D14: m2 | E14: 100 | F14: =IF(ISBLANK(C14),"",C14*E14) -> 1000 | H14: 10 | I14: m2 | J14: 45 | K14: =IF(ISBLANK(H14),"",H14*J14) -> 450 | M14: 10 | N14: m2 | O14: 100 | P14: =IF(ISBLANK(M14),"",M14*O14) -> 1000 | R14: 10 | S14: m2 | T14: 100 | U14: =IF(ISBLANK(R14),"",R14*T14) -> 1000 | X14: m2 | Z14: =IF(ISBLANK(W14),"",W14*Y14) | AC14: m2 | AE14: =IF(ISBLANK(AB14),"",AB14*AD14) | AH14: m2 | AJ14: =IF(ISBLANK(AG14),"",AG14*AI14) | AM14: m2 | AO14: =IF(ISBLANK(AL14),"",AL14*AN14)
A15: =IF(B15>0,IF(C15>0,MAX($A$5:A14)+1," ")," ")
A16: =IF(B16>0,IF(C16>0,MAX($A$5:A15)+1," ")," ") -> 5 | B16: Allowance for temporary diversion works | C16: 10 | D16: m2 | E16: 100 | F16: =IF(ISBLANK(C16),"",C16*E16) -> 1000 | H16: 10 | I16: m2 | J16: 75 | K16: =IF(ISBLANK(H16),"",H16*J16) -> 750 | M16: 10 | N16: m2 | O16: 100 | P16: =IF(ISBLANK(M16),"",M16*O16) -> 1000 | R16: 10 | S16: m2 | T16: 100 | U16: =IF(ISBLANK(R16),"",R16*T16) -> 1000 | X16: m2 | Z16: =IF(ISBLANK(W16),"",W16*Y16) | AC16: m2 | AE16: =IF(ISBLANK(AB16),"",AB16*AD16) | AH16: m2 | AJ16: =IF(ISBLANK(AG16),"",AG16*AI16) | AM16: m2 | AO16: =IF(ISBLANK(AL16),"",AL16*AN16)
A17: =IF(B17>0,IF(C17>0,MAX($A$5:A16)+1," ")," ")
A18: =IF(B18>0,IF(C18>0,MAX($A$5:A17)+1," ")," ") -> 6 | B18: Allowance for site investigation works | C18: 10 | D18: m2 | E18: 100 | F18: =IF(ISBLANK(C18),"",C18*E18) -> 1000 | H18: 10 | I18: m2 | J18: 75 | K18: =IF(ISBLANK(H18),"",H18*J18) -> 750 | M18: 10 | N18: m2 | O18: 100 | P18: =IF(ISBLANK(M18),"",M18*O18) -> 1000 | R18: 10 | S18: m2 | T18: 100 | U18: =IF(ISBLANK(R18),"",R18*T18) -> 1000 | X18: m2 | Z18: =IF(ISBLANK(W18),"",W18*Y18) | AC18: m2 | AE18: =IF(ISBLANK(AB18),"",AB18*AD18) | AH18: m2 | AJ18: =IF(ISBLANK(AG18),"",AG18*AI18) | AM18: m2 | AO18: =IF(ISBLANK(AL18),"",AL18*AN18)
A19: =IF(B19>0,IF(C19>0,MAX($A$5:A18)+1," ")," ") | F19: =IF(ISBLANK(C19),"",C19*E19) | K19: =IF(ISBLANK(H19),"",H19*J19) | P19: =IF(ISBLANK(M19),"",M19*O19) | U19: =IF(ISBLANK(R19),"",R19*T19) | Z19: =IF(ISBLANK(W19),"",W19*Y19) | AE19: =IF(ISBLANK(AB19),"",AB19*AD19) | AJ19: =IF(ISBLANK(AG19),"",AG19*AI19) | AO19: =IF(ISBLANK(AL19),"",AL19*AN19)
A20: =IF(B20>0,IF(C20>0,MAX($A$5:A19)+1," ")," ") -> 7 | B20: Isolation of services | C20: 1 | D20: item | E20: 2500 | F20: =IF(ISBLANK(C20),"",C20*E20) -> 2500 | H20: 1 | I20: item | J20: 5000 | K20: =IF(ISBLANK(H20),"",H20*J20) -> 5000 | M20: 1 | N20: item | O20: 5000 | P20: =IF(ISBLANK(M20),"",M20*O20) -> 5000 | R20: 1 | S20: item | T20: 2500 | U20: =IF(ISBLANK(R20),"",R20*T20) -> 2500 | X20: item | Z20: =IF(ISBLANK(W20),"",W20*Y20) | AC20: item | AE20: =IF(ISBLANK(AB20),"",AB20*AD20) | AH20: item | AJ20: =IF(ISBLANK(AG20),"",AG20*AI20) | AM20: item | AO20: =IF(ISBLANK(AL20),"",AL20*AN20)
A21: =IF(B21>0,IF(C21>0,MAX($A$5:A20)+1," ")," ") | F21: =IF(ISBLANK(C21),"",C21*E21) | K21: =IF(ISBLANK(H21),"",H21*J21) | P21: =IF(ISBLANK(M21),"",M21*O21) | U21: =IF(ISBLANK(R21),"",R21*T21) | Z21: =IF(ISBLANK(W21),"",W21*Y21) | AE21: =IF(ISBLANK(AB21),"",AB21*AD21) | AJ21: =IF(ISBLANK(AG21),"",AG21*AI21) | AO21: =IF(ISBLANK(AL21),"",AL21*AN21)
A22: =IF(B22>0,IF(C22>0,MAX($A$5:A21)+1," ")," ") -> 8 | B22: Removal of suspended ceilings | C22: 1 | D22: item/m2 | E22: 500 | F22: =IF(ISBLANK(C22),"",C22*E22) -> 500 | H22: 1 | I22: item/m2 | J22: 500 | K22: =IF(ISBLANK(H22),"",H22*J22) -> 500 | M22: 1 | N22: item/m2 | O22: 500 | P22: =IF(ISBLANK(M22),"",M22*O22) -> 500 | R22: 1 | S22: item/m2 | T22: 500 | U22: =IF(ISBLANK(R22),"",R22*T22) -> 500 | X22: item/m2 | Z22: =IF(ISBLANK(W22),"",W22*Y22) | AC22: item/m2 | AE22: =IF(ISBLANK(AB22),"",AB22*AD22) | AH22: item/m2 | AJ22: =IF(ISBLANK(AG22),"",AG22*AI22) | AM22: item/m2 | AO22: =IF(ISBLANK(AL22),"",AL22*AN22)
A23: =IF(B23>0,IF(C23>0,MAX($A$5:A22)+1," ")," ") | F23: =IF(ISBLANK(C23),"",C23*E23) | K23: =IF(ISBLANK(H23),"",H23*J23) | P23: =IF(ISBLANK(M23),"",M23*O23) | U23: =IF(ISBLANK(R23),"",R23*T23) | Z23: =IF(ISBLANK(W23),"",W23*Y23) | AE23: =IF(ISBLANK(AB23),"",AB23*AD23) | AJ23: =IF(ISBLANK(AG23),"",AG23*AI23) | AO23: =IF(ISBLANK(AL23),"",AL23*AN23)
A24: =IF(B24>0,IF(C24>0,MAX($A$5:A23)+1," ")," ") -> 9 | B24: Removal of floor finishes | C24: 1 | D24: item/m2 | E24: 150 | F24: =IF(ISBLANK(C24),"",C24*E24) -> 150 | H24: 1 | I24: item/m2 | J24: 150 | K24: =IF(ISBLANK(H24),"",H24*J24) -> 150 | M24: 1 | N24: item/m2 | O24: 150 | P24: =IF(ISBLANK(M24),"",M24*O24) -> 150 | R24: 1 | S24: item/m2 | T24: 150 | U24: =IF(ISBLANK(R24),"",R24*T24) -> 150 | X24: item/m2 | Z24: =IF(ISBLANK(W24),"",W24*Y24) | AC24: item/m2 | AE24: =IF(ISBLANK(AB24),"",AB24*AD24) | AH24: item/m2 | AJ24: =IF(ISBLANK(AG24),"",AG24*AI24) | AM24: item/m2 | AO24: =IF(ISBLANK(AL24),"",AL24*AN24)
A25: =IF(B25>0,IF(C25>0,MAX($A$5:A24)+1," ")," ") | F25: =IF(ISBLANK(C25),"",C25*E25) | K25: =IF(ISBLANK(H25),"",H25*J25) | P25: =IF(ISBLANK(M25),"",M25*O25) | U25: =IF(ISBLANK(R25),"",R25*T25) | Z25: =IF(ISBLANK(W25),"",W25*Y25) | AE25: =IF(ISBLANK(AB25),"",AB25*AD25) | AJ25: =IF(ISBLANK(AG25),"",AG25*AI25) | AO25: =IF(ISBLANK(AL25),"",AL25*AN25)
A26: =IF(B26>0,IF(C26>0,MAX($A$5:A25)+1," ")," ") -> 10 | B26: Removal of wall finishes | C26: 1 | D26: item/m2 | E26: 500 | F26: =IF(ISBLANK(C26),"",C26*E26) -> 500 | H26: 1 | I26: item/m2 | J26: 500 | K26: =IF(ISBLANK(H26),"",H26*J26) -> 500 | M26: 1 | N26: item/m2 | O26: 500 | P26: =IF(ISBLANK(M26),"",M26*O26) -> 500 | R26: 1 | S26: item/m2 | T26: 500 | U26: =IF(ISBLANK(R26),"",R26*T26) -> 500 | X26: item/m2 | Z26: =IF(ISBLANK(W26),"",W26*Y26) | AC26: item/m2 | AE26: =IF(ISBLANK(AB26),"",AB26*AD26) | AH26: item/m2 | AJ26: =IF(ISBLANK(AG26),"",AG26*AI26) | AM26: item/m2 | AO26: =IF(ISBLANK(AL26),"",AL26*AN26)
A27: =IF(B27>0,IF(C27>0,MAX($A$5:A26)+1," ")," ") | F27: =IF(ISBLANK(C27),"",C27*E27) | K27: =IF(ISBLANK(H27),"",H27*J27) | P27: =IF(ISBLANK(M27),"",M27*O27) | U27: =IF(ISBLANK(R27),"",R27*T27) | Z27: =IF(ISBLANK(W27),"",W27*Y27) | AE27: =IF(ISBLANK(AB27),"",AB27*AD27) | AJ27: =IF(ISBLANK(AG27),"",AG27*AI27) | AO27: =IF(ISBLANK(AL27),"",AL27*AN27)
A28: =IF(B28>0,IF(C28>0,MAX($A$5:A27)+1," ")," ") -> 11 | B28: Removal of internal doors | C28: 25 | D28: nr | E28: 75 | F28: =IF(ISBLANK(C28),"",C28*E28) -> 1875 | H28: 25 | I28: nr | J28: 75 | K28: =IF(ISBLANK(H28),"",H28*J28) -> 1875 | M28: 25 | N28: nr | O28: 75 | P28: =IF(ISBLANK(M28),"",M28*O28) -> 1875 | R28: 25 | S28: nr | T28: 75 | U28: =IF(ISBLANK(R28),"",R28*T28) -> 1875 | X28: nr | Z28: =IF(ISBLANK(W28),"",W28*Y28) | AC28: nr | AE28: =IF(ISBLANK(AB28),"",AB28*AD28) | AH28: nr | AJ28: =IF(ISBLANK(AG28),"",AG28*AI28) | AM28: nr | AO28: =IF(ISBLANK(AL28),"",AL28*AN28)
A29: =IF(B29>0,IF(C29>0,MAX($A$5:A28)+1," ")," ") | F29: =IF(ISBLANK(C29),"",C29*E29) | K29: =IF(ISBLANK(H29),"",H29*J29) | P29: =IF(ISBLANK(M29),"",M29*O29) | U29: =IF(ISBLANK(R29),"",R29*T29) | Z29: =IF(ISBLANK(W29),"",W29*Y29) | AE29: =IF(ISBLANK(AB29),"",AB29*AD29) | AJ29: =IF(ISBLANK(AG29),"",AG29*AI29) | AO29: =IF(ISBLANK(AL29),"",AL29*AN29)
A30: =IF(B30>0,IF(C30>0,MAX($A$5:A29)+1," ")," ") -> 12 | B30: Removal of ironmongery | C30: 1 | D30: item/m2 | E30: 500 | F30: =IF(ISBLANK(C30),"",C30*E30) -> 500 | H30: 1 | I30: item/m2 | J30: 500 | K30: =IF(ISBLANK(H30),"",H30*J30) -> 500 | M30: 1 | N30: item/m2 | O30: 500 | P30: =IF(ISBLANK(M30),"",M30*O30) -> 500 | R30: 1 | S30: item/m2 | T30: 500 | U30: =IF(ISBLANK(R30),"",R30*T30) -> 500 | X30: item/m2 | Z30: =IF(ISBLANK(W30),"",W30*Y30) | AC30: item/m2 | AE30: =IF(ISBLANK(AB30),"",AB30*AD30) | AH30: item/m2 | AJ30: =IF(ISBLANK(AG30),"",AG30*AI30) | AM30: item/m2 | AO30: =IF(ISBLANK(AL30),"",AL30*AN30)
A31: =IF(B31>0,IF(C31>0,MAX($A$5:A30)+1," ")," ") | F31: =IF(ISBLANK(C31),"",C31*E31) | K31: =IF(ISBLANK(H31),"",H31*J31) | P31: =IF(ISBLANK(M31),"",M31*O31) | U31: =IF(ISBLANK(R31),"",R31*T31) | Z31: =IF(ISBLANK(W31),"",W31*Y31) | AE31: =IF(ISBLANK(AB31),"",AB31*AD31) | AJ31: =IF(ISBLANK(AG31),"",AG31*AI31) | AO31: =IF(ISBLANK(AL31),"",AL31*AN31)
A32: =IF(B32>0,IF(C32>0,MAX($A$5:A31)+1," ")," ") -> 13 | B32: Removal of fixed fittings | C32: 1 | D32: item/m2 | E32: 1500 | F32: =IF(ISBLANK(C32),"",C32*E32) -> 1500 | H32: 1 | I32: item/m2 | J32: 5000 | K32: =IF(ISBLANK(H32),"",H32*J32) -> 5000 | M32: 1 | N32: item/m2 | O32: 1500 | P32: =IF(ISBLANK(M32),"",M32*O32) -> 1500 | R32: 1 | S32: item/m2 | T32: 5000 | U32: =IF(ISBLANK(R32),"",R32*T32) -> 5000 | X32: item/m2 | Z32: =IF(ISBLANK(W32),"",W32*Y32) | AC32: item/m2 | AE32: =IF(ISBLANK(AB32),"",AB32*AD32) | AH32: item/m2 | AJ32: =IF(ISBLANK(AG32),"",AG32*AI32) | AM32: item/m2 | AO32: =IF(ISBLANK(AL32),"",AL32*AN32)
A33: =IF(B33>0,IF(C33>0,MAX($A$5:A32)+1," ")," ") | F33: =IF(ISBLANK(C33),"",C33*E33) | K33: =IF(ISBLANK(H33),"",H33*J33) | P33: =IF(ISBLANK(M33),"",M33*O33) | U33: =IF(ISBLANK(R33),"",R33*T33) | Z33: =IF(ISBLANK(W33),"",W33*Y33) | AE33: =IF(ISBLANK(AB33),"",AB33*AD33) | AJ33: =IF(ISBLANK(AG33),"",AG33*AI33) | AO33: =IF(ISBLANK(AL33),"",AL33*AN33)
A34: =IF(B34>0,IF(C34>0,MAX($A$5:A33)+1," ")," ") -> 14 | B34: Removal of sanitaryware | C34: 1 | D34: item/m2 | E34: 1000 | F34: =IF(ISBLANK(C34),"",C34*E34) -> 1000 | H34: 1 | I34: item/m2 | J34: 1000 | K34: =IF(ISBLANK(H34),"",H34*J34) -> 1000 | M34: 1 | N34: item/m2 | O34: 1000 | P34: =IF(ISBLANK(M34),"",M34*O34) -> 1000 | R34: 1 | S34: item/m2 | T34: 1000 | U34: =IF(ISBLANK(R34),"",R34*T34) -> 1000 | X34: item/m2 | Z34: =IF(ISBLANK(W34),"",W34*Y34) | AC34: item/m2 | AE34: =IF(ISBLANK(AB34),"",AB34*AD34) | AH34: item/m2 | AJ34: =IF(ISBLANK(AG34),"",AG34*AI34) | AM34: item/m2 | AO34: =IF(ISBLANK(AL34),"",AL34*AN34)
A35: =IF(B35>0,IF(C35>0,MAX($A$5:A34)+1," ")," ") | F35: =IF(ISBLANK(C35),"",C35*E35) | K35: =IF(ISBLANK(H35),"",H35*J35) | P35: =IF(ISBLANK(M35),"",M35*O35) | U35: =IF(ISBLANK(R35),"",R35*T35) | Z35: =IF(ISBLANK(W35),"",W35*Y35) | AE35: =IF(ISBLANK(AB35),"",AB35*AD35) | AJ35: =IF(ISBLANK(AG35),"",AG35*AI35) | AO35: =IF(ISBLANK(AL35),"",AL35*AN35)
A36: =IF(B36>0,IF(C36>0,MAX($A$5:A35)+1," ")," ") -> 15 | B36: Removal of kitchen units | C36: 1 | D36: item/m2 | E36: 1000 | F36: =IF(ISBLANK(C36),"",C36*E36) -> 1000 | H36: 1 | I36: item/m2 | J36: 1000 | K36: =IF(ISBLANK(H36),"",H36*J36) -> 1000 | M36: 1 | N36: item/m2 | O36: 1000 | P36: =IF(ISBLANK(M36),"",M36*O36) -> 1000 | R36: 1 | S36: item/m2 | T36: 2250 | U36: =IF(ISBLANK(R36),"",R36*T36) -> 2250 | X36: item/m2 | Z36: =IF(ISBLANK(W36),"",W36*Y36) | AC36: item/m2 | AE36: =IF(ISBLANK(AB36),"",AB36*AD36) | AH36: item/m2 | AJ36: =IF(ISBLANK(AG36),"",AG36*AI36) | AM36: item/m2 | AO36: =IF(ISBLANK(AL36),"",AL36*AN36)
A37: =IF(B37>0,IF(C37>0,MAX($A$5:A36)+1," ")," ") | F37: =IF(ISBLANK(C37),"",C37*E37) | K37: =IF(ISBLANK(H37),"",H37*J37) | P37: =IF(ISBLANK(M37),"",M37*O37) | U37: =IF(ISBLANK(R37),"",R37*T37) | Z37: =IF(ISBLANK(W37),"",W37*Y37) | AE37: =IF(ISBLANK(AB37),"",AB37*AD37) | AJ37: =IF(ISBLANK(AG37),"",AG37*AI37) | AO37: =IF(ISBLANK(AL37),"",AL37*AN37)
A38: =IF(B38>0,IF(C38>0,MAX($A$5:A37)+1," ")," ") -> 16 | B38: Removal of light fittings | C38: 1 | D38: item/m2 | E38: 500 | F38: =IF(ISBLANK(C38),"",C38*E38) -> 500 | H38: 1 | I38: item/m2 | J38: 1000 | K38: =IF(ISBLANK(H38),"",H38*J38) -> 1000 | M38: 1 | N38: item/m2 | O38: 2500 | P38: =IF(ISBLANK(M38),"",M38*O38) -> 2500 | R38: 1 | S38: item/m2 | T38: 250 | U38: =IF(ISBLANK(R38),"",R38*T38) -> 250 | X38: item/m2 | Z38: =IF(ISBLANK(W38),"",W38*Y38) | AC38: item/m2 | AE38: =IF(ISBLANK(AB38),"",AB38*AD38) | AH38: item/m2 | AJ38: =IF(ISBLANK(AG38),"",AG38*AI38) | AM38: item/m2 | AO38: =IF(ISBLANK(AL38),"",AL38*AN38)
A39: =IF(B39>0,IF(C39>0,MAX($A$5:A38)+1," ")," ") | F39: =IF(ISBLANK(C39),"",C39*E39) | K39: =IF(ISBLANK(H39),"",H39*J39) | P39: =IF(ISBLANK(M39),"",M39*O39) | U39: =IF(ISBLANK(R39),"",R39*T39) | Z39: =IF(ISBLANK(W39),"",W39*Y39) | AE39: =IF(ISBLANK(AB39),"",AB39*AD39) | AJ39: =IF(ISBLANK(AG39),"",AG39*AI39) | AO39: =IF(ISBLANK(AL39),"",AL39*AN39)
A40: =IF(B40>0,IF(C40>0,MAX($A$5:A39)+1," ")," ") -> 17 | B40: Removal of ductwork | C40: 1 | D40: item/m2 | E40: 150 | F40: =IF(ISBLANK(C40),"",C40*E40) -> 150 | H40: 1 | I40: item/m2 | J40: 1000 | K40: =IF(ISBLANK(H40),"",H40*J40) -> 1000 | M40: 1 | N40: item/m2 | O40: 1000 | P40: =IF(ISBLANK(M40),"",M40*O40) -> 1000 | R40: 1 | S40: item/m2 | T40: 650 | U40: =IF(ISBLANK(R40),"",R40*T40) -> 650 | X40: item/m2 | Z40: =IF(ISBLANK(W40),"",W40*Y40) | AC40: item/m2 | AE40: =IF(ISBLANK(AB40),"",AB40*AD40) | AH40: item/m2 | AJ40: =IF(ISBLANK(AG40),"",AG40*AI40) | AM40: item/m2 | AO40: =IF(ISBLANK(AL40),"",AL40*AN40)
A41: =IF(B41>0,IF(C41>0,MAX($A$5:A40)+1," ")," ") | F41: =IF(ISBLANK(C41),"",C41*E41) | K41: =IF(ISBLANK(H41),"",H41*J41) | P41: =IF(ISBLANK(M41),"",M41*O41) | U41: =IF(ISBLANK(R41),"",R41*T41) | Z41: =IF(ISBLANK(W41),"",W41*Y41) | AE41: =IF(ISBLANK(AB41),"",AB41*AD41) | AJ41: =IF(ISBLANK(AG41),"",AG41*AI41) | AO41: =IF(ISBLANK(AL41),"",AL41*AN41)
A42: =IF(B42>0,IF(C42>0,MAX($A$5:A41)+1," ")," ") -> 18 | B42: Removal of pipework | C42: 1 | D42: item/m2 | E42: 500 | F42: =IF(ISBLANK(C42),"",C42*E42) -> 500 | H42: 1 | I42: item/m2 | J42: 2500 | K42: =IF(ISBLANK(H42),"",H42*J42) -> 2500 | M42: 1 | N42: item/m2 | O42: 1000 | P42: =IF(ISBLANK(M42),"",M42*O42) -> 1000 | R42: 1 | S42: item/m2 | T42: 1000 | U42: =IF(ISBLANK(R42),"",R42*T42) -> 1000 | X42: item/m2 | Z42: =IF(ISBLANK(W42),"",W42*Y42) | AC42: item/m2 | AE42: =IF(ISBLANK(AB42),"",AB42*AD42) | AH42: item/m2 | AJ42: =IF(ISBLANK(AG42),"",AG42*AI42) | AM42: item/m2 | AO42: =IF(ISBLANK(AL42),"",AL42*AN42)
A43: =IF(B43>0,IF(C43>0,MAX($A$5:A42)+1," ")," ") | F43: =IF(ISBLANK(C43),"",C43*E43) | K43: =IF(ISBLANK(H43),"",H43*J43) | P43: =IF(ISBLANK(M43),"",M43*O43) | U43: =IF(ISBLANK(R43),"",R43*T43) | Z43: =IF(ISBLANK(W43),"",W43*Y43) | AE43: =IF(ISBLANK(AB43),"",AB43*AD43) | AJ43: =IF(ISBLANK(AG43),"",AG43*AI43) | AO43: =IF(ISBLANK(AL43),"",AL43*AN43)
A44: =IF(B44>0,IF(C44>0,MAX($A$5:A43)+1," ")," ") -> 19 | B44: Demolition of roof structures | C44: 270 | D44: item/m2 | E44: 75 | F44: =IF(ISBLANK(C44),"",C44*E44) -> 20250 | H44: 270 | I44: item/m2 | J44: 45 | K44: =IF(ISBLANK(H44),"",H44*J44) -> 12150 | M44: 270 | N44: item/m2 | O44: 45 | P44: =IF(ISBLANK(M44),"",M44*O44) -> 12150 | R44: 270 | S44: item/m2 | T44: 45 | U44: =IF(ISBLANK(R44),"",R44*T44) -> 12150 | X44: item/m2 | Z44: =IF(ISBLANK(W44),"",W44*Y44) | AC44: item/m2 | AE44: =IF(ISBLANK(AB44),"",AB44*AD44) | AH44: item/m2 | AJ44: =IF(ISBLANK(AG44),"",AG44*AI44) | AM44: item/m2 | AO44: =IF(ISBLANK(AL44),"",AL44*AN44)
F45: =IF(ISBLANK(C45),"",C45*E45) | K45: =IF(ISBLANK(H45),"",H45*J45) | P45: =IF(ISBLANK(M45),"",M45*O45) | U45: =IF(ISBLANK(R45),"",R45*T45) | Z45: =IF(ISBLANK(W45),"",W45*Y45) | AE45: =IF(ISBLANK(AB45),"",AB45*AD45) | AJ45: =IF(ISBLANK(AG45),"",AG45*AI45) | AO45: =IF(ISBLANK(AL45),"",AL45*AN45)
A46: =IF(B46>0,IF(C46>0,MAX($A$5:A44)+1," ")," ") -> 20 | B46: Demolition of floors | C46: 540 | D46: item/m2 | E46: 500 | F46: =IF(ISBLANK(C46),"",C46*E46) -> 270000 | H46: 540 | I46: item/m2 | J46: 75 | K46: =IF(ISBLANK(H46),"",H46*J46) -> 40500 | M46: 540 | N46: item/m2 | O46: 75 | P46: =IF(ISBLANK(M46),"",M46*O46) -> 40500 | R46: 540 | S46: item/m2 | T46: 75 | U46: =IF(ISBLANK(R46),"",R46*T46) -> 40500 | X46: item/m2 | Z46: =IF(ISBLANK(W46),"",W46*Y46) | AC46: item/m2 | AE46: =IF(ISBLANK(AB46),"",AB46*AD46) | AH46: item/m2 | AJ46: =IF(ISBLANK(AG46),"",AG46*AI46) | AM46: item/m2 | AO46: =IF(ISBLANK(AL46),"",AL46*AN46)
A47: =IF(B47>0,IF(C47>0,MAX($A$5:A46)+1," ")," ") | F47: =IF(ISBLANK(C47),"",C47*E47) | K47: =IF(ISBLANK(H47),"",H47*J47) | P47: =IF(ISBLANK(M47),"",M47*O47) | U47: =IF(ISBLANK(R47),"",R47*T47) | Z47: =IF(ISBLANK(W47),"",W47*Y47) | AE47: =IF(ISBLANK(AB47),"",AB47*AD47) | AJ47: =IF(ISBLANK(AG47),"",AG47*AI47) | AO47: =IF(ISBLANK(AL47),"",AL47*AN47)
A48: =IF(B48>0,IF(C48>0,MAX($A$5:A47)+1," ")," ") | B48: Any other works (contractor to specify) | F48: =IF(ISBLANK(C48),"",C48*E48) | K48: =IF(ISBLANK(H48),"",H48*J48) | P48: =IF(ISBLANK(M48),"",M48*O48) | U48: =IF(ISBLANK(R48),"",R48*T48) | Z48: =IF(ISBLANK(W48),"",W48*Y48) | AE48: =IF(ISBLANK(AB48),"",AB48*AD48) | AJ48: =IF(ISBLANK(AG48),"",AG48*AI48) | AO48: =IF(ISBLANK(AL48),"",AL48*AN48)
A49: =IF(B49>0,IF(C49>0,MAX($A$5:A48)+1," ")," ") -> 21 | B49: ……………………………………………. | C49: 1 | D49: item | F49: =IF(ISBLANK(C49),"",C49*E49) -> 0 | H49: 1 | I49: item | K49: =IF(ISBLANK(H49),"",H49*J49) -> 0 | M49: 1 | N49: item | P49: =IF(ISBLANK(M49),"",M49*O49) -> 0 | R49: 1 | S49: item | U49: =IF(ISBLANK(R49),"",R49*T49) -> 0 | W49: 1 | X49: item | Z49: =IF(ISBLANK(W49),"",W49*Y49) -> 0 | AB49: 1 | AC49: item | AE49: =IF(ISBLANK(AB49),"",AB49*AD49) -> 0 | AG49: 1 | AH49: item | AJ49: =IF(ISBLANK(AG49),"",AG49*AI49) -> 0 | AL49: 1 | AM49: item | AO49: =IF(ISBLANK(AL49),"",AL49*AN49) -> 0
A50: =IF(B50>0,IF(C50>0,MAX($A$5:A49)+1," ")," ") -> 22 | B50: ……………………………………………. | C50: 1 | D50: Item | F50: =IF(ISBLANK(C50),"",C50*E50) -> 0 | H50: 1 | I50: Item | K50: =IF(ISBLANK(H50),"",H50*J50) -> 0 | M50: 1 | N50: Item | P50: =IF(ISBLANK(M50),"",M50*O50) -> 0 | R50: 1 | S50: Item | U50: =IF(ISBLANK(R50),"",R50*T50) -> 0 | W50: 1 | X50: Item | Z50: =IF(ISBLANK(W50),"",W50*Y50) -> 0 | AB50: 1 | AC50: Item | AE50: =IF(ISBLANK(AB50),"",AB50*AD50) -> 0 | AG50: 1 | AH50: Item | AJ50: =IF(ISBLANK(AG50),"",AG50*AI50) -> 0 | AL50: 1 | AM50: Item | AO50: =IF(ISBLANK(AL50),"",AL50*AN50) -> 0
A51: =IF(B51>0,IF(C51>0,MAX($A$5:A50)+1," ")," ") -> 23 | B51: ……………………………………………. | C51: 1 | D51: Item | F51: =IF(ISBLANK(C51),"",C51*E51) -> 0 | H51: 1 | I51: Item | K51: =IF(ISBLANK(H51),"",H51*J51) -> 0 | M51: 1 | N51: Item | P51: =IF(ISBLANK(M51),"",M51*O51) -> 0 | R51: 1 | S51: Item | U51: =IF(ISBLANK(R51),"",R51*T51) -> 0 | W51: 1 | X51: Item | Z51: =IF(ISBLANK(W51),"",W51*Y51) -> 0 | AB51: 1 | AC51: Item | AE51: =IF(ISBLANK(AB51),"",AB51*AD51) -> 0 | AG51: 1 | AH51: Item | AJ51: =IF(ISBLANK(AG51),"",AG51*AI51) -> 0 | AL51: 1 | AM51: Item | AO51: =IF(ISBLANK(AL51),"",AL51*AN51) -> 0
A52: =IF(B52>0,IF(C52>0,MAX($A$5:A51)+1," ")," ") -> 24 | B52: ……………………………………………. | C52: 1 | D52: Item | F52: =IF(ISBLANK(C52),"",C52*E52) -> 0 | H52: 1 | I52: Item | K52: =IF(ISBLANK(H52),"",H52*J52) -> 0 | M52: 1 | N52: Item | P52: =IF(ISBLANK(M52),"",M52*O52) -> 0 | R52: 1 | S52: Item | U52: =IF(ISBLANK(R52),"",R52*T52) -> 0 | W52: 1 | X52: Item | Z52: =IF(ISBLANK(W52),"",W52*Y52) -> 0 | AB52: 1 | AC52: Item | AE52: =IF(ISBLANK(AB52),"",AB52*AD52) -> 0 | AG52: 1 | AH52: Item | AJ52: =IF(ISBLANK(AG52),"",AG52*AI52) -> 0 | AL52: 1 | AM52: Item | AO52: =IF(ISBLANK(AL52),"",AL52*AN52) -> 0
A53: =IF(B53>0,IF(C53>0,MAX($A$5:A52)+1," ")," ") | F53: =IF(ISBLANK(C53),"",C53*E53) | K53: =IF(ISBLANK(H53),"",H53*J53) | P53: =IF(ISBLANK(M53),"",M53*O53) | U53: =IF(ISBLANK(R53),"",R53*T53) | Z53: =IF(ISBLANK(W53),"",W53*Y53) | AE53: =IF(ISBLANK(AB53),"",AB53*AD53) | AJ53: =IF(ISBLANK(AG53),"",AG53*AI53) | AO53: =IF(ISBLANK(AL53),"",AL53*AN53)
E54: Total | F54: =SUM(F5:F53) -> 430551.5 | J54: Total | K54: =SUM(K5:K53) -> 195746 | O54: Total | P54: =SUM(P5:P53) -> 183786.5 | T54: Total | U54: =SUM(U5:U53) -> 198451.5 | Y54: Total | Z54: =SUM(Z5:Z53) -> 0 | AD54: Total | AE54: =SUM(AE5:AE53) -> 0 | AI54: Total | AJ54: =SUM(AJ5:AJ53) -> 0 | AN54: Total | AO54: =SUM(AO5:AO53) -> 0

Sheet 1.1 Substructure
B1: Return to ELEMENT INDEX
B2: Return to SUMMARY
C3: =SUMMARY!E3 -> Sample Cost Plan - Elm Court Residential, Rev 01 | H3: =SUMMARY!K3 -> Ridgeway Construction | M3: =SUMMARY!N3 -> Brightstone Builders | R3: =SUMMARY!Q3 -> Kestrel Contractors | W3: =SUMMARY!T3 -> INSERT CONTRACTOR 4 | AB3: =SUMMARY!W3 -> INSERT CONTRACTOR 5 | AG3: =SUMMARY!Z3 -> INSERT CONTRACTOR 6 | AL3: =SUMMARY!AC3 -> INSERT CONTRACTOR 7
B4: {=MID(CELL("filename",A3),FIND("]",CELL("filename",A3))+1,255)} -> 1.1 Substructure | C4: Qty | D4: Unit | E4: Rate | F4: Total | H4: Qty | I4: Unit | J4: Rate | K4: Total | M4: Qty | N4: Unit | O4: Rate | P4: Total | R4: Qty | S4: Unit | T4: Rate | U4: Total | W4: Qty | X4: Unit | Y4: Rate | Z4: Total | AB4: Qty | AC4: Unit | AD4: Rate | AE4: Total | AG4: Qty | AH4: Unit | AI4: Rate | AJ4: Total | AL4: Qty | AM4: Unit | AN4: Rate | AO4: Total
A5: =IF(B5>0,IF(C5>0,MAX($A$3:A4)+1," ")," ") | F5: =IF(ISBLANK(C5),"",C5*E5) | K5: =IF(ISBLANK(H5),"",H5*J5) | P5: =IF(ISBLANK(M5),"",M5*O5) | U5: =IF(ISBLANK(R5),"",R5*T5) | Z5: =IF(ISBLANK(W5),"",W5*Y5) | AE5: =IF(ISBLANK(AB5),"",AB5*AD5) | AJ5: =IF(ISBLANK(AG5),"",AG5*AI5) | AO5: =IF(ISBLANK(AL5),"",AL5*AN5)
A6: =IF(B6>0,IF(C6>0,MAX($A$3:A5)+1," ")," ") | B6: =B4 -> 1.1 Substructure | F6: =IF(ISBLANK(C6),"",C6*E6) | K6: =IF(ISBLANK(H6),"",H6*J6) | P6: =IF(ISBLANK(M6),"",M6*O6) | U6: =IF(ISBLANK(R6),"",R6*T6) | Z6: =IF(ISBLANK(W6),"",W6*Y6) | AE6: =IF(ISBLANK(AB6),"",AB6*AD6) | AJ6: =IF(ISBLANK(AG6),"",AG6*AI6) | AO6: =IF(ISBLANK(AL6),"",AL6*AN6)
A8: =IF(B8>0,IF(C8>0,MAX($A$5:A7)+1," ")," ") -> 1 | B8: Piling mats/platforms: thickness of mat/platform assumed 400mm | C8: 270 | D8: m2 | E8: 250 | F8: =IF(ISBLANK(C8),"",C8*E8) -> 67500 | H8: 270 | I8: m2 | J8: 125 | K8: =IF(ISBLANK(H8),"",H8*J8) -> 33750 | M8: 270 | N8: m2 | O8: 250 | P8: =IF(ISBLANK(M8),"",M8*O8) -> 67500 | R8: 270 | S8: m2 | T8: 125 | U8: =IF(ISBLANK(R8),"",R8*T8) -> 33750 | X8: m2 | Z8: =IF(ISBLANK(W8),"",W8*Y8) | AC8: m2 | AE8: =IF(ISBLANK(AB8),"",AB8*AD8) | AH8: m2 | AJ8: =IF(ISBLANK(AG8),"",AG8*AI8) | AM8: m2 | AO8: =IF(ISBLANK(AL8),"",AL8*AN8)
A9: =IF(B9>0,IF(C9>0,MAX($A$5:A8)+1," ")," ")
A10: =IF(B10>0,IF(C10>0,MAX($A$5:A9)+1," ")," ") -> 2 | B10: Allowance for piling plant; including mobilization and demobilization | C10: 1 | D10: item | E10: 2500 | F10: =IF(ISBLANK(C10),"",C10*E10) -> 2500 | H10: 1 | I10: item | J10: 3500 | K10: =IF(ISBLANK(H10),"",H10*J10) -> 3500 | M10: 1 | N10: item | O10: 2500 | P10: =IF(ISBLANK(M10),"",M10*O10) -> 2500 | R10: 1 | S10: item | T10: 3500 | U10: =IF(ISBLANK(R10),"",R10*T10) -> 3500 | X10: m2 | Z10: =IF(ISBLANK(W10),"",W10*Y10) | AC10: m2 | AE10: =IF(ISBLANK(AB10),"",AB10*AD10) | AH10: m2 | AJ10: =IF(ISBLANK(AG10),"",AG10*AI10) | AM10: m2 | AO10: =IF(ISBLANK(AL10),"",AL10*AN10)
A11: =IF(B11>0,IF(C11>0,MAX($A$5:A10)+1," ")," ")
A12: =IF(B12>0,IF(C12>0,MAX($A$5:A11)+1," ")," ") -> 3 | B12: Piles: assumed bored, 450mm dia, including integrity testing and moving of piling rig to locations and disposal of arisings | C12: 270 | D12: m2 | E12: 100 | F12: =IF(ISBLANK(C12),"",C12*E12) -> 27000 | H12: 270 | I12: m2 | J12: 90 | K12: =IF(ISBLANK(H12),"",H12*J12) -> 24300 | M12: 270 | N12: m2 | O12: 100 | P12: =IF(ISBLANK(M12),"",M12*O12) -> 27000 | R12: 270 | S12: m2 | T12: 90 | U12: =IF(ISBLANK(R12),"",R12*T12) -> 24300 | Z12: =IF(ISBLANK(W12),"",W12*Y12) | AE12: =IF(ISBLANK(AB12),"",AB12*AD12) | AJ12: =IF(ISBLANK(AG12),"",AG12*AI12) | AO12: =IF(ISBLANK(AL12),"",AL12*AN12)
A14: =IF(B14>0,IF(C14>0,MAX($A$5:A12)+1," ")," ") -> 4 | B14: Extra over allowance for breaking through obstructions | C14: 1 | D14: item | E14: 2500 | F14: =IF(ISBLANK(C14),"",C14*E14) -> 2500 | H14: 1 | I14: item | J14: 2500 | K14: =IF(ISBLANK(H14),"",H14*J14) -> 2500 | M14: 1 | N14: item | O14: 2500 | P14: =IF(ISBLANK(M14),"",M14*O14) -> 2500 | R14: 1 | S14: item | T14: 2500 | U14: =IF(ISBLANK(R14),"",R14*T14) -> 2500 | Z14: =IF(ISBLANK(W14),"",W14*Y14) | AE14: =IF(ISBLANK(AB14),"",AB14*AD14) | AJ14: =IF(ISBLANK(AG14),"",AG14*AI14) | AO14: =IF(ISBLANK(AL14),"",AL14*AN14)
X15: m2 | AC15: m2 | AH15: m2 | AM15: m2
A16: =IF(B16>0,IF(C16>0,MAX($A$5:A15)+1," ")," ") -> 5 | B16: Allowance for pile caps | C16: 270 | D16: m2 | E16: 25 | F16: =IF(ISBLANK(C16),"",C16*E16) -> 6750 | H16: 270 | I16: m2 | J16: 15 | K16: =IF(ISBLANK(H16),"",H16*J16) -> 4050 | M16: 270 | N16: m2 | O16: 25 | P16: =IF(ISBLANK(M16),"",M16*O16) -> 6750 | R16: 270 | S16: m2 | T16: 15 | U16: =IF(ISBLANK(R16),"",R16*T16) -> 4050 | X16: % | AC16: % | AH16: % | AM16: %
A18: =IF(B18>0,IF(C18>0,MAX($A$5:A16)+1," ")," ") -> 6 | B18: Allowance for pile caps to stair cores | C18: 270 | D18: m2 | E18: 10 | F18: =IF(ISBLANK(C18),"",C18*E18) -> 2700 | H18: 270 | I18: m2 | J18: 5 | K18: =IF(ISBLANK(H18),"",H18*J18) -> 1350 | M18: 270 | N18: m2 | O18: 25 | P18: =IF(ISBLANK(M18),"",M18*O18) -> 6750 | R18: 270 | S18: m2 | T18: 5 | U18: =IF(ISBLANK(R18),"",R18*T18) -> 1350 | Z18: =IF(ISBLANK(W18),"",W18*Y18) | AE18: =IF(ISBLANK(AB18),"",AB18*AD18) | AJ18: =IF(ISBLANK(AG18),"",AG18*AI18) | AO18: =IF(ISBLANK(AL18),"",AL18*AN18)
A20: =IF(B20>0,IF(C20>0,MAX($A$5:A18)+1," ")," ") -> 7 | B20: Allowance for pile caps generally | C20: 270 | D20: m2 | E20: 15 | F20: =IF(ISBLANK(C20),"",C20*E20) -> 4050 | H20: 270 | I20: m2 | J20: 5 | K20: =IF(ISBLANK(H20),"",H20*J20) -> 1350 | M20: 270 | N20: m2 | O20: 25 | P20: =IF(ISBLANK(M20),"",M20*O20) -> 6750 | R20: 270 | S20: m2 | T20: 5 | U20: =IF(ISBLANK(R20),"",R20*T20) -> 1350 | Z20: =IF(ISBLANK(W20),"",W20*Y20) | AE20: =IF(ISBLANK(AB20),"",AB20*AD20) | AJ20: =IF(ISBLANK(AG20),"",AG20*AI20) | AO20: =IF(ISBLANK(AL20),"",AL20*AN20)
A22: =IF(B22>0,IF(C22>0,MAX($A$5:A21)+1," ")," ") -> 8 | B22: Allowance for ground beams | C22: 1 | D22: item | E22: 2500 | F22: =IF(ISBLANK(C22),"",C22*E22) -> 2500 | H22: 1 | I22: item | J22: 2000 | K22: =IF(ISBLANK(H22),"",H22*J22) -> 2000 | M22: 1 | N22: item | O22: 5000 | P22: =IF(ISBLANK(M22),"",M22*O22) -> 5000 | R22: 1 | S22: item | T22: 2000 | U22: =IF(ISBLANK(R22),"",R22*T22) -> 2000 | Z22: =IF(ISBLANK(W22),"",W22*Y22) | AE22: =IF(ISBLANK(AB22),"",AB22*AD22) | AJ22: =IF(ISBLANK(AG22),"",AG22*AI22) | AO22: =IF(ISBLANK(AL22),"",AL22*AN22)
X23: m2 | AC23: m2 | AH23: m2 | AM23: m2
A24: =IF(B24>0,IF(C24>0,MAX($A$5:A23)+1," ")," ") -> 9 | B24: Allowance for forming lift pit; | C24: 1 | D24: item | E24: 2500 | F24: =IF(ISBLANK(C24),"",C24*E24) -> 2500 | H24: 1 | I24: item | J24: 2000 | K24: =IF(ISBLANK(H24),"",H24*J24) -> 2000 | M24: 1 | N24: item | O24: 5000 | P24: =IF(ISBLANK(M24),"",M24*O24) -> 5000 | R24: 1 | S24: item | T24: 2000 | U24: =IF(ISBLANK(R24),"",R24*T24) -> 2000 | X24: m2 | Z24: =IF(ISBLANK(W24),"",W24*Y24) | AC24: m2 | AE24: =IF(ISBLANK(AB24),"",AB24*AD24) | AH24: m2 | AJ24: =IF(ISBLANK(AG24),"",AG24*AI24) | AM24: m2 | AO24: =IF(ISBLANK(AL24),"",AL24*AN24)
X25: m2 | AC25: m2 | AH25: m2 | AM25: m2
A26: =IF(B26>0,IF(C26>0,MAX($A$5:A25)+1," ")," ") -> 10 | B26: Allowance for underpinning | C26: 1 | D26: item | E26: 1500 | F26: =IF(ISBLANK(C26),"",C26*E26) -> 1500 | H26: 1 | I26: item | J26: 1000 | K26: =IF(ISBLANK(H26),"",H26*J26) -> 1000 | M26: 1 | N26: item | O26: 5000 | P26: =IF(ISBLANK(M26),"",M26*O26) -> 5000 | R26: 1 | S26: item | T26: 1000 | U26: =IF(ISBLANK(R26),"",R26*T26) -> 1000 | Z26: =IF(ISBLANK(W26),"",W26*Y26) | AE26: =IF(ISBLANK(AB26),"",AB26*AD26) | AJ26: =IF(ISBLANK(AG26),"",AG26*AI26) | AO26: =IF(ISBLANK(AL26),"",AL26*AN26)
A27: =IF(B27>0,IF(C27>0,MAX($A$5:A26)+1," ")," ")
A28: =IF(B28>0,IF(C28>0,MAX($A$5:A27)+1," ")," ") -> 11 | B28: Prepare Formation | C28: 270 | D28: m2 | E28: 5 | F28: =IF(ISBLANK(C28),"",C28*E28) -> 1350 | H28: 270 | I28: m2 | J28: 7 | K28: =IF(ISBLANK(H28),"",H28*J28) -> 1890 | M28: 270 | N28: m2 | O28: 5 | P28: =IF(ISBLANK(M28),"",M28*O28) -> 1350 | R28: 270 | S28: m2 | T28: 7 | U28: =IF(ISBLANK(R28),"",R28*T28) -> 1890 | X28: m2 | Z28: =IF(ISBLANK(W28),"",W28*Y28) | AC28: m2 | AE28: =IF(ISBLANK(AB28),"",AB28*AD28) | AH28: m2 | AJ28: =IF(ISBLANK(AG28),"",AG28*AI28) | AM28: m2 | AO28: =IF(ISBLANK(AL28),"",AL28*AN28)
A30: =IF(B30>0,IF(C30>0,MAX($A$5:A28)+1," ")," ") -> 12 | B30: Setting Out | C30: 1 | D30: item | E30: 5 | F30: =IF(ISBLANK(C30),"",C30*E30) -> 5 | H30: 1 | I30: item | J30: 7 | K30: =IF(ISBLANK(H30),"",H30*J30) -> 7 | M30: 1 | N30: item | O30: 5 | P30: =IF(ISBLANK(M30),"",M30*O30) -> 5 | R30: 1 | S30: item | T30: 7 | U30: =IF(ISBLANK(R30),"",R30*T30) -> 7 | X30: % | Z30: =IF(ISBLANK(W30),"",W30*Y30) | AC30: % | AE30: =IF(ISBLANK(AB30),"",AB30*AD30) | AH30: % | AJ30: =IF(ISBLANK(AG30),"",AG30*AI30) | AM30: % | AO30: =IF(ISBLANK(AL30),"",AL30*AN30)
A31: =IF(B31>0,IF(C31>0,MAX($A$5:A30)+1," ")," ")
A32: =IF(B32>0,IF(C32>0,MAX($A$5:A31)+1," ")," ") -> 13 | B32: Level & Compact Excavation | C32: 270 | D32: m2 | E32: 5 | F32: =IF(ISBLANK(C32),"",C32*E32) -> 1350 | H32: 270 | I32: m2 | J32: 7 | K32: =IF(ISBLANK(H32),"",H32*J32) -> 1890 | M32: 270 | N32: m2 | O32: 5 | P32: =IF(ISBLANK(M32),"",M32*O32) -> 1350 | R32: 270 | S32: m2 | T32: 7 | U32: =IF(ISBLANK(R32),"",R32*T32) -> 1890 | Z32: =IF(ISBLANK(W32),"",W32*Y32) | AE32: =IF(ISBLANK(AB32),"",AB32*AD32) | AJ32: =IF(ISBLANK(AG32),"",AG32*AI32) | AO32: =IF(ISBLANK(AL32),"",AL32*AN32)
A33: =IF(B33>0,IF(C33>0,MAX($A$5:A32)+1," ")," ")
A34: =IF(B34>0,IF(C34>0,MAX($A$5:A33)+1," ")," ") -> 14 | B34: Allowance for strip foundations (min 600mm wide, 1000mm deep) including concrete and all associated works including excavation and disposal. | C34: 50 | D34: lm | E34: 175 | F34: =IF(ISBLANK(C34),"",C34*E34) -> 8750 | H34: 50 | I34: lm | J34: 200 | K34: =IF(ISBLANK(H34),"",H34*J34) -> 10000 | M34: 50 | N34: lm | O34: 175 | P34: =IF(ISBLANK(M34),"",M34*O34) -> 8750 | R34: 50 | S34: lm | T34: 175 | U34: =IF(ISBLANK(R34),"",R34*T34) -> 8750 | X34: m2 | AC34: m2 | AH34: m2 | AM34: m2
A36: =IF(B36>0,IF(C36>0,MAX($A$5:A34)+1," ")," ") -> 15 | B36: Foundations | C36: 10 | D36: m2 | E36: 100 | F36: =IF(ISBLANK(C36),"",C36*E36) -> 1000 | H36: 10 | I36: m2 | J36: 90 | K36: =IF(ISBLANK(H36),"",H36*J36) -> 900 | M36: 10 | N36: m2 | O36: 50 | P36: =IF(ISBLANK(M36),"",M36*O36) -> 500 | R36: 10 | S36: m2 | T36: 100 | U36: =IF(ISBLANK(R36),"",R36*T36) -> 1000 | X36: m2 | Z36: =IF(ISBLANK(W36),"",W36*Y36) | AC36: m2 | AE36: =IF(ISBLANK(AB36),"",AB36*AD36) | AH36: m2 | AJ36: =IF(ISBLANK(AG36),"",AG36*AI36) | AM36: m2 | AO36: =IF(ISBLANK(AL36),"",AL36*AN36)
A38: =IF(B38>0,IF(C38>0,MAX($A$5:A37)+1," ")," ") -> 16 | B38: Blockwork walls below ground using concrete block in 1:1:6 cement:sand mortar | C38: 50 | D38: lm | E38: 75 | F38: =IF(ISBLANK(C38),"",C38*E38) -> 3750 | H38: 50 | I38: lm | J38: 50 | K38: =IF(ISBLANK(H38),"",H38*J38) -> 2500 | M38: 50 | N38: lm | O38: 75 | P38: =IF(ISBLANK(M38),"",M38*O38) -> 3750 | R38: 50 | S38: lm | T38: 75 | U38: =IF(ISBLANK(R38),"",R38*T38) -> 3750 | X38: m | AC38: m | AH38: m | AM38: m
A40: =IF(B40>0,IF(C40>0,MAX($A$5:A38)+1," ")," ") -> 17 | B40: Perimeter Walls n.e 1000mm high | C40: 50 | D40: lm | E40: 25 | F40: =IF(ISBLANK(C40),"",C40*E40) -> 1250 | H40: 50 | I40: lm | J40: 20 | K40: =IF(ISBLANK(H40),"",H40*J40) -> 1000 | M40: 50 | N40: lm | O40: 25 | P40: =IF(ISBLANK(M40),"",M40*O40) -> 1250 | R40: 50 | S40: lm | T40: 25 | U40: =IF(ISBLANK(R40),"",R40*T40) -> 1250 | X40: m | AC40: m | AH40: m | AM40: m
A42: =IF(B42>0,IF(C42>0,MAX($A$5:A40)+1," ")," ") -> 18 | B42: 100mm Thk blockwork wall inner leaf | C42: 50 | D42: lm | E42: 150 | F42: =IF(ISBLANK(C42),"",C42*E42) -> 7500 | H42: 50 | I42: lm | J42: 150 | K42: =IF(ISBLANK(H42),"",H42*J42) -> 7500 | M42: 50 | N42: lm | O42: 225 | P42: =IF(ISBLANK(M42),"",M42*O42) -> 11250 | R42: 50 | S42: lm | T42: 150 | U42: =IF(ISBLANK(R42),"",R42*T42) -> 7500 | X42: m | Z42: =IF(ISBLANK(W42),"",W42*Y42) | AC42: m | AE42: =IF(ISBLANK(AB42),"",AB42*AD42) | AH42: m | AJ42: =IF(ISBLANK(AG42),"",AG42*AI42) | AM42: m | AO42: =IF(ISBLANK(AL42),"",AL42*AN42)
A44: =IF(B44>0,IF(C44>0,MAX($A$5:A42)+1," ")," ") -> 19 | B44: Form cavity c/w lean mix | C44: 50 | D44: lm | E44: 125 | F44: =IF(ISBLANK(C44),"",C44*E44) -> 6250 | H44: 50 | I44: lm | J44: 125 | K44: =IF(ISBLANK(H44),"",H44*J44) -> 6250 | M44: 50 | N44: lm | O44: 130 | P44: =IF(ISBLANK(M44),"",M44*O44) -> 6500 | R44: 50 | S44: lm | T44: 125 | U44: =IF(ISBLANK(R44),"",R44*T44) -> 6250 | X44: m | Z44: =IF(ISBLANK(W44),"",W44*Y44) | AC44: m | AE44: =IF(ISBLANK(AB44),"",AB44*AD44) | AH44: m | AJ44: =IF(ISBLANK(AG44),"",AG44*AI44) | AM44: m | AO44: =IF(ISBLANK(AL44),"",AL44*AN44)
A46: =IF(B46>0,IF(C46>0,MAX($A$5:A44)+1," ")," ") -> 20 | B46: 100mm Thk blockwork wall inner leaf | C46: 50 | D46: lm | E46: 50 | F46: =IF(ISBLANK(C46),"",C46*E46) -> 2500 | H46: 50 | I46: lm | J46: 25 | K46: =IF(ISBLANK(H46),"",H46*J46) -> 1250 | M46: 50 | N46: lm | O46: 55 | P46: =IF(ISBLANK(M46),"",M46*O46) -> 2750 | R46: 50 | S46: lm | T46: 50 | U46: =IF(ISBLANK(R46),"",R46*T46) -> 2500 | Z46: =IF(ISBLANK(W46),"",W46*Y46) | AE46: =IF(ISBLANK(AB46),"",AB46*AD46) | AJ46: =IF(ISBLANK(AG46),"",AG46*AI46) | AO46: =IF(ISBLANK(AL46),"",AL46*AN46)
A48: =IF(B48>0,IF(C48>0,MAX($A$5:A47)+1," ")," ") | B48: Any other works (contractor to specify) | F48: =IF(ISBLANK(C48),"",C48*E48) | K48: =IF(ISBLANK(H48),"",H48*J48) | P48: =IF(ISBLANK(M48),"",M48*O48) | U48: =IF(ISBLANK(R48),"",R48*T48) | Z48: =IF(ISBLANK(W48),"",W48*Y48) | AE48: =IF(ISBLANK(AB48),"",AB48*AD48) | AJ48: =IF(ISBLANK(AG48),"",AG48*AI48) | AO48: =IF(ISBLANK(AL48),"",AL48*AN48)
A49: =IF(B49>0,IF(C49>0,MAX($A$5:A48)+1," ")," ") -> 21 | B49: ……………………………………………. | C49: 1 | D49: item | F49: =IF(ISBLANK(C49),"",C49*E49) -> 0 | H49: 1 | I49: item | K49: =IF(ISBLANK(H49),"",H49*J49) -> 0 | M49: 1 | N49: item | P49: =IF(ISBLANK(M49),"",M49*O49) -> 0 | R49: 1 | S49: item | U49: =IF(ISBLANK(R49),"",R49*T49) -> 0 | W49: 1 | X49: item | Z49: =IF(ISBLANK(W49),"",W49*Y49) -> 0 | AB49: 1 | AC49: item | AE49: =IF(ISBLANK(AB49),"",AB49*AD49) -> 0 | AG49: 1 | AH49: item | AJ49: =IF(ISBLANK(AG49),"",AG49*AI49) -> 0 | AL49: 1 | AM49: item | AO49: =IF(ISBLANK(AL49),"",AL49*AN49) -> 0
A50: =IF(B50>0,IF(C50>0,MAX($A$5:A49)+1," ")," ") -> 22 | B50: ……………………………………………. | C50: 1 | D50: Item | F50: =IF(ISBLANK(C50),"",C50*E50) -> 0 | H50: 1 | I50: Item | K50: =IF(ISBLANK(H50),"",H50*J50) -> 0 | M50: 1 | N50: Item | P50: =IF(ISBLANK(M50),"",M50*O50) -> 0 | R50: 1 | S50: Item | U50: =IF(ISBLANK(R50),"",R50*T50) -> 0 | W50: 1 | X50: Item | Z50: =IF(ISBLANK(W50),"",W50*Y50) -> 0 | AB50: 1 | AC50: Item | AE50: =IF(ISBLANK(AB50),"",AB50*AD50) -> 0 | AG50: 1 | AH50: Item | AJ50: =IF(ISBLANK(AG50),"",AG50*AI50) -> 0 | AL50: 1 | AM50: Item | AO50: =IF(ISBLANK(AL50),"",AL50*AN50) -> 0
A51: =IF(B51>0,IF(C51>0,MAX($A$5:A50)+1," ")," ") -> 23 | B51: ……………………………………………. | C51: 1 | D51: Item | F51: =IF(ISBLANK(C51),"",C51*E51) -> 0 | H51: 1 | I51: Item | K51: =IF(ISBLANK(H51),"",H51*J51) -> 0 | M51: 1 | N51: Item | P51: =IF(ISBLANK(M51),"",M51*O51) -> 0 | R51: 1 | S51: Item | U51: =IF(ISBLANK(R51),"",R51*T51) -> 0 | W51: 1 | X51: Item | Z51: =IF(ISBLANK(W51),"",W51*Y51) -> 0 | AB51: 1 | AC51: Item | AE51: =IF(ISBLANK(AB51),"",AB51*AD51) -> 0 | AG51: 1 | AH51: Item | AJ51: =IF(ISBLANK(AG51),"",AG51*AI51) -> 0 | AL51: 1 | AM51: Item | AO51: =IF(ISBLANK(AL51),"",AL51*AN51) -> 0
A52: =IF(B52>0,IF(C52>0,MAX($A$5:A51)+1," ")," ") -> 24 | B52: ……………………………………………. | C52: 1 | D52: Item | F52: =IF(ISBLANK(C52),"",C52*E52) -> 0 | H52: 1 | I52: Item | K52: =IF(ISBLANK(H52),"",H52*J52) -> 0 | M52: 1 | N52: Item | P52: =IF(ISBLANK(M52),"",M52*O52) -> 0 | R52: 1 | S52: Item | U52: =IF(ISBLANK(R52),"",R52*T52) -> 0 | W52: 1 | X52: Item | Z52: =IF(ISBLANK(W52),"",W52*Y52) -> 0 | AB52: 1 | AC52: Item | AE52: =IF(ISBLANK(AB52),"",AB52*AD52) -> 0 | AG52: 1 | AH52: Item | AJ52: =IF(ISBLANK(AG52),"",AG52*AI52) -> 0 | AL52: 1 | AM52: Item | AO52: =IF(ISBLANK(AL52),"",AL52*AN52) -> 0
A53: =IF(B53>0,IF(C53>0,MAX($A$3:A47)+1," ")," ") | F53: =IF(ISBLANK(C53),"",C53*E53) | K53: =IF(ISBLANK(H53),"",H53*J53) | P53: =IF(ISBLANK(M53),"",M53*O53) | U53: =IF(ISBLANK(R53),"",R53*T53) | Z53: =IF(ISBLANK(W53),"",W53*Y53) | AE53: =IF(ISBLANK(AB53),"",AB53*AD53) | AJ53: =IF(ISBLANK(AG53),"",AG53*AI53) | AO53: =IF(ISBLANK(AL53),"",AL53*AN53)
E54: Total | F54: =SUM(F5:F53) -> 153205 | J54: Total | K54: =SUM(K5:K53) -> 108987 | O54: Total | P54: =SUM(P5:P53) -> 172205 | T54: Total | U54: =SUM(U5:U53) -> 110587 | Y54: Total | Z54: =SUM(Z5:Z53) -> 0 | AD54: Total | AE54: =SUM(AE5:AE53) -> 0 | AI54: Total | AJ54: =SUM(AJ5:AJ53) -> 0 | AN54: Total | AO54: =SUM(AO5:AO53) -> 0

Sheet 2.1 Frame
B1: Return to ELEMENT INDEX
B2: Return to SUMMARY
C3: =SUMMARY!E3 -> Sample Cost Plan - Elm Court Residential, Rev 01 | H3: =SUMMARY!K3 -> Ridgeway Construction | M3: =SUMMARY!N3 -> Brightstone Builders | R3: =SUMMARY!Q3 -> Kestrel Contractors | W3: =SUMMARY!T3 -> INSERT CONTRACTOR 4 | AB3: =SUMMARY!W3 -> INSERT CONTRACTOR 5 | AG3: =SUMMARY!Z3 -> INSERT CONTRACTOR 6 | AL3: =SUMMARY!AC3 -> INSERT CONTRACTOR 7
B4: {=MID(CELL("filename",A3),FIND("]",CELL("filename",A3))+1,255)} -> 2.1 Frame | C4: Qty | D4: Unit | E4: Rate | F4: Total | H4: Qty | I4: Unit | J4: Rate | K4: Total | M4: Qty | N4: Unit | O4: Rate | P4: Total | R4: Qty | S4: Unit | T4: Rate | U4: Total | W4: Qty | X4: Unit | Y4: Rate | Z4: Total | AB4: Qty | AC4: Unit | AD4: Rate | AE4: Total | AG4: Qty | AH4: Unit | AI4: Rate | AJ4: Total | AL4: Qty | AM4: Unit | AN4: Rate | AO4: Total
A5: =IF(B5>0,IF(C5>0,MAX($A$3:A4)+1," ")," ") | F5: =IF(ISBLANK(C5),"",C5*E5) | K5: =IF(ISBLANK(H5),"",H5*J5) | P5: =IF(ISBLANK(M5),"",M5*O5) | U5: =IF(ISBLANK(R5),"",R5*T5) | Z5: =IF(ISBLANK(W5),"",W5*Y5) | AE5: =IF(ISBLANK(AB5),"",AB5*AD5) | AJ5: =IF(ISBLANK(AG5),"",AG5*AI5) | AO5: =IF(ISBLANK(AL5),"",AL5*AN5)
A6: =IF(B6>0,IF(C6>0,MAX($A$3:A5)+1," ")," ") | B6: Frame | F6: =IF(ISBLANK(C6),"",C6*E6) | K6: =IF(ISBLANK(H6),"",H6*J6) | P6: =IF(ISBLANK(M6),"",M6*O6) | U6: =IF(ISBLANK(R6),"",R6*T6) | Z6: =IF(ISBLANK(W6),"",W6*Y6) | AE6: =IF(ISBLANK(AB6),"",AB6*AD6) | AJ6: =IF(ISBLANK(AG6),"",AG6*AI6) | AO6: =IF(ISBLANK(AL6),"",AL6*AN6)
A7: =IF(B7>0,IF(C7>0,MAX($A$3:A6)+1," ")," ") | F7: =IF(ISBLANK(C7),"",C7*E7) | K7: =IF(ISBLANK(H7),"",H7*J7) | P7: =IF(ISBLANK(M7),"",M7*O7) | U7: =IF(ISBLANK(R7),"",R7*T7) | Z7: =IF(ISBLANK(W7),"",W7*Y7) | AE7: =IF(ISBLANK(AB7),"",AB7*AD7) | AJ7: =IF(ISBLANK(AG7),"",AG7*AI7) | AO7: =IF(ISBLANK(AL7),"",AL7*AN7)
A8: =IF(B8>0,IF(C8>0,MAX($A$5:A7)+1," ")," ") -> 1 | B8: Structural frame design coordination | C8: 1 | D8: item | E8: 5000 | F8: =IF(ISBLANK(C8),"",C8*E8) -> 5000 | H8: 1 | I8: item | J8: 5000 | K8: =IF(ISBLANK(H8),"",H8*J8) -> 5000 | M8: 1 | N8: item | O8: 5000 | P8: =IF(ISBLANK(M8),"",M8*O8) -> 5000 | R8: 1 | S8: item | T8: 5000 | U8: =IF(ISBLANK(R8),"",R8*T8) -> 5000 | X8: item | Z8: =IF(ISBLANK(W8),"",W8*Y8) | AC8: item | AE8: =IF(ISBLANK(AB8),"",AB8*AD8) | AH8: item | AJ8: =IF(ISBLANK(AG8),"",AG8*AI8) | AM8: item | AO8: =IF(ISBLANK(AL8),"",AL8*AN8)
A9: =IF(B9>0,IF(C9>0,MAX($A$5:A8)+1," ")," ") | F9: =IF(ISBLANK(C9),"",C9*E9) | K9: =IF(ISBLANK(H9),"",H9*J9) | P9: =IF(ISBLANK(M9),"",M9*O9) | U9: =IF(ISBLANK(R9),"",R9*T9) | Z9: =IF(ISBLANK(W9),"",W9*Y9) | AE9: =IF(ISBLANK(AB9),"",AB9*AD9) | AJ9: =IF(ISBLANK(AG9),"",AG9*AI9) | AO9: =IF(ISBLANK(AL9),"",AL9*AN9)
A10: =IF(B10>0,IF(C10>0,MAX($A$5:A9)+1," ")," ") -> 2 | B10: Setting out for structural frame | C10: 1 | D10: item | E10: 2500 | F10: =IF(ISBLANK(C10),"",C10*E10) -> 2500 | H10: 1 | I10: item | J10: 2500 | K10: =IF(ISBLANK(H10),"",H10*J10) -> 2500 | M10: 1 | N10: item | O10: 2500 | P10: =IF(ISBLANK(M10),"",M10*O10) -> 2500 | R10: 1 | S10: item | T10: 2500 | U10: =IF(ISBLANK(R10),"",R10*T10) -> 2500 | X10: item | Z10: =IF(ISBLANK(W10),"",W10*Y10) | AC10: item | AE10: =IF(ISBLANK(AB10),"",AB10*AD10) | AH10: item | AJ10: =IF(ISBLANK(AG10),"",AG10*AI10) | AM10: item | AO10: =IF(ISBLANK(AL10),"",AL10*AN10)
A11: =IF(B11>0,IF(C11>0,MAX($A$5:A10)+1," ")," ") | F11: =IF(ISBLANK(C11),"",C11*E11) | K11: =IF(ISBLANK(H11),"",H11*J11) | P11: =IF(ISBLANK(M11),"",M11*O11) | U11: =IF(ISBLANK(R11),"",R11*T11) | Z11: =IF(ISBLANK(W11),"",W11*Y11) | AE11: =IF(ISBLANK(AB11),"",AB11*AD11) | AJ11: =IF(ISBLANK(AG11),"",AG11*AI11) | AO11: =IF(ISBLANK(AL11),"",AL11*AN11)
A12: =IF(B12>0,IF(C12>0,MAX($A$5:A11)+1," ")," ") -> 3 | B12: Temporary works design for frame | C12: 1 | D12: item | E12: 2500 | F12: =IF(ISBLANK(C12),"",C12*E12) -> 2500 | H12: 1 | I12: item | J12: 2500 | K12: =IF(ISBLANK(H12),"",H12*J12) -> 2500 | M12: 1 | N12: item | O12: 2500 | P12: =IF(ISBLANK(M12),"",M12*O12) -> 2500 | R12: 1 | S12: item | T12: 2500 | U12: =IF(ISBLANK(R12),"",R12*T12) -> 2500 | X12: item | Z12: =IF(ISBLANK(W12),"",W12*Y12) | AC12: item | AE12: =IF(ISBLANK(AB12),"",AB12*AD12) | AH12: item | AJ12: =IF(ISBLANK(AG12),"",AG12*AI12) | AM12: item | AO12: =IF(ISBLANK(AL12),"",AL12*AN12)
A13: =IF(B13>0,IF(C13>0,MAX($A$5:A12)+1," ")," ") | F13: =IF(ISBLANK(C13),"",C13*E13) | K13: =IF(ISBLANK(H13),"",H13*J13) | P13: =IF(ISBLANK(M13),"",M13*O13) | U13: =IF(ISBLANK(R13),"",R13*T13) | Z13: =IF(ISBLANK(W13),"",W13*Y13) | AE13: =IF(ISBLANK(AB13),"",AB13*AD13) | AJ13: =IF(ISBLANK(AG13),"",AG13*AI13) | AO13: =IF(ISBLANK(AL13),"",AL13*AN13)
A14: =IF(B14>0,IF(C14>0,MAX($A$5:A13)+1," ")," ") -> 4 | B14: Formwork systems | C14: 540 | D14: m2 | E14: 25 | F14: =IF(ISBLANK(C14),"",C14*E14) -> 13500 | H14: 540 | I14: m2 | J14: 25 | K14: =IF(ISBLANK(H14),"",H14*J14) -> 13500 | M14: 540 | N14: m2 | O14: 25 | P14: =IF(ISBLANK(M14),"",M14*O14) -> 13500 | R14: 540 | S14: m2 | T14: 25 | U14: =IF(ISBLANK(R14),"",R14*T14) -> 13500 | X14: m2 | Z14: =IF(ISBLANK(W14),"",W14*Y14) | AC14: m2 | AE14: =IF(ISBLANK(AB14),"",AB14*AD14) | AH14: m2 | AJ14: =IF(ISBLANK(AG14),"",AG14*AI14) | AM14: m2 | AO14: =IF(ISBLANK(AL14),"",AL14*AN14)
A15: =IF(B15>0,IF(C15>0,MAX($A$5:A14)+1," ")," ") | F15: =IF(ISBLANK(C15),"",C15*E15) | K15: =IF(ISBLANK(H15),"",H15*J15) | P15: =IF(ISBLANK(M15),"",M15*O15) | U15: =IF(ISBLANK(R15),"",R15*T15) | Z15: =IF(ISBLANK(W15),"",W15*Y15) | AE15: =IF(ISBLANK(AB15),"",AB15*AD15) | AJ15: =IF(ISBLANK(AG15),"",AG15*AI15) | AO15: =IF(ISBLANK(AL15),"",AL15*AN15)
A16: =IF(B16>0,IF(C16>0,MAX($A$5:A15)+1," ")," ") -> 5 | B16: Falsework and propping | C16: 1 | D16: item | E16: 2500 | F16: =IF(ISBLANK(C16),"",C16*E16) -> 2500 | H16: 1 | I16: item | J16: 2500 | K16: =IF(ISBLANK(H16),"",H16*J16) -> 2500 | M16: 1 | N16: item | O16: 2500 | P16: =IF(ISBLANK(M16),"",M16*O16) -> 2500 | R16: 1 | S16: item | T16: 2500 | U16: =IF(ISBLANK(R16),"",R16*T16) -> 2500 | X16: item | Z16: =IF(ISBLANK(W16),"",W16*Y16) | AC16: item | AE16: =IF(ISBLANK(AB16),"",AB16*AD16) | AH16: item | AJ16: =IF(ISBLANK(AG16),"",AG16*AI16) | AM16: item | AO16: =IF(ISBLANK(AL16),"",AL16*AN16)
A17: =IF(B17>0,IF(C17>0,MAX($A$5:A16)+1," ")," ") | F17: =IF(ISBLANK(C17),"",C17*E17) | K17: =IF(ISBLANK(H17),"",H17*J17) | P17: =IF(ISBLANK(M17),"",M17*O17) | U17: =IF(ISBLANK(R17),"",R17*T17) | Z17: =IF(ISBLANK(W17),"",W17*Y17) | AE17: =IF(ISBLANK(AB17),"",AB17*AD17) | AJ17: =IF(ISBLANK(AG17),"",AG17*AI17) | AO17: =IF(ISBLANK(AL17),"",AL17*AN17)
A18: =IF(B18>0,IF(C18>0,MAX($A$5:A17)+1," ")," ") -> 6 | B18: In-situ reinforced concrete columns | C18: 150 | D18: m3 | E18: 350 | F18: =IF(ISBLANK(C18),"",C18*E18) -> 52500 | H18: 150 | I18: m3 | J18: 350 | K18: =IF(ISBLANK(H18),"",H18*J18) -> 52500 | M18: 150 | N18: m3 | O18: 350 | P18: =IF(ISBLANK(M18),"",M18*O18) -> 52500 | R18: 150 | S18: m3 | T18: 350 | U18: =IF(ISBLANK(R18),"",R18*T18) -> 52500 | X18: m3 | Z18: =IF(ISBLANK(W18),"",W18*Y18) | AC18: m3 | AE18: =IF(ISBLANK(AB18),"",AB18*AD18) | AH18: m3 | AJ18: =IF(ISBLANK(AG18),"",AG18*AI18) | AM18: m3 | AO18: =IF(ISBLANK(AL18),"",AL18*AN18)
A19: =IF(B19>0,IF(C19>0,MAX($A$5:A18)+1," ")," ") | F19: =IF(ISBLANK(C19),"",C19*E19) | K19: =IF(ISBLANK(H19),"",H19*J19) | P19: =IF(ISBLANK(M19),"",M19*O19) | U19: =IF(ISBLANK(R19),"",R19*T19) | Z19: =IF(ISBLANK(W19),"",W19*Y19) | AE19: =IF(ISBLANK(AB19),"",AB19*AD19) | AJ19: =IF(ISBLANK(AG19),"",AG19*AI19) | AO19: =IF(ISBLANK(AL19),"",AL19*AN19)
A20: =IF(B20>0,IF(C20>0,MAX($A$5:A19)+1," ")," ") -> 7 | B20: In-situ reinforced concrete beams | C20: 265 | D20: m3 | E20: 350 | F20: =IF(ISBLANK(C20),"",C20*E20) -> 92750 | H20: 265 | I20: m3 | J20: 350 | K20: =IF(ISBLANK(H20),"",H20*J20) -> 92750 | M20: 265 | N20: m3 | O20: 350 | P20: =IF(ISBLANK(M20),"",M20*O20) -> 92750 | R20: 265 | S20: m3 | T20: 350 | U20: =IF(ISBLANK(R20),"",R20*T20) -> 92750 | X20: m3 | Z20: =IF(ISBLANK(W20),"",W20*Y20) | AC20: m3 | AE20: =IF(ISBLANK(AB20),"",AB20*AD20) | AH20: m3 | AJ20: =IF(ISBLANK(AG20),"",AG20*AI20) | AM20: m3 | AO20: =IF(ISBLANK(AL20),"",AL20*AN20)
A21: =IF(B21>0,IF(C21>0,MAX($A$5:A20)+1," ")," ") | F21: =IF(ISBLANK(C21),"",C21*E21) | K21: =IF(ISBLANK(H21),"",H21*J21) | P21: =IF(ISBLANK(M21),"",M21*O21) | U21: =IF(ISBLANK(R21),"",R21*T21) | Z21: =IF(ISBLANK(W21),"",W21*Y21) | AE21: =IF(ISBLANK(AB21),"",AB21*AD21) | AJ21: =IF(ISBLANK(AG21),"",AG21*AI21) | AO21: =IF(ISBLANK(AL21),"",AL21*AN21)
A22: =IF(B22>0,IF(C22>0,MAX($A$5:A21)+1," ")," ") -> 8 | B22: In-situ reinforced concrete floor slabs | C22: 225 | D22: m3 | E22: 350 | F22: =IF(ISBLANK(C22),"",C22*E22) -> 78750 | H22: 225 | I22: m3 | J22: 350 | K22: =IF(ISBLANK(H22),"",H22*J22) -> 78750 | M22: 225 | N22: m3 | O22: 350 | P22: =IF(ISBLANK(M22),"",M22*O22) -> 78750 | R22: 225 | S22: m3 | T22: 350 | U22: =IF(ISBLANK(R22),"",R22*T22) -> 78750 | X22: m3 | Z22: =IF(ISBLANK(W22),"",W22*Y22) | AC22: m3 | AE22: =IF(ISBLANK(AB22),"",AB22*AD22) | AH22: m3 | AJ22: =IF(ISBLANK(AG22),"",AG22*AI22) | AM22: m3 | AO22: =IF(ISBLANK(AL22),"",AL22*AN22)
A23: =IF(B23>0,IF(C23>0,MAX($A$5:A22)+1," ")," ") | F23: =IF(ISBLANK(C23),"",C23*E23) | K23: =IF(ISBLANK(H23),"",H23*J23) | P23: =IF(ISBLANK(M23),"",M23*O23) | U23: =IF(ISBLANK(R23),"",R23*T23) | Z23: =IF(ISBLANK(W23),"",W23*Y23) | AE23: =IF(ISBLANK(AB23),"",AB23*AD23) | AJ23: =IF(ISBLANK(AG23),"",AG23*AI23) | AO23: =IF(ISBLANK(AL23),"",AL23*AN23)
A24: =IF(B24>0,IF(C24>0,MAX($A$5:A23)+1," ")," ") -> 9 | B24: Reinforced concrete cores | C24: 55 | D24: m3 | E24: 475 | F24: =IF(ISBLANK(C24),"",C24*E24) -> 26125 | H24: 55 | I24: m3 | J24: 475 | K24: =IF(ISBLANK(H24),"",H24*J24) -> 26125 | M24: 55 | N24: m3 | O24: 475 | P24: =IF(ISBLANK(M24),"",M24*O24) -> 26125 | R24: 55 | S24: m3 | T24: 475 | U24: =IF(ISBLANK(R24),"",R24*T24) -> 26125 | X24: m3 | Z24: =IF(ISBLANK(W24),"",W24*Y24) | AC24: m3 | AE24: =IF(ISBLANK(AB24),"",AB24*AD24) | AH24: m3 | AJ24: =IF(ISBLANK(AG24),"",AG24*AI24) | AM24: m3 | AO24: =IF(ISBLANK(AL24),"",AL24*AN24)
A25: =IF(B25>0,IF(C25>0,MAX($A$5:A24)+1," ")," ") | F25: =IF(ISBLANK(C25),"",C25*E25) | K25: =IF(ISBLANK(H25),"",H25*J25) | P25: =IF(ISBLANK(M25),"",M25*O25) | U25: =IF(ISBLANK(R25),"",R25*T25) | Z25: =IF(ISBLANK(W25),"",W25*Y25) | AE25: =IF(ISBLANK(AB25),"",AB25*AD25) | AJ25: =IF(ISBLANK(AG25),"",AG25*AI25) | AO25: =IF(ISBLANK(AL25),"",AL25*AN25)
A26: =IF(B26>0,IF(C26>0,MAX($A$5:A25)+1," ")," ") -> 10 | B26: Supply and fix reinforcement | C26: 7 | D26: t | E26: 3500 | F26: =IF(ISBLANK(C26),"",C26*E26) -> 24500 | H26: 7 | I26: t | J26: 3500 | K26: =IF(ISBLANK(H26),"",H26*J26) -> 24500 | M26: 7 | N26: t | O26: 3500 | P26: =IF(ISBLANK(M26),"",M26*O26) -> 24500 | R26: 7 | S26: t | T26: 3500 | U26: =IF(ISBLANK(R26),"",R26*T26) -> 24500 | X26: t | Z26: =IF(ISBLANK(W26),"",W26*Y26) | AC26: t | AE26: =IF(ISBLANK(AB26),"",AB26*AD26) | AH26: t | AJ26: =IF(ISBLANK(AG26),"",AG26*AI26) | AM26: t | AO26: =IF(ISBLANK(AL26),"",AL26*AN26)
A27: =IF(B27>0,IF(C27>0,MAX($A$5:A26)+1," ")," ") | F27: =IF(ISBLANK(C27),"",C27*E27) | K27: =IF(ISBLANK(H27),"",H27*J27) | P27: =IF(ISBLANK(M27),"",M27*O27) | U27: =IF(ISBLANK(R27),"",R27*T27) | Z27: =IF(ISBLANK(W27),"",W27*Y27) | AE27: =IF(ISBLANK(AB27),"",AB27*AD27) | AJ27: =IF(ISBLANK(AG27),"",AG27*AI27) | AO27: =IF(ISBLANK(AL27),"",AL27*AN27)
A28: =IF(B28>0,IF(C28>0,MAX($A$5:A27)+1," ")," ") -> 11 | B28: Formwork to vertical elements | C28: 150 | D28: m2 | E28: 150 | F28: =IF(ISBLANK(C28),"",C28*E28) -> 22500 | H28: 150 | I28: m2 | J28: 150 | K28: =IF(ISBLANK(H28),"",H28*J28) -> 22500 | M28: 150 | N28: m2 | O28: 150 | P28: =IF(ISBLANK(M28),"",M28*O28) -> 22500 | R28: 150 | S28: m2 | T28: 150 | U28: =IF(ISBLANK(R28),"",R28*T28) -> 22500 | X28: m2 | Z28: =IF(ISBLANK(W28),"",W28*Y28) | AC28: m2 | AE28: =IF(ISBLANK(AB28),"",AB28*AD28) | AH28: m2 | AJ28: =IF(ISBLANK(AG28),"",AG28*AI28) | AM28: m2 | AO28: =IF(ISBLANK(AL28),"",AL28*AN28)
A29: =IF(B29>0,IF(C29>0,MAX($A$5:A28)+1," ")," ") | F29: =IF(ISBLANK(C29),"",C29*E29) | K29: =IF(ISBLANK(H29),"",H29*J29) | P29: =IF(ISBLANK(M29),"",M29*O29) | U29: =IF(ISBLANK(R29),"",R29*T29) | Z29: =IF(ISBLANK(W29),"",W29*Y29) | AE29: =IF(ISBLANK(AB29),"",AB29*AD29) | AJ29: =IF(ISBLANK(AG29),"",AG29*AI29) | AO29: =IF(ISBLANK(AL29),"",AL29*AN29)
A30: =IF(B30>0,IF(C30>0,MAX($A$5:A29)+1," ")," ") -> 12 | B30: Formwork to horizontal elements | C30: 350 | D30: m2 | E30: 150 | F30: =IF(ISBLANK(C30),"",C30*E30) -> 52500 | H30: 350 | I30: m2 | J30: 150 | K30: =IF(ISBLANK(H30),"",H30*J30) -> 52500 | M30: 350 | N30: m2 | O30: 150 | P30: =IF(ISBLANK(M30),"",M30*O30) -> 52500 | R30: 350 | S30: m2 | T30: 150 | U30: =IF(ISBLANK(R30),"",R30*T30) -> 52500 | X30: m2 | Z30: =IF(ISBLANK(W30),"",W30*Y30) | AC30: m2 | AE30: =IF(ISBLANK(AB30),"",AB30*AD30) | AH30: m2 | AJ30: =IF(ISBLANK(AG30),"",AG30*AI30) | AM30: m2 | AO30: =IF(ISBLANK(AL30),"",AL30*AN30)
A31: =IF(B31>0,IF(C31>0,MAX($A$5:A30)+1," ")," ") | F31: =IF(ISBLANK(C31),"",C31*E31) | K31: =IF(ISBLANK(H31),"",H31*J31) | P31: =IF(ISBLANK(M31),"",M31*O31) | U31: =IF(ISBLANK(R31),"",R31*T31) | Z31: =IF(ISBLANK(W31),"",W31*Y31) | AE31: =IF(ISBLANK(AB31),"",AB31*AD31) | AJ31: =IF(ISBLANK(AG31),"",AG31*AI31) | AO31: =IF(ISBLANK(AL31),"",AL31*AN31)
A32: =IF(B32>0,IF(C32>0,MAX($A$5:A31)+1," ")," ") -> 13 | B32: Precast concrete columns | C32: 2 | D32: m3 | E32: 350 | F32: =IF(ISBLANK(C32),"",C32*E32) -> 700 | H32: 2 | I32: m3 | J32: 350 | K32: =IF(ISBLANK(H32),"",H32*J32) -> 700 | M32: 2 | N32: m3 | O32: 350 | P32: =IF(ISBLANK(M32),"",M32*O32) -> 700 | R32: 2 | S32: m3 | T32: 350 | U32: =IF(ISBLANK(R32),"",R32*T32) -> 700 | X32: m3 | Z32: =IF(ISBLANK(W32),"",W32*Y32) | AC32: m3 | AE32: =IF(ISBLANK(AB32),"",AB32*AD32) | AH32: m3 | AJ32: =IF(ISBLANK(AG32),"",AG32*AI32) | AM32: m3 | AO32: =IF(ISBLANK(AL32),"",AL32*AN32)
A33: =IF(B33>0,IF(C33>0,MAX($A$5:A32)+1," ")," ") | F33: =IF(ISBLANK(C33),"",C33*E33) | K33: =IF(ISBLANK(H33),"",H33*J33) | P33: =IF(ISBLANK(M33),"",M33*O33) | U33: =IF(ISBLANK(R33),"",R33*T33) | Z33: =IF(ISBLANK(W33),"",W33*Y33) | AE33: =IF(ISBLANK(AB33),"",AB33*AD33) | AJ33: =IF(ISBLANK(AG33),"",AG33*AI33) | AO33: =IF(ISBLANK(AL33),"",AL33*AN33)
A34: =IF(B34>0,IF(C34>0,MAX($A$5:A33)+1," ")," ") -> 14 | B34: Precast concrete beams | C34: 4 | D34: m3 | E34: 350 | F34: =IF(ISBLANK(C34),"",C34*E34) -> 1400 | H34: 4 | I34: m3 | J34: 350 | K34: =IF(ISBLANK(H34),"",H34*J34) -> 1400 | M34: 4 | N34: m3 | O34: 350 | P34: =IF(ISBLANK(M34),"",M34*O34) -> 1400 | R34: 4 | S34: m3 | T34: 350 | U34: =IF(ISBLANK(R34),"",R34*T34) -> 1400 | X34: m3 | Z34: =IF(ISBLANK(W34),"",W34*Y34) | AC34: m3 | AE34: =IF(ISBLANK(AB34),"",AB34*AD34) | AH34: m3 | AJ34: =IF(ISBLANK(AG34),"",AG34*AI34) | AM34: m3 | AO34: =IF(ISBLANK(AL34),"",AL34*AN34)
A35: =IF(B35>0,IF(C35>0,MAX($A$5:A34)+1," ")," ") | F35: =IF(ISBLANK(C35),"",C35*E35) | K35: =IF(ISBLANK(H35),"",H35*J35) | P35: =IF(ISBLANK(M35),"",M35*O35) | U35: =IF(ISBLANK(R35),"",R35*T35) | Z35: =IF(ISBLANK(W35),"",W35*Y35) | AE35: =IF(ISBLANK(AB35),"",AB35*AD35) | AJ35: =IF(ISBLANK(AG35),"",AG35*AI35) | AO35: =IF(ISBLANK(AL35),"",AL35*AN35)
A36: =IF(B36>0,IF(C36>0,MAX($A$5:A35)+1," ")," ") -> 15 | B36: Precast concrete floor units | C36: 5 | D36: m3 | E36: 350 | F36: =IF(ISBLANK(C36),"",C36*E36) -> 1750 | H36: 5 | I36: m3 | J36: 350 | K36: =IF(ISBLANK(H36),"",H36*J36) -> 1750 | M36: 5 | N36: m3 | O36: 350 | P36: =IF(ISBLANK(M36),"",M36*O36) -> 1750 | R36: 5 | S36: m3 | T36: 350 | U36: =IF(ISBLANK(R36),"",R36*T36) -> 1750 | X36: m3 | Z36: =IF(ISBLANK(W36),"",W36*Y36) | AC36: m3 | AE36: =IF(ISBLANK(AB36),"",AB36*AD36) | AH36: m3 | AJ36: =IF(ISBLANK(AG36),"",AG36*AI36) | AM36: m3 | AO36: =IF(ISBLANK(AL36),"",AL36*AN36)
A37: =IF(B37>0,IF(C37>0,MAX($A$5:A36)+1," ")," ") | F37: =IF(ISBLANK(C37),"",C37*E37) | K37: =IF(ISBLANK(H37),"",H37*J37) | P37: =IF(ISBLANK(M37),"",M37*O37) | U37: =IF(ISBLANK(R37),"",R37*T37) | Z37: =IF(ISBLANK(W37),"",W37*Y37) | AE37: =IF(ISBLANK(AB37),"",AB37*AD37) | AJ37: =IF(ISBLANK(AG37),"",AG37*AI37) | AO37: =IF(ISBLANK(AL37),"",AL37*AN37)
A38: =IF(B38>0,IF(C38>0,MAX($A$5:A37)+1," ")," ") -> 16 | B38: Precast concrete stairs | C38: 2 | D38: nr | E38: 3500 | F38: =IF(ISBLANK(C38),"",C38*E38) -> 7000 | H38: 2 | I38: nr | J38: 3500 | K38: =IF(ISBLANK(H38),"",H38*J38) -> 7000 | M38: 2 | N38: nr | O38: 3500 | P38: =IF(ISBLANK(M38),"",M38*O38) -> 7000 | R38: 2 | S38: nr | T38: 3500 | U38: =IF(ISBLANK(R38),"",R38*T38) -> 7000 | X38: nr | Z38: =IF(ISBLANK(W38),"",W38*Y38) | AC38: nr | AE38: =IF(ISBLANK(AB38),"",AB38*AD38) | AH38: nr | AJ38: =IF(ISBLANK(AG38),"",AG38*AI38) | AM38: nr | AO38: =IF(ISBLANK(AL38),"",AL38*AN38)
A39: =IF(B39>0,IF(C39>0,MAX($A$5:A38)+1," ")," ") | F39: =IF(ISBLANK(C39),"",C39*E39) | K39: =IF(ISBLANK(H39),"",H39*J39) | P39: =IF(ISBLANK(M39),"",M39*O39) | U39: =IF(ISBLANK(R39),"",R39*T39) | Z39: =IF(ISBLANK(W39),"",W39*Y39) | AE39: =IF(ISBLANK(AB39),"",AB39*AD39) | AJ39: =IF(ISBLANK(AG39),"",AG39*AI39) | AO39: =IF(ISBLANK(AL39),"",AL39*AN39)
A40: =IF(B40>0,IF(C40>0,MAX($A$5:A39)+1," ")," ") -> 17 | B40: Grouting and structural connections | C40: 1 | D40: item | E40: 1500 | F40: =IF(ISBLANK(C40),"",C40*E40) -> 1500 | H40: 1 | I40: item | J40: 1500 | K40: =IF(ISBLANK(H40),"",H40*J40) -> 1500 | M40: 1 | N40: item | O40: 1500 | P40: =IF(ISBLANK(M40),"",M40*O40) -> 1500 | R40: 1 | S40: item | T40: 1500 | U40: =IF(ISBLANK(R40),"",R40*T40) -> 1500 | X40: item | Z40: =IF(ISBLANK(W40),"",W40*Y40) | AC40: item | AE40: =IF(ISBLANK(AB40),"",AB40*AD40) | AH40: item | AJ40: =IF(ISBLANK(AG40),"",AG40*AI40) | AM40: item | AO40: =IF(ISBLANK(AL40),"",AL40*AN40)
A41: =IF(B41>0,IF(C41>0,MAX($A$5:A40)+1," ")," ") | F41: =IF(ISBLANK(C41),"",C41*E41) | K41: =IF(ISBLANK(H41),"",H41*J41) | P41: =IF(ISBLANK(M41),"",M41*O41) | U41: =IF(ISBLANK(R41),"",R41*T41) | Z41: =IF(ISBLANK(W41),"",W41*Y41) | AE41: =IF(ISBLANK(AB41),"",AB41*AD41) | AJ41: =IF(ISBLANK(AG41),"",AG41*AI41) | AO41: =IF(ISBLANK(AL41),"",AL41*AN41)
A42: =IF(B42>0,IF(C42>0,MAX($A$5:A41)+1," ")," ") -> 18 | B42: Structural steel columns | C42: 8 | D42: t | E42: 3500 | F42: =IF(ISBLANK(C42),"",C42*E42) -> 28000 | H42: 8 | I42: t | J42: 3500 | K42: =IF(ISBLANK(H42),"",H42*J42) -> 28000 | M42: 8 | N42: t | O42: 3500 | P42: =IF(ISBLANK(M42),"",M42*O42) -> 28000 | R42: 8 | S42: t | T42: 3500 | U42: =IF(ISBLANK(R42),"",R42*T42) -> 28000 | X42: t | Z42: =IF(ISBLANK(W42),"",W42*Y42) | AC42: t | AE42: =IF(ISBLANK(AB42),"",AB42*AD42) | AH42: t | AJ42: =IF(ISBLANK(AG42),"",AG42*AI42) | AM42: t | AO42: =IF(ISBLANK(AL42),"",AL42*AN42)
A43: =IF(B43>0,IF(C43>0,MAX($A$5:A42)+1," ")," ") | F43: =IF(ISBLANK(C43),"",C43*E43) | K43: =IF(ISBLANK(H43),"",H43*J43) | P43: =IF(ISBLANK(M43),"",M43*O43) | U43: =IF(ISBLANK(R43),"",R43*T43) | Z43: =IF(ISBLANK(W43),"",W43*Y43) | AE43: =IF(ISBLANK(AB43),"",AB43*AD43) | AJ43: =IF(ISBLANK(AG43),"",AG43*AI43) | AO43: =IF(ISBLANK(AL43),"",AL43*AN43)
A44: =IF(B44>0,IF(C44>0,MAX($A$5:A43)+1," ")," ") -> 19 | B44: Structural steel beams | C44: 8 | D44: t | E44: 3500 | F44: =IF(ISBLANK(C44),"",C44*E44) -> 28000 | H44: 8 | I44: t | J44: 3500 | K44: =IF(ISBLANK(H44),"",H44*J44) -> 28000 | M44: 8 | N44: t | O44: 3500 | P44: =IF(ISBLANK(M44),"",M44*O44) -> 28000 | R44: 8 | S44: t | T44: 3500 | U44: =IF(ISBLANK(R44),"",R44*T44) -> 28000 | X44: t | Z44: =IF(ISBLANK(W44),"",W44*Y44) | AC44: t | AE44: =IF(ISBLANK(AB44),"",AB44*AD44) | AH44: t | AJ44: =IF(ISBLANK(AG44),"",AG44*AI44) | AM44: t | AO44: =IF(ISBLANK(AL44),"",AL44*AN44)
A45: =IF(B45>0,IF(C45>0,MAX($A$5:A44)+1," ")," ") | F45: =IF(ISBLANK(C45),"",C45*E45) | K45: =IF(ISBLANK(H45),"",H45*J45) | P45: =IF(ISBLANK(M45),"",M45*O45) | U45: =IF(ISBLANK(R45),"",R45*T45) | Z45: =IF(ISBLANK(W45),"",W45*Y45) | AE45: =IF(ISBLANK(AB45),"",AB45*AD45) | AJ45: =IF(ISBLANK(AG45),"",AG45*AI45) | AO45: =IF(ISBLANK(AL45),"",AL45*AN45)
A46: =IF(B46>0,IF(C46>0,MAX($A$5:A45)+1," ")," ") -> 20 | B46: Steel bracing members | C46: 8 | D46: t | E46: 3500 | F46: =IF(ISBLANK(C46),"",C46*E46) -> 28000 | H46: 8 | I46: t | J46: 3500 | K46: =IF(ISBLANK(H46),"",H46*J46) -> 28000 | M46: 8 | N46: t | O46: 3500 | P46: =IF(ISBLANK(M46),"",M46*O46) -> 28000 | R46: 8 | S46: t | T46: 3500 | U46: =IF(ISBLANK(R46),"",R46*T46) -> 28000 | X46: t | Z46: =IF(ISBLANK(W46),"",W46*Y46) | AC46: t | AE46: =IF(ISBLANK(AB46),"",AB46*AD46) | AH46: t | AJ46: =IF(ISBLANK(AG46),"",AG46*AI46) | AM46: t | AO46: =IF(ISBLANK(AL46),"",AL46*AN46)
A47: =IF(B47>0,IF(C47>0,MAX($A$5:A46)+1," ")," ") | F47: =IF(ISBLANK(C47),"",C47*E47) | K47: =IF(ISBLANK(H47),"",H47*J47) | P47: =IF(ISBLANK(M47),"",M47*O47) | U47: =IF(ISBLANK(R47),"",R47*T47) | Z47: =IF(ISBLANK(W47),"",W47*Y47) | AE47: =IF(ISBLANK(AB47),"",AB47*AD47) | AJ47: =IF(ISBLANK(AG47),"",AG47*AI47) | AO47: =IF(ISBLANK(AL47),"",AL47*AN47)
A48: =IF(B48>0,IF(C48>0,MAX($A$5:A47)+1," ")," ") | B48: Any other works (contractor to specify) | F48: =IF(ISBLANK(C48),"",C48*E48) | K48: =IF(ISBLANK(H48),"",H48*J48) | P48: =IF(ISBLANK(M48),"",M48*O48) | U48: =IF(ISBLANK(R48),"",R48*T48) | Z48: =IF(ISBLANK(W48),"",W48*Y48) | AE48: =IF(ISBLANK(AB48),"",AB48*AD48) | AJ48: =IF(ISBLANK(AG48),"",AG48*AI48) | AO48: =IF(ISBLANK(AL48),"",AL48*AN48)
A49: =IF(B49>0,IF(C49>0,MAX($A$5:A48)+1," ")," ") -> 21 | B49: ……………………………………………. | C49: 1 | D49: item | F49: =IF(ISBLANK(C49),"",C49*E49) -> 0 | H49: 1 | I49: item | K49: =IF(ISBLANK(H49),"",H49*J49) -> 0 | M49: 1 | N49: item | P49: =IF(ISBLANK(M49),"",M49*O49) -> 0 | R49: 1 | S49: item | U49: =IF(ISBLANK(R49),"",R49*T49) -> 0 | W49: 1 | X49: item | Z49: =IF(ISBLANK(W49),"",W49*Y49) -> 0 | AB49: 1 | AC49: item | AE49: =IF(ISBLANK(AB49),"",AB49*AD49) -> 0 | AG49: 1 | AH49: item | AJ49: =IF(ISBLANK(AG49),"",AG49*AI49) -> 0 | AL49: 1 | AM49: item | AO49: =IF(ISBLANK(AL49),"",AL49*AN49) -> 0
A50: =IF(B50>0,IF(C50>0,MAX($A$5:A49)+1," ")," ") -> 22 | B50: ……………………………………………. | C50: 1 | D50: Item | F50: =IF(ISBLANK(C50),"",C50*E50) -> 0 | H50: 1 | I50: Item | K50: =IF(ISBLANK(H50),"",H50*J50) -> 0 | M50: 1 | N50: Item | P50: =IF(ISBLANK(M50),"",M50*O50) -> 0 | R50: 1 | S50: Item | U50: =IF(ISBLANK(R50),"",R50*T50) -> 0 | W50: 1 | X50: Item | Z50: =IF(ISBLANK(W50),"",W50*Y50) -> 0 | AB50: 1 | AC50: Item | AE50: =IF(ISBLANK(AB50),"",AB50*AD50) -> 0 | AG50: 1 | AH50: Item | AJ50: =IF(ISBLANK(AG50),"",AG50*AI50) -> 0 | AL50: 1 | AM50: Item | AO50: =IF(ISBLANK(AL50),"",AL50*AN50) -> 0
A51: =IF(B51>0,IF(C51>0,MAX($A$5:A50)+1," ")," ") -> 23 | B51: ……………………………………………. | C51: 1 | D51: Item | F51: =IF(ISBLANK(C51),"",C51*E51) -> 0 | H51: 1 | I51: Item | K51: =IF(ISBLANK(H51),"",H51*J51) -> 0 | M51: 1 | N51: Item | P51: =IF(ISBLANK(M51),"",M51*O51) -> 0 | R51: 1 | S51: Item | U51: =IF(ISBLANK(R51),"",R51*T51) -> 0 | W51: 1 | X51: Item | Z51: =IF(ISBLANK(W51),"",W51*Y51) -> 0 | AB51: 1 | AC51: Item | AE51: =IF(ISBLANK(AB51),"",AB51*AD51) -> 0 | AG51: 1 | AH51: Item | AJ51: =IF(ISBLANK(AG51),"",AG51*AI51) -> 0 | AL51: 1 | AM51: Item | AO51: =IF(ISBLANK(AL51),"",AL51*AN51) -> 0
A52: =IF(B52>0,IF(C52>0,MAX($A$5:A51)+1," ")," ") -> 24 | B52: ……………………………………………. | C52: 1 | D52: Item | F52: =IF(ISBLANK(C52),"",C52*E52) -> 0 | H52: 1 | I52: Item | K52: =IF(ISBLANK(H52),"",H52*J52) -> 0 | M52: 1 | N52: Item | P52: =IF(ISBLANK(M52),"",M52*O52) -> 0 | R52: 1 | S52: Item | U52: =IF(ISBLANK(R52),"",R52*T52) -> 0 | W52: 1 | X52: Item | Z52: =IF(ISBLANK(W52),"",W52*Y52) -> 0 | AB52: 1 | AC52: Item | AE52: =IF(ISBLANK(AB52),"",AB52*AD52) -> 0 | AG52: 1 | AH52: Item | AJ52: =IF(ISBLANK(AG52),"",AG52*AI52) -> 0 | AL52: 1 | AM52: Item | AO52: =IF(ISBLANK(AL52),"",AL52*AN52) -> 0
A53: =IF(B53>0,IF(C53>0,MAX($A$3:A47)+1," ")," ") | F53: =IF(ISBLANK(C53),"",C53*E53) | K53: =IF(ISBLANK(H53),"",H53*J53) | P53: =IF(ISBLANK(M53),"",M53*O53) | U53: =IF(ISBLANK(R53),"",R53*T53) | Z53: =IF(ISBLANK(W53),"",W53*Y53) | AE53: =IF(ISBLANK(AB53),"",AB53*AD53) | AJ53: =IF(ISBLANK(AG53),"",AG53*AI53) | AO53: =IF(ISBLANK(AL53),"",AL53*AN53)
E54: Total | F54: =SUM(F5:F53) -> 471975 | J54: Total | K54: =SUM(K5:K53) -> 471975 | O54: Total | P54: =SUM(P5:P53) -> 471975 | T54: Total | U54: =SUM(U5:U53) -> 471975 | Y54: Total | Z54: =SUM(Z5:Z53) -> 0 | AD54: Total | AE54: =SUM(AE5:AE53) -> 0 | AI54: Total | AJ54: =SUM(AJ5:AJ53) -> 0 | AN54: Total | AO54: =SUM(AO5:AO53) -> 0

Sheet 2.2 Upper floors
B1: Return to ELEMENT INDEX
B2: Return to SUMMARY
C3: =SUMMARY!E3 -> Sample Cost Plan - Elm Court Residential, Rev 01 | H3: =SUMMARY!K3 -> Ridgeway Construction | M3: =SUMMARY!N3 -> Brightstone Builders | R3: =SUMMARY!Q3 -> Kestrel Contractors | W3: =SUMMARY!T3 -> INSERT CONTRACTOR 4 | AB3: =SUMMARY!W3 -> INSERT CONTRACTOR 5 | AG3: =SUMMARY!Z3 -> INSERT CONTRACTOR 6 | AL3: =SUMMARY!AC3 -> INSERT CONTRACTOR 7
B4: {=MID(CELL("filename",A3),FIND("]",CELL("filename",A3))+1,255)} -> 2.2 Upper floors | C4: Qty | D4: Unit | E4: Rate | F4: Total | H4: Qty | I4: Unit | J4: Rate | K4: Total | M4: Qty | N4: Unit | O4: Rate | P4: Total | R4: Qty | S4: Unit | T4: Rate | U4: Total | W4: Qty | X4: Unit | Y4: Rate | Z4: Total | AB4: Qty | AC4: Unit | AD4: Rate | AE4: Total | AG4: Qty | AH4: Unit | AI4: Rate | AJ4: Total | AL4: Qty | AM4: Unit | AN4: Rate | AO4: Total
A5: =IF(B5>0,IF(C5>0,MAX($A$3:A4)+1," ")," ") | F5: =IF(ISBLANK(C5),"",C5*E5) | K5: =IF(ISBLANK(H5),"",H5*J5) | P5: =IF(ISBLANK(M5),"",M5*O5) | U5: =IF(ISBLANK(R5),"",R5*T5) | Z5: =IF(ISBLANK(W5),"",W5*Y5) | AE5: =IF(ISBLANK(AB5),"",AB5*AD5) | AJ5: =IF(ISBLANK(AG5),"",AG5*AI5) | AO5: =IF(ISBLANK(AL5),"",AL5*AN5)
A6: =IF(B6>0,IF(C6>0,MAX($A$5:A5)+1," ")," ") | B6: Upper Floors
A7: =IF(B7>0,IF(C7>0,MAX($A$5:A6)+1," ")," ")
A8: =IF(B8>0,IF(C8>0,MAX($A$5:A7)+1," ")," ") -> 1 | B8: In-situ reinforced concrete upper floor slabs | C8: 540 | D8: m³ | E8: 350 | F8: =IF(ISBLANK(C8),"",C8*E8) -> 189000 | H8: 540 | I8: m³ | J8: 350 | K8: =IF(ISBLANK(H8),"",H8*J8) -> 189000 | M8: 540 | N8: m³ | O8: 350 | P8: =IF(ISBLANK(M8),"",M8*O8) -> 189000 | R8: 540 | S8: m³ | T8: 350 | U8: =IF(ISBLANK(R8),"",R8*T8) -> 189000 | X8: m³ | Z8: =IF(ISBLANK(W8),"",W8*Y8) | AC8: m³ | AE8: =IF(ISBLANK(AB8),"",AB8*AD8) | AH8: m³ | AJ8: =IF(ISBLANK(AG8),"",AG8*AI8) | AM8: m³ | AO8: =IF(ISBLANK(AL8),"",AL8*AN8)
F9: =IF(ISBLANK(C9),"",C9*E9) | K9: =IF(ISBLANK(H9),"",H9*J9) | P9: =IF(ISBLANK(M9),"",M9*O9) | U9: =IF(ISBLANK(R9),"",R9*T9) | Z9: =IF(ISBLANK(W9),"",W9*Y9) | AE9: =IF(ISBLANK(AB9),"",AB9*AD9) | AJ9: =IF(ISBLANK(AG9),"",AG9*AI9) | AO9: =IF(ISBLANK(AL9),"",AL9*AN9)
A10: =IF(B10>0,IF(C10>0,MAX($A$5:A8)+1," ")," ") -> 2 | B10: Precast concrete floor planks | C10: 250 | D10: m² | E10: 250 | F10: =IF(ISBLANK(C10),"",C10*E10) -> 62500 | H10: 250 | I10: m² | J10: 250 | K10: =IF(ISBLANK(H10),"",H10*J10) -> 62500 | M10: 250 | N10: m² | O10: 250 | P10: =IF(ISBLANK(M10),"",M10*O10) -> 62500 | R10: 250 | S10: m² | T10: 250 | U10: =IF(ISBLANK(R10),"",R10*T10) -> 62500 | X10: m² | Z10: =IF(ISBLANK(W10),"",W10*Y10) | AC10: m² | AE10: =IF(ISBLANK(AB10),"",AB10*AD10) | AH10: m² | AJ10: =IF(ISBLANK(AG10),"",AG10*AI10) | AM10: m² | AO10: =IF(ISBLANK(AL10),"",AL10*AN10)
A12: =IF(B12>0,IF(C12>0,MAX($A$5:A10)+1," ")," ") -> 3 | B12: Composite metal deck floor system | C12: 270 | D12: m² | E12: 100 | F12: =IF(ISBLANK(C12),"",C12*E12) -> 27000 | H12: 270 | I12: m² | J12: 100 | K12: =IF(ISBLANK(H12),"",H12*J12) -> 27000 | M12: 270 | N12: m² | O12: 100 | P12: =IF(ISBLANK(M12),"",M12*O12) -> 27000 | R12: 270 | S12: m² | T12: 100 | U12: =IF(ISBLANK(R12),"",R12*T12) -> 27000 | X12: m² | Z12: =IF(ISBLANK(W12),"",W12*Y12) | AC12: m² | AE12: =IF(ISBLANK(AB12),"",AB12*AD12) | AH12: m² | AJ12: =IF(ISBLANK(AG12),"",AG12*AI12) | AM12: m² | AO12: =IF(ISBLANK(AL12),"",AL12*AN12)
F13: =IF(ISBLANK(C13),"",C13*E13) | K13: =IF(ISBLANK(H13),"",H13*J13) | P13: =IF(ISBLANK(M13),"",M13*O13) | U13: =IF(ISBLANK(R13),"",R13*T13) | Z13: =IF(ISBLANK(W13),"",W13*Y13) | AE13: =IF(ISBLANK(AB13),"",AB13*AD13) | AJ13: =IF(ISBLANK(AG13),"",AG13*AI13) | AO13: =IF(ISBLANK(AL13),"",AL13*AN13)
A14: =IF(B14>0,IF(C14>0,MAX($A$5:A12)+1," ")," ") -> 4 | B14: Cross laminated timber floor panels | C14: 270 | D14: m² | E14: 25 | F14: =IF(ISBLANK(C14),"",C14*E14) -> 6750 | H14: 270 | I14: m² | J14: 25 | K14: =IF(ISBLANK(H14),"",H14*J14) -> 6750 | M14: 270 | N14: m² | O14: 25 | P14: =IF(ISBLANK(M14),"",M14*O14) -> 6750 | R14: 270 | S14: m² | T14: 25 | U14: =IF(ISBLANK(R14),"",R14*T14) -> 6750 | X14: m² | Z14: =IF(ISBLANK(W14),"",W14*Y14) | AC14: m² | AE14: =IF(ISBLANK(AB14),"",AB14*AD14) | AH14: m² | AJ14: =IF(ISBLANK(AG14),"",AG14*AI14) | AM14: m² | AO14: =IF(ISBLANK(AL14),"",AL14*AN14)
F15: =IF(ISBLANK(C15),"",C15*E15) | K15: =IF(ISBLANK(H15),"",H15*J15) | P15: =IF(ISBLANK(M15),"",M15*O15) | U15: =IF(ISBLANK(R15),"",R15*T15) | Z15: =IF(ISBLANK(W15),"",W15*Y15) | AE15: =IF(ISBLANK(AB15),"",AB15*AD15) | AJ15: =IF(ISBLANK(AG15),"",AG15*AI15) | AO15: =IF(ISBLANK(AL15),"",AL15*AN15)
A16: =IF(B16>0,IF(C16>0,MAX($A$5:A14)+1," ")," ") -> 5 | B16: Sand/cement screed to floors | C16: 270 | D16: m² | E16: 45 | F16: =IF(ISBLANK(C16),"",C16*E16) -> 12150 | H16: 270 | I16: m² | J16: 45 | K16: =IF(ISBLANK(H16),"",H16*J16) -> 12150 | M16: 270 | N16: m² | O16: 45 | P16: =IF(ISBLANK(M16),"",M16*O16) -> 12150 | R16: 270 | S16: m² | T16: 45 | U16: =IF(ISBLANK(R16),"",R16*T16) -> 12150 | X16: m² | Z16: =IF(ISBLANK(W16),"",W16*Y16) | AC16: m² | AE16: =IF(ISBLANK(AB16),"",AB16*AD16) | AH16: m² | AJ16: =IF(ISBLANK(AG16),"",AG16*AI16) | AM16: m² | AO16: =IF(ISBLANK(AL16),"",AL16*AN16)
F17: =IF(ISBLANK(C17),"",C17*E17) | K17: =IF(ISBLANK(H17),"",H17*J17) | P17: =IF(ISBLANK(M17),"",M17*O17) | U17: =IF(ISBLANK(R17),"",R17*T17) | Z17: =IF(ISBLANK(W17),"",W17*Y17) | AE17: =IF(ISBLANK(AB17),"",AB17*AD17) | AJ17: =IF(ISBLANK(AG17),"",AG17*AI17) | AO17: =IF(ISBLANK(AL17),"",AL17*AN17)
A18: =IF(B18>0,IF(C18>0,MAX($A$5:A16)+1," ")," ") -> 6 | B18: Proprietary flowing screed | C18: 270 | D18: m² | E18: 15 | F18: =IF(ISBLANK(C18),"",C18*E18) -> 4050 | H18: 270 | I18: m² | J18: 15 | K18: =IF(ISBLANK(H18),"",H18*J18) -> 4050 | M18: 270 | N18: m² | O18: 15 | P18: =IF(ISBLANK(M18),"",M18*O18) -> 4050 | R18: 270 | S18: m² | T18: 15 | U18: =IF(ISBLANK(R18),"",R18*T18) -> 4050 | X18: m² | Z18: =IF(ISBLANK(W18),"",W18*Y18) | AC18: m² | AE18: =IF(ISBLANK(AB18),"",AB18*AD18) | AH18: m² | AJ18: =IF(ISBLANK(AG18),"",AG18*AI18) | AM18: m² | AO18: =IF(ISBLANK(AL18),"",AL18*AN18)
F19: =IF(ISBLANK(C19),"",C19*E19) | K19: =IF(ISBLANK(H19),"",H19*J19) | P19: =IF(ISBLANK(M19),"",M19*O19) | U19: =IF(ISBLANK(R19),"",R19*T19) | Z19: =IF(ISBLANK(W19),"",W19*Y19) | AE19: =IF(ISBLANK(AB19),"",AB19*AD19) | AJ19: =IF(ISBLANK(AG19),"",AG19*AI19) | AO19: =IF(ISBLANK(AL19),"",AL19*AN19)
A20: =IF(B20>0,IF(C20>0,MAX($A$5:A19)+1," ")," ") -> 7 | B20: Rigid floor insulation | C20: 270 | D20: m² | E20: 25 | F20: =IF(ISBLANK(C20),"",C20*E20) -> 6750 | H20: 270 | I20: m² | J20: 25 | K20: =IF(ISBLANK(H20),"",H20*J20) -> 6750 | M20: 270 | N20: m² | O20: 25 | P20: =IF(ISBLANK(M20),"",M20*O20) -> 6750 | R20: 270 | S20: m² | T20: 25 | U20: =IF(ISBLANK(R20),"",R20*T20) -> 6750 | X20: m² | Z20: =IF(ISBLANK(W20),"",W20*Y20) | AC20: m² | AE20: =IF(ISBLANK(AB20),"",AB20*AD20) | AH20: m² | AJ20: =IF(ISBLANK(AG20),"",AG20*AI20) | AM20: m² | AO20: =IF(ISBLANK(AL20),"",AL20*AN20)
F21: =IF(ISBLANK(C21),"",C21*E21) | K21: =IF(ISBLANK(H21),"",H21*J21) | P21: =IF(ISBLANK(M21),"",M21*O21) | U21: =IF(ISBLANK(R21),"",R21*T21) | Z21: =IF(ISBLANK(W21),"",W21*Y21) | AE21: =IF(ISBLANK(AB21),"",AB21*AD21) | AJ21: =IF(ISBLANK(AG21),"",AG21*AI21) | AO21: =IF(ISBLANK(AL21),"",AL21*AN21)
A22: =IF(B22>0,IF(C22>0,MAX($A$5:A20)+1," ")," ") -> 8 | B22: Acoustic floor insulation | C22: 270 | D22: m² | E22: 10 | F22: =IF(ISBLANK(C22),"",C22*E22) -> 2700 | H22: 270 | I22: m² | J22: 10 | K22: =IF(ISBLANK(H22),"",H22*J22) -> 2700 | M22: 270 | N22: m² | O22: 10 | P22: =IF(ISBLANK(M22),"",M22*O22) -> 2700 | R22: 270 | S22: m² | T22: 10 | U22: =IF(ISBLANK(R22),"",R22*T22) -> 2700 | X22: m² | Z22: =IF(ISBLANK(W22),"",W22*Y22) | AC22: m² | AE22: =IF(ISBLANK(AB22),"",AB22*AD22) | AH22: m² | AJ22: =IF(ISBLANK(AG22),"",AG22*AI22) | AM22: m² | AO22: =IF(ISBLANK(AL22),"",AL22*AN22)
F23: =IF(ISBLANK(C23),"",C23*E23) | K23: =IF(ISBLANK(H23),"",H23*J23) | P23: =IF(ISBLANK(M23),"",M23*O23) | U23: =IF(ISBLANK(R23),"",R23*T23) | Z23: =IF(ISBLANK(W23),"",W23*Y23) | AE23: =IF(ISBLANK(AB23),"",AB23*AD23) | AJ23: =IF(ISBLANK(AG23),"",AG23*AI23) | AO23: =IF(ISBLANK(AL23),"",AL23*AN23)
A24: =IF(B24>0,IF(C24>0,MAX($A$5:A22)+1," ")," ") -> 9 | B24: Vapour control layers | C24: 280 | D24: m² | E24: 5 | F24: =IF(ISBLANK(C24),"",C24*E24) -> 1400 | H24: 280 | I24: m² | J24: 5 | K24: =IF(ISBLANK(H24),"",H24*J24) -> 1400 | M24: 280 | N24: m² | O24: 5 | P24: =IF(ISBLANK(M24),"",M24*O24) -> 1400 | R24: 280 | S24: m² | T24: 5 | U24: =IF(ISBLANK(R24),"",R24*T24) -> 1400 | X24: m² | Z24: =IF(ISBLANK(W24),"",W24*Y24) | AC24: m² | AE24: =IF(ISBLANK(AB24),"",AB24*AD24) | AH24: m² | AJ24: =IF(ISBLANK(AG24),"",AG24*AI24) | AM24: m² | AO24: =IF(ISBLANK(AL24),"",AL24*AN24)
F25: =IF(ISBLANK(C25),"",C25*E25) | K25: =IF(ISBLANK(H25),"",H25*J25) | P25: =IF(ISBLANK(M25),"",M25*O25) | U25: =IF(ISBLANK(R25),"",R25*T25) | Z25: =IF(ISBLANK(W25),"",W25*Y25) | AE25: =IF(ISBLANK(AB25),"",AB25*AD25) | AJ25: =IF(ISBLANK(AG25),"",AG25*AI25) | AO25: =IF(ISBLANK(AL25),"",AL25*AN25)
A26: =IF(B26>0,IF(C26>0,MAX($A$5:A24)+1," ")," ") -> 10 | B26: Self levelling compound | C26: 270 | D26: m² | E26: 13 | F26: =IF(ISBLANK(C26),"",C26*E26) -> 3510 | H26: 270 | I26: m² | J26: 13 | K26: =IF(ISBLANK(H26),"",H26*J26) -> 3510 | M26: 270 | N26: m² | O26: 13 | P26: =IF(ISBLANK(M26),"",M26*O26) -> 3510 | R26: 270 | S26: m² | T26: 13 | U26: =IF(ISBLANK(R26),"",R26*T26) -> 3510 | X26: m² | Z26: =IF(ISBLANK(W26),"",W26*Y26) | AC26: m² | AE26: =IF(ISBLANK(AB26),"",AB26*AD26) | AH26: m² | AJ26: =IF(ISBLANK(AG26),"",AG26*AI26) | AM26: m² | AO26: =IF(ISBLANK(AL26),"",AL26*AN26)
F27: =IF(ISBLANK(C27),"",C27*E27) | K27: =IF(ISBLANK(H27),"",H27*J27) | P27: =IF(ISBLANK(M27),"",M27*O27) | U27: =IF(ISBLANK(R27),"",R27*T27) | Z27: =IF(ISBLANK(W27),"",W27*Y27) | AE27: =IF(ISBLANK(AB27),"",AB27*AD27) | AJ27: =IF(ISBLANK(AG27),"",AG27*AI27) | AO27: =IF(ISBLANK(AL27),"",AL27*AN27)
A28: =IF(B28>0,IF(C28>0,MAX($A$5:A26)+1," ")," ") -> 11 | B28: Concrete upstands to slab edges | C28: 150 | D28: m | E28: 225 | F28: =IF(ISBLANK(C28),"",C28*E28) -> 33750 | H28: 150 | I28: m | J28: 225 | K28: =IF(ISBLANK(H28),"",H28*J28) -> 33750 | M28: 150 | N28: m | O28: 225 | P28: =IF(ISBLANK(M28),"",M28*O28) -> 33750 | R28: 150 | S28: m | T28: 225 | U28: =IF(ISBLANK(R28),"",R28*T28) -> 33750 | X28: m | Z28: =IF(ISBLANK(W28),"",W28*Y28) | AC28: m | AE28: =IF(ISBLANK(AB28),"",AB28*AD28) | AH28: m | AJ28: =IF(ISBLANK(AG28),"",AG28*AI28) | AM28: m | AO28: =IF(ISBLANK(AL28),"",AL28*AN28)
F29: =IF(ISBLANK(C29),"",C29*E29) | K29: =IF(ISBLANK(H29),"",H29*J29) | P29: =IF(ISBLANK(M29),"",M29*O29) | U29: =IF(ISBLANK(R29),"",R29*T29) | Z29: =IF(ISBLANK(W29),"",W29*Y29) | AE29: =IF(ISBLANK(AB29),"",AB29*AD29) | AJ29: =IF(ISBLANK(AG29),"",AG29*AI29) | AO29: =IF(ISBLANK(AL29),"",AL29*AN29)
A30: =IF(B30>0,IF(C30>0,MAX($A$5:A28)+1," ")," ") -> 12 | B30: Metal edge trims | C30: 25 | D30: m | E30: 15 | F30: =IF(ISBLANK(C30),"",C30*E30) -> 375 | H30: 25 | I30: m | J30: 15 | K30: =IF(ISBLANK(H30),"",H30*J30) -> 375 | M30: 25 | N30: m | O30: 15 | P30: =IF(ISBLANK(M30),"",M30*O30) -> 375 | R30: 25 | S30: m | T30: 15 | U30: =IF(ISBLANK(R30),"",R30*T30) -> 375 | X30: m | Z30: =IF(ISBLANK(W30),"",W30*Y30) | AC30: m | AE30: =IF(ISBLANK(AB30),"",AB30*AD30) | AH30: m | AJ30: =IF(ISBLANK(AG30),"",AG30*AI30) | AM30: m | AO30: =IF(ISBLANK(AL30),"",AL30*AN30)
F31: =IF(ISBLANK(C31),"",C31*E31) | K31: =IF(ISBLANK(H31),"",H31*J31) | P31: =IF(ISBLANK(M31),"",M31*O31) | U31: =IF(ISBLANK(R31),"",R31*T31) | Z31: =IF(ISBLANK(W31),"",W31*Y31) | AE31: =IF(ISBLANK(AB31),"",AB31*AD31) | AJ31: =IF(ISBLANK(AG31),"",AG31*AI31) | AO31: =IF(ISBLANK(AL31),"",AL31*AN31)
A32: =IF(B32>0,IF(C32>0,MAX($A$5:A30)+1," ")," ") -> 13 | B32: Movement joints in floor slab | C32: 50 | D32: m | E32: 25 | F32: =IF(ISBLANK(C32),"",C32*E32) -> 1250 | H32: 50 | I32: m | J32: 25 | K32: =IF(ISBLANK(H32),"",H32*J32) -> 1250 | M32: 50 | N32: m | O32: 25 | P32: =IF(ISBLANK(M32),"",M32*O32) -> 1250 | R32: 50 | S32: m | T32: 25 | U32: =IF(ISBLANK(R32),"",R32*T32) -> 1250 | X32: m | Z32: =IF(ISBLANK(W32),"",W32*Y32) | AC32: m | AE32: =IF(ISBLANK(AB32),"",AB32*AD32) | AH32: m | AJ32: =IF(ISBLANK(AG32),"",AG32*AI32) | AM32: m | AO32: =IF(ISBLANK(AL32),"",AL32*AN32)
F33: =IF(ISBLANK(C33),"",C33*E33) | K33: =IF(ISBLANK(H33),"",H33*J33) | P33: =IF(ISBLANK(M33),"",M33*O33) | U33: =IF(ISBLANK(R33),"",R33*T33) | Z33: =IF(ISBLANK(W33),"",W33*Y33) | AE33: =IF(ISBLANK(AB33),"",AB33*AD33) | AJ33: =IF(ISBLANK(AG33),"",AG33*AI33) | AO33: =IF(ISBLANK(AL33),"",AL33*AN33)
A34: =IF(B34>0,IF(C34>0,MAX($A$5:A32)+1," ")," ") -> 14 | B34: Structural trimming around floor openings | C34: 1 | D34: item | E34: 500 | F34: =IF(ISBLANK(C34),"",C34*E34) -> 500 | H34: 1 | I34: item | J34: 500 | K34: =IF(ISBLANK(H34),"",H34*J34) -> 500 | M34: 1 | N34: item | O34: 500 | P34: =IF(ISBLANK(M34),"",M34*O34) -> 500 | R34: 1 | S34: item | T34: 500 | U34: =IF(ISBLANK(R34),"",R34*T34) -> 500 | X34: item | Z34: =IF(ISBLANK(W34),"",W34*Y34) | AC34: item | AE34: =IF(ISBLANK(AB34),"",AB34*AD34) | AH34: item | AJ34: =IF(ISBLANK(AG34),"",AG34*AI34) | AM34: item | AO34: =IF(ISBLANK(AL34),"",AL34*AN34)
F35: =IF(ISBLANK(C35),"",C35*E35) | K35: =IF(ISBLANK(H35),"",H35*J35) | P35: =IF(ISBLANK(M35),"",M35*O35) | U35: =IF(ISBLANK(R35),"",R35*T35) | Z35: =IF(ISBLANK(W35),"",W35*Y35) | AE35: =IF(ISBLANK(AB35),"",AB35*AD35) | AJ35: =IF(ISBLANK(AG35),"",AG35*AI35) | AO35: =IF(ISBLANK(AL35),"",AL35*AN35)
A36: =IF(B36>0,IF(C36>0,MAX($A$5:A34)+1," ")," ") -> 15 | B36: Allowance for service penetrations through floors | C36: 6 | D36: nr | E36: 200 | F36: =IF(ISBLANK(C36),"",C36*E36) -> 1200 | H36: 6 | I36: nr | J36: 200 | K36: =IF(ISBLANK(H36),"",H36*J36) -> 1200 | M36: 6 | N36: nr | O36: 200 | P36: =IF(ISBLANK(M36),"",M36*O36) -> 1200 | R36: 6 | S36: nr | T36: 200 | U36: =IF(ISBLANK(R36),"",R36*T36) -> 1200 | X36: nr | Z36: =IF(ISBLANK(W36),"",W36*Y36) | AC36: nr | AE36: =IF(ISBLANK(AB36),"",AB36*AD36) | AH36: nr | AJ36: =IF(ISBLANK(AG36),"",AG36*AI36) | AM36: nr | AO36: =IF(ISBLANK(AL36),"",AL36*AN36)
F37: =IF(ISBLANK(C37),"",C37*E37) | K37: =IF(ISBLANK(H37),"",H37*J37) | P37: =IF(ISBLANK(M37),"",M37*O37) | U37: =IF(ISBLANK(R37),"",R37*T37) | Z37: =IF(ISBLANK(W37),"",W37*Y37) | AE37: =IF(ISBLANK(AB37),"",AB37*AD37) | AJ37: =IF(ISBLANK(AG37),"",AG37*AI37) | AO37: =IF(ISBLANK(AL37),"",AL37*AN37)
A38: =IF(B38>0,IF(C38>0,MAX($A$5:A36)+1," ")," ") -> 16 | B38: Structural balcony slabs | C38: 10 | D38: m² | E38: 350 | F38: =IF(ISBLANK(C38),"",C38*E38) -> 3500 | H38: 10 | I38: m² | J38: 350 | K38: =IF(ISBLANK(H38),"",H38*J38) -> 3500 | M38: 10 | N38: m² | O38: 350 | P38: =IF(ISBLANK(M38),"",M38*O38) -> 3500 | R38: 10 | S38: m² | T38: 350 | U38: =IF(ISBLANK(R38),"",R38*T38) -> 3500 | X38: m² | Z38: =IF(ISBLANK(W38),"",W38*Y38) | AC38: m² | AE38: =IF(ISBLANK(AB38),"",AB38*AD38) | AH38: m² | AJ38: =IF(ISBLANK(AG38),"",AG38*AI38) | AM38: m² | AO38: =IF(ISBLANK(AL38),"",AL38*AN38)
F39: =IF(ISBLANK(C39),"",C39*E39) | K39: =IF(ISBLANK(H39),"",H39*J39) | P39: =IF(ISBLANK(M39),"",M39*O39) | U39: =IF(ISBLANK(R39),"",R39*T39) | Z39: =IF(ISBLANK(W39),"",W39*Y39) | AE39: =IF(ISBLANK(AB39),"",AB39*AD39) | AJ39: =IF(ISBLANK(AG39),"",AG39*AI39) | AO39: =IF(ISBLANK(AL39),"",AL39*AN39)
A40: =IF(B40>0,IF(C40>0,MAX($A$5:A38)+1," ")," ") -> 17 | B40: Balcony waterproofing systems | C40: 10 | D40: m² | E40: 100 | F40: =IF(ISBLANK(C40),"",C40*E40) -> 1000 | H40: 10 | I40: m² | J40: 100 | K40: =IF(ISBLANK(H40),"",H40*J40) -> 1000 | M40: 10 | N40: m² | O40: 100 | P40: =IF(ISBLANK(M40),"",M40*O40) -> 1000 | R40: 10 | S40: m² | T40: 100 | U40: =IF(ISBLANK(R40),"",R40*T40) -> 1000 | X40: m² | Z40: =IF(ISBLANK(W40),"",W40*Y40) | AC40: m² | AE40: =IF(ISBLANK(AB40),"",AB40*AD40) | AH40: m² | AJ40: =IF(ISBLANK(AG40),"",AG40*AI40) | AM40: m² | AO40: =IF(ISBLANK(AL40),"",AL40*AN40)
F41: =IF(ISBLANK(C41),"",C41*E41) | K41: =IF(ISBLANK(H41),"",H41*J41) | P41: =IF(ISBLANK(M41),"",M41*O41) | U41: =IF(ISBLANK(R41),"",R41*T41) | Z41: =IF(ISBLANK(W41),"",W41*Y41) | AE41: =IF(ISBLANK(AB41),"",AB41*AD41) | AJ41: =IF(ISBLANK(AG41),"",AG41*AI41) | AO41: =IF(ISBLANK(AL41),"",AL41*AN41)
A42: =IF(B42>0,IF(C42>0,MAX($A$5:A40)+1," ")," ") -> 18 | B42: Balcony surface finishes | C42: 10 | D42: m² | E42: 65 | F42: =IF(ISBLANK(C42),"",C42*E42) -> 650 | H42: 10 | I42: m² | J42: 65 | K42: =IF(ISBLANK(H42),"",H42*J42) -> 650 | M42: 10 | N42: m² | O42: 65 | P42: =IF(ISBLANK(M42),"",M42*O42) -> 650 | R42: 10 | S42: m² | T42: 65 | U42: =IF(ISBLANK(R42),"",R42*T42) -> 650 | X42: m² | Z42: =IF(ISBLANK(W42),"",W42*Y42) | AC42: m² | AE42: =IF(ISBLANK(AB42),"",AB42*AD42) | AH42: m² | AJ42: =IF(ISBLANK(AG42),"",AG42*AI42) | AM42: m² | AO42: =IF(ISBLANK(AL42),"",AL42*AN42)
F43: =IF(ISBLANK(C43),"",C43*E43) | K43: =IF(ISBLANK(H43),"",H43*J43) | P43: =IF(ISBLANK(M43),"",M43*O43) | U43: =IF(ISBLANK(R43),"",R43*T43) | Z43: =IF(ISBLANK(W43),"",W43*Y43) | AE43: =IF(ISBLANK(AB43),"",AB43*AD43) | AJ43: =IF(ISBLANK(AG43),"",AG43*AI43) | AO43: =IF(ISBLANK(AL43),"",AL43*AN43)
A44: =IF(B44>0,IF(C44>0,MAX($A$5:A42)+1," ")," ") -> 19 | B44: Fire stopping to floor penetrations | C44: 6 | D44: nr | E44: 200 | F44: =IF(ISBLANK(C44),"",C44*E44) -> 1200 | H44: 6 | I44: nr | J44: 200 | K44: =IF(ISBLANK(H44),"",H44*J44) -> 1200 | M44: 6 | N44: nr | O44: 200 | P44: =IF(ISBLANK(M44),"",M44*O44) -> 1200 | R44: 6 | S44: nr | T44: 200 | U44: =IF(ISBLANK(R44),"",R44*T44) -> 1200 | X44: nr | Z44: =IF(ISBLANK(W44),"",W44*Y44) | AC44: nr | AE44: =IF(ISBLANK(AB44),"",AB44*AD44) | AH44: nr | AJ44: =IF(ISBLANK(AG44),"",AG44*AI44) | AM44: nr | AO44: =IF(ISBLANK(AL44),"",AL44*AN44)
F45: =IF(ISBLANK(C45),"",C45*E45) | K45: =IF(ISBLANK(H45),"",H45*J45) | P45: =IF(ISBLANK(M45),"",M45*O45) | U45: =IF(ISBLANK(R45),"",R45*T45) | Z45: =IF(ISBLANK(W45),"",W45*Y45) | AE45: =IF(ISBLANK(AB45),"",AB45*AD45) | AJ45: =IF(ISBLANK(AG45),"",AG45*AI45) | AO45: =IF(ISBLANK(AL45),"",AL45*AN45)
A46: =IF(B46>0,IF(C46>0,MAX($A$5:A44)+1," ")," ") -> 20 | B46: Testing and inspection of floor construction | C46: 1 | D46: item | E46: 1000 | F46: =IF(ISBLANK(C46),"",C46*E46) -> 1000 | H46: 1 | I46: item | J46: 1000 | K46: =IF(ISBLANK(H46),"",H46*J46) -> 1000 | M46: 1 | N46: item | O46: 1000 | P46: =IF(ISBLANK(M46),"",M46*O46) -> 1000 | R46: 1 | S46: item | T46: 1000 | U46: =IF(ISBLANK(R46),"",R46*T46) -> 1000 | X46: item | Z46: =IF(ISBLANK(W46),"",W46*Y46) | AC46: item | AE46: =IF(ISBLANK(AB46),"",AB46*AD46) | AH46: item | AJ46: =IF(ISBLANK(AG46),"",AG46*AI46) | AM46: item | AO46: =IF(ISBLANK(AL46),"",AL46*AN46)
A47: =IF(B47>0,IF(C47>0,MAX($A$5:A46)+1," ")," ") | F47: =IF(ISBLANK(C47),"",C47*E47) | K47: =IF(ISBLANK(H47),"",H47*J47) | P47: =IF(ISBLANK(M47),"",M47*O47) | U47: =IF(ISBLANK(R47),"",R47*T47) | Z47: =IF(ISBLANK(W47),"",W47*Y47) | AE47: =IF(ISBLANK(AB47),"",AB47*AD47) | AJ47: =IF(ISBLANK(AG47),"",AG47*AI47) | AO47: =IF(ISBLANK(AL47),"",AL47*AN47)
A48: =IF(B48>0,IF(C48>0,MAX($A$5:A47)+1," ")," ") | B48: Any other works (contractor to specify) | F48: =IF(ISBLANK(C48),"",C48*E48) | K48: =IF(ISBLANK(H48),"",H48*J48) | P48: =IF(ISBLANK(M48),"",M48*O48) | U48: =IF(ISBLANK(R48),"",R48*T48) | Z48: =IF(ISBLANK(W48),"",W48*Y48) | AE48: =IF(ISBLANK(AB48),"",AB48*AD48) | AJ48: =IF(ISBLANK(AG48),"",AG48*AI48) | AO48: =IF(ISBLANK(AL48),"",AL48*AN48)
A49: =IF(B49>0,IF(C49>0,MAX($A$5:A48)+1," ")," ") -> 21 | B49: ……………………………………………. | C49: 1 | D49: item | F49: =IF(ISBLANK(C49),"",C49*E49) -> 0 | H49: 1 | I49: item | K49: =IF(ISBLANK(H49),"",H49*J49) -> 0 | M49: 1 | N49: item | P49: =IF(ISBLANK(M49),"",M49*O49) -> 0 | R49: 1 | S49: item | U49: =IF(ISBLANK(R49),"",R49*T49) -> 0 | W49: 1 | X49: item | Z49: =IF(ISBLANK(W49),"",W49*Y49) -> 0 | AB49: 1 | AC49: item | AE49: =IF(ISBLANK(AB49),"",AB49*AD49) -> 0 | AG49: 1 | AH49: item | AJ49: =IF(ISBLANK(AG49),"",AG49*AI49) -> 0 | AL49: 1 | AM49: item | AO49: =IF(ISBLANK(AL49),"",AL49*AN49) -> 0
A50: =IF(B50>0,IF(C50>0,MAX($A$5:A49)+1," ")," ") -> 22 | B50: ……………………………………………. | C50: 1 | D50: Item | F50: =IF(ISBLANK(C50),"",C50*E50) -> 0 | H50: 1 | I50: Item | K50: =IF(ISBLANK(H50),"",H50*J50) -> 0 | M50: 1 | N50: Item | P50: =IF(ISBLANK(M50),"",M50*O50) -> 0 | R50: 1 | S50: Item | U50: =IF(ISBLANK(R50),"",R50*T50) -> 0 | W50: 1 | X50: Item | Z50: =IF(ISBLANK(W50),"",W50*Y50) -> 0 | AB50: 1 | AC50: Item | AE50: =IF(ISBLANK(AB50),"",AB50*AD50) -> 0 | AG50: 1 | AH50: Item | AJ50: =IF(ISBLANK(AG50),"",AG50*AI50) -> 0 | AL50: 1 | AM50: Item | AO50: =IF(ISBLANK(AL50),"",AL50*AN50) -> 0
A51: =IF(B51>0,IF(C51>0,MAX($A$5:A50)+1," ")," ") -> 23 | B51: ……………………………………………. | C51: 1 | D51: Item | F51: =IF(ISBLANK(C51),"",C51*E51) -> 0 | H51: 1 | I51: Item | K51: =IF(ISBLANK(H51),"",H51*J51) -> 0 | M51: 1 | N51: Item | P51: =IF(ISBLANK(M51),"",M51*O51) -> 0 | R51: 1 | S51: Item | U51: =IF(ISBLANK(R51),"",R51*T51) -> 0 | W51: 1 | X51: Item | Z51: =IF(ISBLANK(W51),"",W51*Y51) -> 0 | AB51: 1 | AC51: Item | AE51: =IF(ISBLANK(AB51),"",AB51*AD51) -> 0 | AG51: 1 | AH51: Item | AJ51: =IF(ISBLANK(AG51),"",AG51*AI51) -> 0 | AL51: 1 | AM51: Item | AO51: =IF(ISBLANK(AL51),"",AL51*AN51) -> 0
A52: =IF(B52>0,IF(C52>0,MAX($A$5:A51)+1," ")," ") -> 24 | B52: ……………………………………………. | C52: 1 | D52: Item | F52: =IF(ISBLANK(C52),"",C52*E52) -> 0 | H52: 1 | I52: Item | K52: =IF(ISBLANK(H52),"",H52*J52) -> 0 | M52: 1 | N52: Item | P52: =IF(ISBLANK(M52),"",M52*O52) -> 0 | R52: 1 | S52: Item | U52: =IF(ISBLANK(R52),"",R52*T52) -> 0 | W52: 1 | X52: Item | Z52: =IF(ISBLANK(W52),"",W52*Y52) -> 0 | AB52: 1 | AC52: Item | AE52: =IF(ISBLANK(AB52),"",AB52*AD52) -> 0 | AG52: 1 | AH52: Item | AJ52: =IF(ISBLANK(AG52),"",AG52*AI52) -> 0 | AL52: 1 | AM52: Item | AO52: =IF(ISBLANK(AL52),"",AL52*AN52) -> 0
A53: =IF(B53>0,IF(C53>0,MAX($A$3:A47)+1," ")," ") | F53: =IF(ISBLANK(C53),"",C53*E53) | K53: =IF(ISBLANK(H53),"",H53*J53) | P53: =IF(ISBLANK(M53),"",M53*O53) | U53: =IF(ISBLANK(R53),"",R53*T53) | Z53: =IF(ISBLANK(W53),"",W53*Y53) | AE53: =IF(ISBLANK(AB53),"",AB53*AD53) | AJ53: =IF(ISBLANK(AG53),"",AG53*AI53) | AO53: =IF(ISBLANK(AL53),"",AL53*AN53)
E54: Total | F54: =SUM(F5:F53) -> 360235 | J54: Total | K54: =SUM(K5:K53) -> 360235 | O54: Total | P54: =SUM(P5:P53) -> 360235 | T54: Total | U54: =SUM(U5:U53) -> 360235 | Y54: Total | Z54: =SUM(Z5:Z53) -> 0 | AD54: Total | AE54: =SUM(AE5:AE53) -> 0 | AI54: Total | AJ54: =SUM(AJ5:AJ53) -> 0 | AN54: Total | AO54: =SUM(AO5:AO53) -> 0

Sheet 2.3 Roof
B1: Return to ELEMENT INDEX
B2: Return to SUMMARY
C3: =SUMMARY!E3 -> Sample Cost Plan - Elm Court Residential, Rev 01 | H3: =SUMMARY!K3 -> Ridgeway Construction | M3: =SUMMARY!N3 -> Brightstone Builders | R3: =SUMMARY!Q3 -> Kestrel Contractors | W3: =SUMMARY!T3 -> INSERT CONTRACTOR 4 | AB3: =SUMMARY!W3 -> INSERT CONTRACTOR 5 | AG3: =SUMMARY!Z3 -> INSERT CONTRACTOR 6 | AL3: =SUMMARY!AC3 -> INSERT CONTRACTOR 7
B4: {=MID(CELL("filename",A3),FIND("]",CELL("filename",A3))+1,255)} -> 2.3 Roof | C4: Qty | D4: Unit | E4: Rate | F4: Total | H4: Qty | I4: Unit | J4: Rate | K4: Total | M4: Qty | N4: Unit | O4: Rate | P4: Total | R4: Qty | S4: Unit | T4: Rate | U4: Total | W4: Qty | X4: Unit | Y4: Rate | Z4: Total | AB4: Qty | AC4: Unit | AD4: Rate | AE4: Total | AG4: Qty | AH4: Unit | AI4: Rate | AJ4: Total | AL4: Qty | AM4: Unit | AN4: Rate | AO4: Total
A5: =IF(B5>0,IF(C5>0,MAX($A$3:A4)+1," ")," ") | F5: =IF(ISBLANK(C5),"",C5*E5) | K5: =IF(ISBLANK(H5),"",H5*J5) | P5: =IF(ISBLANK(M5),"",M5*O5) | U5: =IF(ISBLANK(R5),"",R5*T5) | Z5: =IF(ISBLANK(W5),"",W5*Y5) | AE5: =IF(ISBLANK(AB5),"",AB5*AD5) | AJ5: =IF(ISBLANK(AG5),"",AG5*AI5) | AO5: =IF(ISBLANK(AL5),"",AL5*AN5)
A6: =IF(B6>0,IF(C6>0,MAX($A$5:A5)+1," ")," ") | B6: Roof Structure
A8: =IF(B8>0,IF(C8>0,MAX($A$5:A7)+1," ")," ") -> 1 | B8: Allowance for reinforced concrete roof slab; insulation and coverings elsewhere | C8: 250 | D8: m2 | E8: 10 | F8: =IF(ISBLANK(C8),"",C8*E8) -> 2500 | H8: 250 | I8: m2 | J8: 10 | K8: =IF(ISBLANK(H8),"",H8*J8) -> 2500 | M8: 250 | N8: m2 | O8: 10 | P8: =IF(ISBLANK(M8),"",M8*O8) -> 2500 | R8: 250 | S8: m2 | T8: 10 | U8: =IF(ISBLANK(R8),"",R8*T8) -> 2500 | X8: m2 | Y8: =IF(ISBLANK(V8),"",V8*X8) | AC8: m2 | AD8: =IF(ISBLANK(AA8),"",AA8*AC8) | AH8: m2 | AI8: =IF(ISBLANK(AF8),"",AF8*AH8) | AM8: m2 | AN8: =IF(ISBLANK(AK8),"",AK8*AM8)
Y9: =IF(ISBLANK(V9),"",V9*X9) | AD9: =IF(ISBLANK(AA9),"",AA9*AC9) | AI9: =IF(ISBLANK(AF9),"",AF9*AH9) | AN9: =IF(ISBLANK(AK9),"",AK9*AM9)
A10: =IF(B10>0,IF(C10>0,MAX($A$5:A9)+1," ")," ") -> 2 | B10: Nominal allowance for sundry upstands ec | C10: 250 | D10: m2 | E10: 10 | F10: =IF(ISBLANK(C10),"",C10*E10) -> 2500 | H10: 250 | I10: m2 | J10: 10 | K10: =IF(ISBLANK(H10),"",H10*J10) -> 2500 | M10: 250 | N10: m2 | O10: 10 | P10: =IF(ISBLANK(M10),"",M10*O10) -> 2500 | R10: 250 | S10: m2 | T10: 10 | U10: =IF(ISBLANK(R10),"",R10*T10) -> 2500 | X10: m2 | Y10: =IF(ISBLANK(V10),"",V10*X10) | AC10: m2 | AD10: =IF(ISBLANK(AA10),"",AA10*AC10) | AH10: m2 | AI10: =IF(ISBLANK(AF10),"",AF10*AH10) | AM10: m2 | AN10: =IF(ISBLANK(AK10),"",AK10*AM10)
A11: =IF(B11>0,IF(C11>0,MAX($A$5:A10)+1," ")," ") | Y11: =IF(ISBLANK(V11),"",V11*X11) | AD11: =IF(ISBLANK(AA11),"",AA11*AC11) | AI11: =IF(ISBLANK(AF11),"",AF11*AH11) | AN11: =IF(ISBLANK(AK11),"",AK11*AM11)
A12: =IF(B12>0,IF(C12>0,MAX($A$5:A11)+1," ")," ") -> 3 | B12: Supply and Installation of Roof Structure | C12: 250 | D12: m2 | E12: 10 | F12: =IF(ISBLANK(C12),"",C12*E12) -> 2500 | H12: 250 | I12: m2 | J12: 10 | K12: =IF(ISBLANK(H12),"",H12*J12) -> 2500 | M12: 250 | N12: m2 | O12: 10 | P12: =IF(ISBLANK(M12),"",M12*O12) -> 2500 | R12: 250 | S12: m2 | T12: 10 | U12: =IF(ISBLANK(R12),"",R12*T12) -> 2500 | X12: m2 | Y12: =IF(ISBLANK(V12),"",V12*X12) | AC12: m2 | AD12: =IF(ISBLANK(AA12),"",AA12*AC12) | AH12: m2 | AI12: =IF(ISBLANK(AF12),"",AF12*AH12) | AM12: m2 | AN12: =IF(ISBLANK(AK12),"",AK12*AM12)
Y13: =IF(ISBLANK(V13),"",V13*X13) | AD13: =IF(ISBLANK(AA13),"",AA13*AC13) | AI13: =IF(ISBLANK(AF13),"",AF13*AH13) | AN13: =IF(ISBLANK(AK13),"",AK13*AM13)
A14: =IF(B14>0,IF(C14>0,MAX($A$5:A12)+1," ")," ") -> 4 | B14: Sundry allowances | C14: 250 | D14: item | E14: 10 | F14: =IF(ISBLANK(C14),"",C14*E14) -> 2500 | H14: 250 | I14: item | J14: 10 | K14: =IF(ISBLANK(H14),"",H14*J14) -> 2500 | M14: 250 | N14: item | O14: 10 | P14: =IF(ISBLANK(M14),"",M14*O14) -> 2500 | R14: 250 | S14: item | T14: 10 | U14: =IF(ISBLANK(R14),"",R14*T14) -> 2500 | X14: item | Y14: =IF(ISBLANK(V14),"",V14*X14) | AC14: item | AD14: =IF(ISBLANK(AA14),"",AA14*AC14) | AH14: item | AI14: =IF(ISBLANK(AF14),"",AF14*AH14) | AM14: item | AN14: =IF(ISBLANK(AK14),"",AK14*AM14)
A15: =IF(B15>0,IF(C15>0,MAX($A$5:A14)+1," ")," ") | Y15: =IF(ISBLANK(V15),"",V15*X15) | AD15: =IF(ISBLANK(AA15),"",AA15*AC15) | AI15: =IF(ISBLANK(AF15),"",AF15*AH15) | AN15: =IF(ISBLANK(AK15),"",AK15*AM15)
A16: =IF(B16>0,IF(C16>0,MAX($A$5:A15)+1," ")," ") -> 5 | B16: Underlay | C16: 250 | D16: m2 | E16: 10 | F16: =IF(ISBLANK(C16),"",C16*E16) -> 2500 | H16: 250 | I16: m2 | J16: 10 | K16: =IF(ISBLANK(H16),"",H16*J16) -> 2500 | M16: 250 | N16: m2 | O16: 10 | P16: =IF(ISBLANK(M16),"",M16*O16) -> 2500 | R16: 250 | S16: m2 | T16: 10 | U16: =IF(ISBLANK(R16),"",R16*T16) -> 2500 | X16: m2 | Y16: =IF(ISBLANK(V16),"",V16*X16) | AC16: m2 | AD16: =IF(ISBLANK(AA16),"",AA16*AC16) | AH16: m2 | AI16: =IF(ISBLANK(AF16),"",AF16*AH16) | AM16: m2 | AN16: =IF(ISBLANK(AK16),"",AK16*AM16)
Y17: =IF(ISBLANK(V17),"",V17*X17) | AD17: =IF(ISBLANK(AA17),"",AA17*AC17) | AI17: =IF(ISBLANK(AF17),"",AF17*AH17) | AN17: =IF(ISBLANK(AK17),"",AK17*AM17)
A18: =IF(B18>0,IF(C18>0,MAX($A$5:A16)+1," ")," ") -> 6 | B18: Battens | C18: 250 | D18: m2 | E18: 10 | F18: =IF(ISBLANK(C18),"",C18*E18) -> 2500 | H18: 250 | I18: m2 | J18: 10 | K18: =IF(ISBLANK(H18),"",H18*J18) -> 2500 | M18: 250 | N18: m2 | O18: 10 | P18: =IF(ISBLANK(M18),"",M18*O18) -> 2500 | R18: 250 | S18: m2 | T18: 10 | U18: =IF(ISBLANK(R18),"",R18*T18) -> 2500 | X18: m2 | Y18: =IF(ISBLANK(V18),"",V18*X18) | AC18: m2 | AD18: =IF(ISBLANK(AA18),"",AA18*AC18) | AH18: m2 | AI18: =IF(ISBLANK(AF18),"",AF18*AH18) | AM18: m2 | AN18: =IF(ISBLANK(AK18),"",AK18*AM18)
Y19: =IF(ISBLANK(V19),"",V19*X19) | AD19: =IF(ISBLANK(AA19),"",AA19*AC19) | AI19: =IF(ISBLANK(AF19),"",AF19*AH19) | AN19: =IF(ISBLANK(AK19),"",AK19*AM19)
A20: =IF(B20>0,IF(C20>0,MAX($A$5:A18)+1," ")," ") -> 7 | B20: Roof Tiles | C20: 250 | D20: m2 | E20: 10 | F20: =IF(ISBLANK(C20),"",C20*E20) -> 2500 | H20: 250 | I20: m2 | J20: 10 | K20: =IF(ISBLANK(H20),"",H20*J20) -> 2500 | M20: 250 | N20: m2 | O20: 10 | P20: =IF(ISBLANK(M20),"",M20*O20) -> 2500 | R20: 250 | S20: m2 | T20: 10 | U20: =IF(ISBLANK(R20),"",R20*T20) -> 2500 | X20: m2 | Y20: =IF(ISBLANK(V20),"",V20*X20) | AC20: m2 | AD20: =IF(ISBLANK(AA20),"",AA20*AC20) | AH20: m2 | AI20: =IF(ISBLANK(AF20),"",AF20*AH20) | AM20: m2 | AN20: =IF(ISBLANK(AK20),"",AK20*AM20)
A21: =IF(B21>0,IF(C21>0,MAX($A$5:A20)+1," ")," ") | Y21: =IF(ISBLANK(V21),"",V21*X21) | AD21: =IF(ISBLANK(AA21),"",AA21*AC21) | AI21: =IF(ISBLANK(AF21),"",AF21*AH21) | AN21: =IF(ISBLANK(AK21),"",AK21*AM21)
A22: =IF(B22>0,IF(C22>0,MAX($A$5:A21)+1," ")," ") -> 8 | B22: Supply and Installation of Roof Structure | C22: 250 | D22: m2 | E22: 10 | F22: =IF(ISBLANK(C22),"",C22*E22) -> 2500 | H22: 250 | I22: m2 | J22: 10 | K22: =IF(ISBLANK(H22),"",H22*J22) -> 2500 | M22: 250 | N22: m2 | O22: 10 | P22: =IF(ISBLANK(M22),"",M22*O22) -> 2500 | R22: 250 | S22: m2 | T22: 10 | U22: =IF(ISBLANK(R22),"",R22*T22) -> 2500 | X22: m2 | Y22: =IF(ISBLANK(V22),"",V22*X22) | AC22: m2 | AD22: =IF(ISBLANK(AA22),"",AA22*AC22) | AH22: m2 | AI22: =IF(ISBLANK(AF22),"",AF22*AH22) | AM22: m2 | AN22: =IF(ISBLANK(AK22),"",AK22*AM22)
Y23: =IF(ISBLANK(V23),"",V23*X23) | AD23: =IF(ISBLANK(AA23),"",AA23*AC23) | AI23: =IF(ISBLANK(AF23),"",AF23*AH23) | AN23: =IF(ISBLANK(AK23),"",AK23*AM23)
A24: =IF(B24>0,IF(C24>0,MAX($A$5:A22)+1," ")," ") -> 9 | B24: Sundry allowances | C24: 250 | D24: item | E24: 10 | F24: =IF(ISBLANK(C24),"",C24*E24) -> 2500 | H24: 250 | I24: item | J24: 10 | K24: =IF(ISBLANK(H24),"",H24*J24) -> 2500 | M24: 250 | N24: item | O24: 10 | P24: =IF(ISBLANK(M24),"",M24*O24) -> 2500 | R24: 250 | S24: item | T24: 10 | U24: =IF(ISBLANK(R24),"",R24*T24) -> 2500 | X24: item | Y24: =IF(ISBLANK(V24),"",V24*X24) | AC24: item | AD24: =IF(ISBLANK(AA24),"",AA24*AC24) | AH24: item | AI24: =IF(ISBLANK(AF24),"",AF24*AH24) | AM24: item | AN24: =IF(ISBLANK(AK24),"",AK24*AM24)
A25: =IF(B25>0,IF(C25>0,MAX($A$5:A24)+1," ")," ") | Y25: =IF(ISBLANK(V25),"",V25*X25) | AD25: =IF(ISBLANK(AA25),"",AA25*AC25) | AI25: =IF(ISBLANK(AF25),"",AF25*AH25) | AN25: =IF(ISBLANK(AK25),"",AK25*AM25)
A26: =IF(B26>0,IF(C26>0,MAX($A$5:A25)+1," ")," ") -> 10 | B26: Underlay | C26: 250 | D26: m2 | E26: 10 | F26: =IF(ISBLANK(C26),"",C26*E26) -> 2500 | H26: 250 | I26: m2 | J26: 10 | K26: =IF(ISBLANK(H26),"",H26*J26) -> 2500 | M26: 250 | N26: m2 | O26: 10 | P26: =IF(ISBLANK(M26),"",M26*O26) -> 2500 | R26: 250 | S26: m2 | T26: 10 | U26: =IF(ISBLANK(R26),"",R26*T26) -> 2500 | X26: m2 | Y26: =IF(ISBLANK(V26),"",V26*X26) | AC26: m2 | AD26: =IF(ISBLANK(AA26),"",AA26*AC26) | AH26: m2 | AI26: =IF(ISBLANK(AF26),"",AF26*AH26) | AM26: m2 | AN26: =IF(ISBLANK(AK26),"",AK26*AM26)
Y27: =IF(ISBLANK(V27),"",V27*X27) | AD27: =IF(ISBLANK(AA27),"",AA27*AC27) | AI27: =IF(ISBLANK(AF27),"",AF27*AH27) | AN27: =IF(ISBLANK(AK27),"",AK27*AM27)
A28: =IF(B28>0,IF(C28>0,MAX($A$5:A26)+1," ")," ") -> 11 | B28: Battens | C28: 250 | D28: m2 | E28: 10 | F28: =IF(ISBLANK(C28),"",C28*E28) -> 2500 | H28: 250 | I28: m2 | J28: 10 | K28: =IF(ISBLANK(H28),"",H28*J28) -> 2500 | M28: 250 | N28: m2 | O28: 10 | P28: =IF(ISBLANK(M28),"",M28*O28) -> 2500 | R28: 250 | S28: m2 | T28: 10 | U28: =IF(ISBLANK(R28),"",R28*T28) -> 2500 | X28: m2 | Y28: =IF(ISBLANK(V28),"",V28*X28) | AC28: m2 | AD28: =IF(ISBLANK(AA28),"",AA28*AC28) | AH28: m2 | AI28: =IF(ISBLANK(AF28),"",AF28*AH28) | AM28: m2 | AN28: =IF(ISBLANK(AK28),"",AK28*AM28)
Y29: =IF(ISBLANK(V29),"",V29*X29) | AD29: =IF(ISBLANK(AA29),"",AA29*AC29) | AI29: =IF(ISBLANK(AF29),"",AF29*AH29) | AN29: =IF(ISBLANK(AK29),"",AK29*AM29)
A30: =IF(B30>0,IF(C30>0,MAX($A$5:A28)+1," ")," ") -> 12 | B30: Roof Tiles | C30: 250 | D30: m2 | E30: 10 | F30: =IF(ISBLANK(C30),"",C30*E30) -> 2500 | H30: 250 | I30: m2 | J30: 10 | K30: =IF(ISBLANK(H30),"",H30*J30) -> 2500 | M30: 250 | N30: m2 | O30: 10 | P30: =IF(ISBLANK(M30),"",M30*O30) -> 2500 | R30: 250 | S30: m2 | T30: 10 | U30: =IF(ISBLANK(R30),"",R30*T30) -> 2500 | X30: m2 | Y30: =IF(ISBLANK(V30),"",V30*X30) | AC30: m2 | AD30: =IF(ISBLANK(AA30),"",AA30*AC30) | AH30: m2 | AI30: =IF(ISBLANK(AF30),"",AF30*AH30) | AM30: m2 | AN30: =IF(ISBLANK(AK30),"",AK30*AM30)
A31: =IF(B31>0,IF(C31>0,MAX($A$5:A30)+1," ")," ") | Y31: =IF(ISBLANK(V31),"",V31*X31) | AD31: =IF(ISBLANK(AA31),"",AA31*AC31) | AI31: =IF(ISBLANK(AF31),"",AF31*AH31) | AN31: =IF(ISBLANK(AK31),"",AK31*AM31)
A32: =IF(B32>0,IF(C32>0,MAX($A$5:A31)+1," ")," ") -> 13 | B32: Eaves tiles | C32: 250 | D32: m | E32: 10 | F32: =IF(ISBLANK(C32),"",C32*E32) -> 2500 | H32: 250 | I32: m | J32: 10 | K32: =IF(ISBLANK(H32),"",H32*J32) -> 2500 | M32: 250 | N32: m | O32: 10 | P32: =IF(ISBLANK(M32),"",M32*O32) -> 2500 | R32: 250 | S32: m | T32: 10 | U32: =IF(ISBLANK(R32),"",R32*T32) -> 2500 | X32: m | Y32: =IF(ISBLANK(V32),"",V32*X32) | AC32: m | AD32: =IF(ISBLANK(AA32),"",AA32*AC32) | AH32: m | AI32: =IF(ISBLANK(AF32),"",AF32*AH32) | AM32: m | AN32: =IF(ISBLANK(AK32),"",AK32*AM32)
Y33: =IF(ISBLANK(V33),"",V33*X33) | AD33: =IF(ISBLANK(AA33),"",AA33*AC33) | AI33: =IF(ISBLANK(AF33),"",AF33*AH33) | AN33: =IF(ISBLANK(AK33),"",AK33*AM33)
A34: =IF(B34>0,IF(C34>0,MAX($A$5:A32)+1," ")," ") -> 14 | B34: Ridge tiles | C34: 250 | D34: m | E34: 10 | F34: =IF(ISBLANK(C34),"",C34*E34) -> 2500 | H34: 250 | I34: m | J34: 10 | K34: =IF(ISBLANK(H34),"",H34*J34) -> 2500 | M34: 250 | N34: m | O34: 10 | P34: =IF(ISBLANK(M34),"",M34*O34) -> 2500 | R34: 250 | S34: m | T34: 10 | U34: =IF(ISBLANK(R34),"",R34*T34) -> 2500 | X34: m | Y34: =IF(ISBLANK(V34),"",V34*X34) | AC34: m | AD34: =IF(ISBLANK(AA34),"",AA34*AC34) | AH34: m | AI34: =IF(ISBLANK(AF34),"",AF34*AH34) | AM34: m | AN34: =IF(ISBLANK(AK34),"",AK34*AM34)
Y35: =IF(ISBLANK(V35),"",V35*X35) | AD35: =IF(ISBLANK(AA35),"",AA35*AC35) | AI35: =IF(ISBLANK(AF35),"",AF35*AH35) | AN35: =IF(ISBLANK(AK35),"",AK35*AM35)
A36: =IF(B36>0,IF(C36>0,MAX($A$5:A34)+1," ")," ") -> 15 | B36: Verge tiles | C36: 250 | D36: m | E36: 10 | F36: =IF(ISBLANK(C36),"",C36*E36) -> 2500 | H36: 250 | I36: m | J36: 10 | K36: =IF(ISBLANK(H36),"",H36*J36) -> 2500 | M36: 250 | N36: m | O36: 10 | P36: =IF(ISBLANK(M36),"",M36*O36) -> 2500 | R36: 250 | S36: m | T36: 10 | U36: =IF(ISBLANK(R36),"",R36*T36) -> 2500 | X36: m | Y36: =IF(ISBLANK(V36),"",V36*X36) | AC36: m | AD36: =IF(ISBLANK(AA36),"",AA36*AC36) | AH36: m | AI36: =IF(ISBLANK(AF36),"",AF36*AH36) | AM36: m | AN36: =IF(ISBLANK(AK36),"",AK36*AM36)
Y37: =IF(ISBLANK(V37),"",V37*X37) | AD37: =IF(ISBLANK(AA37),"",AA37*AC37) | AI37: =IF(ISBLANK(AF37),"",AF37*AH37) | AN37: =IF(ISBLANK(AK37),"",AK37*AM37)
A38: =IF(B38>0,IF(C38>0,MAX($A$5:A36)+1," ")," ") -> 16 | B38: Valley tiles | C38: 250 | D38: m | E38: 10 | F38: =IF(ISBLANK(C38),"",C38*E38) -> 2500 | H38: 250 | I38: m | J38: 10 | K38: =IF(ISBLANK(H38),"",H38*J38) -> 2500 | M38: 250 | N38: m | O38: 10 | P38: =IF(ISBLANK(M38),"",M38*O38) -> 2500 | R38: 250 | S38: m | T38: 10 | U38: =IF(ISBLANK(R38),"",R38*T38) -> 2500 | X38: m | Y38: =IF(ISBLANK(V38),"",V38*X38) | AC38: m | AD38: =IF(ISBLANK(AA38),"",AA38*AC38) | AH38: m | AI38: =IF(ISBLANK(AF38),"",AF38*AH38) | AM38: m | AN38: =IF(ISBLANK(AK38),"",AK38*AM38)
Y39: =IF(ISBLANK(V39),"",V39*X39) | AD39: =IF(ISBLANK(AA39),"",AA39*AC39) | AI39: =IF(ISBLANK(AF39),"",AF39*AH39) | AN39: =IF(ISBLANK(AK39),"",AK39*AM39)
A40: =IF(B40>0,IF(C40>0,MAX($A$5:A38)+1," ")," ") -> 17 | B40: Hip tiles | C40: 250 | D40: m | E40: 10 | F40: =IF(ISBLANK(C40),"",C40*E40) -> 2500 | H40: 250 | I40: m | J40: 10 | K40: =IF(ISBLANK(H40),"",H40*J40) -> 2500 | M40: 250 | N40: m | O40: 10 | P40: =IF(ISBLANK(M40),"",M40*O40) -> 2500 | R40: 250 | S40: m | T40: 10 | U40: =IF(ISBLANK(R40),"",R40*T40) -> 2500 | X40: m | Y40: =IF(ISBLANK(V40),"",V40*X40) | AC40: m | AD40: =IF(ISBLANK(AA40),"",AA40*AC40) | AH40: m | AI40: =IF(ISBLANK(AF40),"",AF40*AH40) | AM40: m | AN40: =IF(ISBLANK(AK40),"",AK40*AM40)
A41: =IF(B41>0,IF(C41>0,MAX($A$5:A40)+1," ")," ") | Y41: =IF(ISBLANK(V41),"",V41*X41) | AD41: =IF(ISBLANK(AA41),"",AA41*AC41) | AI41: =IF(ISBLANK(AF41),"",AF41*AH41) | AN41: =IF(ISBLANK(AK41),"",AK41*AM41)
A42: =IF(B42>0,IF(C42>0,MAX($A$5:A41)+1," ")," ") -> 18 | B42: Fascia and Soffit detail to truss overhangs, details unclear | C42: 250 | D42: m | E42: 10 | F42: =IF(ISBLANK(C42),"",C42*E42) -> 2500 | H42: 250 | I42: m | J42: 10 | K42: =IF(ISBLANK(H42),"",H42*J42) -> 2500 | M42: 250 | N42: m | O42: 10 | P42: =IF(ISBLANK(M42),"",M42*O42) -> 2500 | R42: 250 | S42: m | T42: 10 | U42: =IF(ISBLANK(R42),"",R42*T42) -> 2500 | X42: m | Y42: =IF(ISBLANK(V42),"",V42*X42) | AC42: m | AD42: =IF(ISBLANK(AA42),"",AA42*AC42) | AH42: m | AI42: =IF(ISBLANK(AF42),"",AF42*AH42) | AM42: m | AN42: =IF(ISBLANK(AK42),"",AK42*AM42)
A43: =IF(B43>0,IF(C43>0,MAX($A$5:A42)+1," ")," ") | Y43: =IF(ISBLANK(V43),"",V43*X43) | AD43: =IF(ISBLANK(AA43),"",AA43*AC43) | AI43: =IF(ISBLANK(AF43),"",AF43*AH43) | AN43: =IF(ISBLANK(AK43),"",AK43*AM43)
A44: =IF(B44>0,IF(C44>0,MAX($A$5:A43)+1," ")," ") -> 19 | B44: Gutters; | C44: 250 | D44: m | E44: 10 | F44: =IF(ISBLANK(C44),"",C44*E44) -> 2500 | H44: 250 | I44: m | J44: 10 | K44: =IF(ISBLANK(H44),"",H44*J44) -> 2500 | M44: 250 | N44: m | O44: 10 | P44: =IF(ISBLANK(M44),"",M44*O44) -> 2500 | R44: 250 | S44: m | T44: 10 | U44: =IF(ISBLANK(R44),"",R44*T44) -> 2500 | X44: m | Y44: =IF(ISBLANK(V44),"",V44*X44) | AC44: m | AD44: =IF(ISBLANK(AA44),"",AA44*AC44) | AH44: m | AI44: =IF(ISBLANK(AF44),"",AF44*AH44) | AM44: m | AN44: =IF(ISBLANK(AK44),"",AK44*AM44)
Y45: =IF(ISBLANK(V45),"",V45*X45) | AD45: =IF(ISBLANK(AA45),"",AA45*AC45) | AI45: =IF(ISBLANK(AF45),"",AF45*AH45) | AN45: =IF(ISBLANK(AK45),"",AK45*AM45)
A46: =IF(B46>0,IF(C46>0,MAX($A$5:A44)+1," ")," ") -> 20 | B46: downpipes | C46: 250 | D46: m | E46: 10 | F46: =IF(ISBLANK(C46),"",C46*E46) -> 2500 | H46: 250 | I46: m | J46: 10 | K46: =IF(ISBLANK(H46),"",H46*J46) -> 2500 | M46: 250 | N46: m | O46: 10 | P46: =IF(ISBLANK(M46),"",M46*O46) -> 2500 | R46: 250 | S46: m | T46: 10 | U46: =IF(ISBLANK(R46),"",R46*T46) -> 2500 | X46: m | Y46: =IF(ISBLANK(V46),"",V46*X46) | AC46: m | AD46: =IF(ISBLANK(AA46),"",AA46*AC46) | AH46: m | AI46: =IF(ISBLANK(AF46),"",AF46*AH46) | AM46: m | AN46: =IF(ISBLANK(AK46),"",AK46*AM46)
A47: =IF(B47>0,IF(C47>0,MAX($A$5:A46)+1," ")," ") | F47: =IF(ISBLANK(C47),"",C47*E47) | K47: =IF(ISBLANK(H47),"",H47*J47) | P47: =IF(ISBLANK(M47),"",M47*O47) | U47: =IF(ISBLANK(R47),"",R47*T47) | Z47: =IF(ISBLANK(W47),"",W47*Y47) | AE47: =IF(ISBLANK(AB47),"",AB47*AD47) | AJ47: =IF(ISBLANK(AG47),"",AG47*AI47) | AO47: =IF(ISBLANK(AL47),"",AL47*AN47)
A48: =IF(B48>0,IF(C48>0,MAX($A$5:A47)+1," ")," ") | B48: Any other works (contractor to specify) | F48: =IF(ISBLANK(C48),"",C48*E48) | K48: =IF(ISBLANK(H48),"",H48*J48) | P48: =IF(ISBLANK(M48),"",M48*O48) | U48: =IF(ISBLANK(R48),"",R48*T48) | Z48: =IF(ISBLANK(W48),"",W48*Y48) | AE48: =IF(ISBLANK(AB48),"",AB48*AD48) | AJ48: =IF(ISBLANK(AG48),"",AG48*AI48) | AO48: =IF(ISBLANK(AL48),"",AL48*AN48)
A49: =IF(B49>0,IF(C49>0,MAX($A$5:A48)+1," ")," ") -> 21 | B49: ……………………………………………. | C49: 1 | D49: item | F49: =IF(ISBLANK(C49),"",C49*E49) -> 0 | H49: 1 | I49: item | K49: =IF(ISBLANK(H49),"",H49*J49) -> 0 | M49: 1 | N49: item | P49: =IF(ISBLANK(M49),"",M49*O49) -> 0 | R49: 1 | S49: item | U49: =IF(ISBLANK(R49),"",R49*T49) -> 0 | W49: 1 | X49: item | Z49: =IF(ISBLANK(W49),"",W49*Y49) -> 0 | AB49: 1 | AC49: item | AE49: =IF(ISBLANK(AB49),"",AB49*AD49) -> 0 | AG49: 1 | AH49: item | AJ49: =IF(ISBLANK(AG49),"",AG49*AI49) -> 0 | AL49: 1 | AM49: item | AO49: =IF(ISBLANK(AL49),"",AL49*AN49) -> 0
A50: =IF(B50>0,IF(C50>0,MAX($A$5:A49)+1," ")," ") -> 22 | B50: ……………………………………………. | C50: 1 | D50: Item | F50: =IF(ISBLANK(C50),"",C50*E50) -> 0 | H50: 1 | I50: Item | K50: =IF(ISBLANK(H50),"",H50*J50) -> 0 | M50: 1 | N50: Item | P50: =IF(ISBLANK(M50),"",M50*O50) -> 0 | R50: 1 | S50: Item | U50: =IF(ISBLANK(R50),"",R50*T50) -> 0 | W50: 1 | X50: Item | Z50: =IF(ISBLANK(W50),"",W50*Y50) -> 0 | AB50: 1 | AC50: Item | AE50: =IF(ISBLANK(AB50),"",AB50*AD50) -> 0 | AG50: 1 | AH50: Item | AJ50: =IF(ISBLANK(AG50),"",AG50*AI50) -> 0 | AL50: 1 | AM50: Item | AO50: =IF(ISBLANK(AL50),"",AL50*AN50) -> 0
A51: =IF(B51>0,IF(C51>0,MAX($A$5:A50)+1," ")," ") -> 23 | B51: ……………………………………………. | C51: 1 | D51: Item | F51: =IF(ISBLANK(C51),"",C51*E51) -> 0 | H51: 1 | I51: Item | K51: =IF(ISBLANK(H51),"",H51*J51) -> 0 | M51: 1 | N51: Item | P51: =IF(ISBLANK(M51),"",M51*O51) -> 0 | R51: 1 | S51: Item | U51: =IF(ISBLANK(R51),"",R51*T51) -> 0 | W51: 1 | X51: Item | Z51: =IF(ISBLANK(W51),"",W51*Y51) -> 0 | AB51: 1 | AC51: Item | AE51: =IF(ISBLANK(AB51),"",AB51*AD51) -> 0 | AG51: 1 | AH51: Item | AJ51: =IF(ISBLANK(AG51),"",AG51*AI51) -> 0 | AL51: 1 | AM51: Item | AO51: =IF(ISBLANK(AL51),"",AL51*AN51) -> 0
A52: =IF(B52>0,IF(C52>0,MAX($A$5:A51)+1," ")," ") -> 24 | B52: ……………………………………………. | C52: 1 | D52: Item | F52: =IF(ISBLANK(C52),"",C52*E52) -> 0 | H52: 1 | I52: Item | K52: =IF(ISBLANK(H52),"",H52*J52) -> 0 | M52: 1 | N52: Item | P52: =IF(ISBLANK(M52),"",M52*O52) -> 0 | R52: 1 | S52: Item | U52: =IF(ISBLANK(R52),"",R52*T52) -> 0 | W52: 1 | X52: Item | Z52: =IF(ISBLANK(W52),"",W52*Y52) -> 0 | AB52: 1 | AC52: Item | AE52: =IF(ISBLANK(AB52),"",AB52*AD52) -> 0 | AG52: 1 | AH52: Item | AJ52: =IF(ISBLANK(AG52),"",AG52*AI52) -> 0 | AL52: 1 | AM52: Item | AO52: =IF(ISBLANK(AL52),"",AL52*AN52) -> 0
A53: =IF(B53>0,IF(C53>0,MAX($A$3:A47)+1," ")," ") | F53: =IF(ISBLANK(C53),"",C53*E53) | K53: =IF(ISBLANK(H53),"",H53*J53) | P53: =IF(ISBLANK(M53),"",M53*O53) | U53: =IF(ISBLANK(R53),"",R53*T53) | Z53: =IF(ISBLANK(W53),"",W53*Y53) | AE53: =IF(ISBLANK(AB53),"",AB53*AD53) | AJ53: =IF(ISBLANK(AG53),"",AG53*AI53) | AO53: =IF(ISBLANK(AL53),"",AL53*AN53)
E54: Total | F54: =SUM(F5:F53) -> 50000 | J54: Total | K54: =SUM(K5:K53) -> 50000 | O54: Total | P54: =SUM(P5:P53) -> 50000 | T54: Total | U54: =SUM(U5:U53) -> 50000 | Y54: Total | Z54: =SUM(Z5:Z53) -> 0 | AD54: Total | AE54: =SUM(AE5:AE53) -> 0 | AI54: Total | AJ54: =SUM(AJ5:AJ53) -> 0 | AN54: Total | AO54: =SUM(AO5:AO53) -> 0

Sheet 2.6 Windows & external Doors
B1: Return to ELEMENT INDEX
B2: Return to SUMMARY
C3: =SUMMARY!E3 -> Sample Cost Plan - Elm Court Residential, Rev 01 | H3: =SUMMARY!K3 -> Ridgeway Construction | M3: =SUMMARY!N3 -> Brightstone Builders | R3: =SUMMARY!Q3 -> Kestrel Contractors | W3: =SUMMARY!T3 -> INSERT CONTRACTOR 4 | AB3: =SUMMARY!W3 -> INSERT CONTRACTOR 5 | AG3: =SUMMARY!Z3 -> INSERT CONTRACTOR 6 | AL3: =SUMMARY!AC3 -> INSERT CONTRACTOR 7
B4: {=MID(CELL("filename",A3),FIND("]",CELL("filename",A3))+1,255)} -> 2.6 Windows & external Doors | C4: Qty | D4: Unit | E4: Rate | F4: Total | H4: Qty | I4: Unit | J4: Rate | K4: Total | M4: Qty | N4: Unit | O4: Rate | P4: Total | R4: Qty | S4: Unit | T4: Rate | U4: Total | W4: Qty | X4: Unit | Y4: Rate | Z4: Total | AB4: Qty | AC4: Unit | AD4: Rate | AE4: Total | AG4: Qty | AH4: Unit | AI4: Rate | AJ4: Total | AL4: Qty | AM4: Unit | AN4: Rate | AO4: Total
A5: =IF(B5>0,IF(C5>0,MAX($A$3:A4)+1," ")," ") | F5: =IF(ISBLANK(C5),"",C5*E5) | K5: =IF(ISBLANK(H5),"",H5*J5) | P5: =IF(ISBLANK(M5),"",M5*O5) | U5: =IF(ISBLANK(R5),"",R5*T5) | Z5: =IF(ISBLANK(W5),"",W5*Y5) | AE5: =IF(ISBLANK(AB5),"",AB5*AD5) | AJ5: =IF(ISBLANK(AG5),"",AG5*AI5) | AO5: =IF(ISBLANK(AL5),"",AL5*AN5)
A6: =IF(B6>0,IF(C6>0,MAX($A$3:A5)+1," ")," ") | B6: =B4 -> 2.6 Windows & external Doors | F6: =IF(ISBLANK(C6),"",C6*E6) | K6: =IF(ISBLANK(H6),"",H6*J6) | P6: =IF(ISBLANK(M6),"",M6*O6) | U6: =IF(ISBLANK(R6),"",R6*T6) | Z6: =IF(ISBLANK(W6),"",W6*Y6) | AE6: =IF(ISBLANK(AB6),"",AB6*AD6) | AJ6: =IF(ISBLANK(AG6),"",AG6*AI6) | AO6: =IF(ISBLANK(AL6),"",AL6*AN6)
A7: =IF(B7>0,IF(C7>0,MAX($A$3:A6)+1," ")," ") | F7: =IF(ISBLANK(C7),"",C7*E7) | K7: =IF(ISBLANK(H7),"",H7*J7) | P7: =IF(ISBLANK(M7),"",M7*O7) | U7: =IF(ISBLANK(R7),"",R7*T7) | Z7: =IF(ISBLANK(W7),"",W7*Y7) | AE7: =IF(ISBLANK(AB7),"",AB7*AD7) | AJ7: =IF(ISBLANK(AG7),"",AG7*AI7) | AO7: =IF(ISBLANK(AL7),"",AL7*AN7)
A8: =IF(B8>0,IF(C8>0,MAX($A$5:A7)+1," ")," ") -> 1 | B8: Setting out of Windows and Door Openings | C8: 1 | D8: item | E8: 500 | F8: =IF(ISBLANK(C8),"",C8*E8) -> 500 | H8: 1 | I8: item | J8: 500 | K8: =IF(ISBLANK(H8),"",H8*J8) -> 500 | M8: 1 | N8: item | O8: 500 | P8: =IF(ISBLANK(M8),"",M8*O8) -> 500 | R8: 1 | S8: item | T8: 500 | U8: =IF(ISBLANK(R8),"",R8*T8) -> 500 | X8: item | Z8: =IF(ISBLANK(W8),"",W8*Y8) | AC8: item | AE8: =IF(ISBLANK(AB8),"",AB8*AD8) | AH8: item | AJ8: =IF(ISBLANK(AG8),"",AG8*AI8) | AM8: item | AO8: =IF(ISBLANK(AL8),"",AL8*AN8)
F9: =IF(ISBLANK(C9),"",C9*E9) | K9: =IF(ISBLANK(H9),"",H9*J9) | P9: =IF(ISBLANK(M9),"",M9*O9) | U9: =IF(ISBLANK(R9),"",R9*T9) | Z9: =IF(ISBLANK(W9),"",W9*Y9) | AE9: =IF(ISBLANK(AB9),"",AB9*AD9) | AJ9: =IF(ISBLANK(AG9),"",AG9*AI9) | AO9: =IF(ISBLANK(AL9),"",AL9*AN9)
A10: =IF(B10>0,IF(C10>0,MAX($A$5:A9)+1," ")," ") -> 2 | B10: UPVC Doors: Assumed 975mm (w) x 2500mm (h) Entrance Door | C10: 10 | D10: nr | E10: 100 | F10: =IF(ISBLANK(C10),"",C10*E10) -> 1000 | H10: 10 | I10: nr | J10: 100 | K10: =IF(ISBLANK(H10),"",H10*J10) -> 1000 | M10: 10 | N10: nr | O10: 100 | P10: =IF(ISBLANK(M10),"",M10*O10) -> 1000 | R10: 10 | S10: nr | T10: 100 | U10: =IF(ISBLANK(R10),"",R10*T10) -> 1000 | X10: nr | Z10: =IF(ISBLANK(W10),"",W10*Y10) | AC10: nr | AE10: =IF(ISBLANK(AB10),"",AB10*AD10) | AH10: nr | AJ10: =IF(ISBLANK(AG10),"",AG10*AI10) | AM10: nr | AO10: =IF(ISBLANK(AL10),"",AL10*AN10)
A11: =IF(B11>0,IF(C11>0,MAX($A$5:A10)+1," ")," ")
A12: =IF(B12>0,IF(C12>0,MAX($A$5:A11)+1," ")," ") -> 3 | B12: UPVC Doors: Assumed 1200mm (w) x 2500mm (h) Entrance Door | C12: 10 | D12: nr | E12: 100 | F12: =IF(ISBLANK(C12),"",C12*E12) -> 1000 | H12: 10 | I12: nr | J12: 100 | K12: =IF(ISBLANK(H12),"",H12*J12) -> 1000 | M12: 10 | N12: nr | O12: 100 | P12: =IF(ISBLANK(M12),"",M12*O12) -> 1000 | R12: 10 | S12: nr | T12: 100 | U12: =IF(ISBLANK(R12),"",R12*T12) -> 1000 | X12: nr | Z12: =IF(ISBLANK(W12),"",W12*Y12) | AC12: nr | AE12: =IF(ISBLANK(AB12),"",AB12*AD12) | AH12: nr | AJ12: =IF(ISBLANK(AG12),"",AG12*AI12) | AM12: nr | AO12: =IF(ISBLANK(AL12),"",AL12*AN12)
A13: =IF(B13>0,IF(C13>0,MAX($A$5:A12)+1," ")," ")
A14: =IF(B14>0,IF(C14>0,MAX($A$5:A13)+1," ")," ") -> 4 | B14: Aluminium Glazed Doors: Assumed 975mm (w) x 2500mm (h) Entrance Door | C14: 10 | D14: nr | E14: 100 | F14: =IF(ISBLANK(C14),"",C14*E14) -> 1000 | H14: 10 | I14: nr | J14: 100 | K14: =IF(ISBLANK(H14),"",H14*J14) -> 1000 | M14: 10 | N14: nr | O14: 100 | P14: =IF(ISBLANK(M14),"",M14*O14) -> 1000 | R14: 10 | S14: nr | T14: 100 | U14: =IF(ISBLANK(R14),"",R14*T14) -> 1000 | X14: nr | Z14: =IF(ISBLANK(W14),"",W14*Y14) | AC14: nr | AE14: =IF(ISBLANK(AB14),"",AB14*AD14) | AH14: nr | AJ14: =IF(ISBLANK(AG14),"",AG14*AI14) | AM14: nr | AO14: =IF(ISBLANK(AL14),"",AL14*AN14)
A15: =IF(B15>0,IF(C15>0,MAX($A$5:A14)+1," ")," ")
A16: =IF(B16>0,IF(C16>0,MAX($A$5:A15)+1," ")," ") -> 5 | B16: Aluminium Glazed Doors: Assumed 1200mm (w) x 2500mm (h) Entrance Door | C16: 10 | D16: nr | E16: 100 | F16: =IF(ISBLANK(C16),"",C16*E16) -> 1000 | H16: 10 | I16: nr | J16: 100 | K16: =IF(ISBLANK(H16),"",H16*J16) -> 1000 | M16: 10 | N16: nr | O16: 100 | P16: =IF(ISBLANK(M16),"",M16*O16) -> 1000 | R16: 10 | S16: nr | T16: 100 | U16: =IF(ISBLANK(R16),"",R16*T16) -> 1000 | X16: nr | Z16: =IF(ISBLANK(W16),"",W16*Y16) | AC16: nr | AE16: =IF(ISBLANK(AB16),"",AB16*AD16) | AH16: nr | AJ16: =IF(ISBLANK(AG16),"",AG16*AI16) | AM16: nr | AO16: =IF(ISBLANK(AL16),"",AL16*AN16)
A17: =IF(B17>0,IF(C17>0,MAX($A$5:A16)+1," ")," ")
A18: =IF(B18>0,IF(C18>0,MAX($A$5:A17)+1," ")," ") -> 6 | B18: Composite Doors: Assumed 975mm (w) x 2500mm (h) Entrance Door | C18: 10 | D18: nr | E18: 100 | F18: =IF(ISBLANK(C18),"",C18*E18) -> 1000 | H18: 10 | I18: nr | J18: 100 | K18: =IF(ISBLANK(H18),"",H18*J18) -> 1000 | M18: 10 | N18: nr | O18: 100 | P18: =IF(ISBLANK(M18),"",M18*O18) -> 1000 | R18: 10 | S18: nr | T18: 100 | U18: =IF(ISBLANK(R18),"",R18*T18) -> 1000 | X18: nr | Z18: =IF(ISBLANK(W18),"",W18*Y18) | AC18: nr | AE18: =IF(ISBLANK(AB18),"",AB18*AD18) | AH18: nr | AJ18: =IF(ISBLANK(AG18),"",AG18*AI18) | AM18: nr | AO18: =IF(ISBLANK(AL18),"",AL18*AN18)
A19: =IF(B19>0,IF(C19>0,MAX($A$5:A18)+1," ")," ")
A20: =IF(B20>0,IF(C20>0,MAX($A$5:A19)+1," ")," ") -> 7 | B20: Composite Doors: Assumed 975mm (w) x 2500mm (h) Entrance Door | C20: 10 | D20: nr | E20: 100 | F20: =IF(ISBLANK(C20),"",C20*E20) -> 1000 | H20: 10 | I20: nr | J20: 100 | K20: =IF(ISBLANK(H20),"",H20*J20) -> 1000 | M20: 10 | N20: nr | O20: 100 | P20: =IF(ISBLANK(M20),"",M20*O20) -> 1000 | R20: 10 | S20: nr | T20: 100 | U20: =IF(ISBLANK(R20),"",R20*T20) -> 1000 | X20: nr | Z20: =IF(ISBLANK(W20),"",W20*Y20) | AC20: nr | AE20: =IF(ISBLANK(AB20),"",AB20*AD20) | AH20: nr | AJ20: =IF(ISBLANK(AG20),"",AG20*AI20) | AM20: nr | AO20: =IF(ISBLANK(AL20),"",AL20*AN20)
A21: =IF(B21>0,IF(C21>0,MAX($A$5:A20)+1," ")," ")
A22: =IF(B22>0,IF(C22>0,MAX($A$5:A21)+1," ")," ") -> 8 | B22: External Windows: Aluminium Framaed, small (<1.5m2) | C22: 10 | D22: m2 | E22: 100 | F22: =IF(ISBLANK(C22),"",C22*E22) -> 1000 | H22: 10 | I22: m2 | J22: 100 | K22: =IF(ISBLANK(H22),"",H22*J22) -> 1000 | M22: 10 | N22: m2 | O22: 100 | P22: =IF(ISBLANK(M22),"",M22*O22) -> 1000 | R22: 10 | S22: m2 | T22: 100 | U22: =IF(ISBLANK(R22),"",R22*T22) -> 1000 | X22: m2 | Z22: =IF(ISBLANK(W22),"",W22*Y22) | AC22: m2 | AE22: =IF(ISBLANK(AB22),"",AB22*AD22) | AH22: m2 | AJ22: =IF(ISBLANK(AG22),"",AG22*AI22) | AM22: m2 | AO22: =IF(ISBLANK(AL22),"",AL22*AN22)
A23: =IF(B23>0,IF(C23>0,MAX($A$5:A22)+1," ")," ")
A24: =IF(B24>0,IF(C24>0,MAX($A$5:A23)+1," ")," ") -> 9 | B24: External Windows: Aluminium Framed, Medium (<1.5-3m2) | C24: 10 | D24: m2 | E24: 100 | F24: =IF(ISBLANK(C24),"",C24*E24) -> 1000 | H24: 10 | I24: m2 | J24: 100 | K24: =IF(ISBLANK(H24),"",H24*J24) -> 1000 | M24: 10 | N24: m2 | O24: 100 | P24: =IF(ISBLANK(M24),"",M24*O24) -> 1000 | R24: 10 | S24: m2 | T24: 100 | U24: =IF(ISBLANK(R24),"",R24*T24) -> 1000 | X24: m2 | Z24: =IF(ISBLANK(W24),"",W24*Y24) | AC24: m2 | AE24: =IF(ISBLANK(AB24),"",AB24*AD24) | AH24: m2 | AJ24: =IF(ISBLANK(AG24),"",AG24*AI24) | AM24: m2 | AO24: =IF(ISBLANK(AL24),"",AL24*AN24)
A25: =IF(B25>0,IF(C25>0,MAX($A$5:A24)+1," ")," ")
A26: =IF(B26>0,IF(C26>0,MAX($A$5:A25)+1," ")," ") -> 10 | B26: External Windows: Aluminium Framed, small (>3m2) | C26: 10 | D26: m2 | E26: 100 | F26: =IF(ISBLANK(C26),"",C26*E26) -> 1000 | H26: 10 | I26: m2 | J26: 100 | K26: =IF(ISBLANK(H26),"",H26*J26) -> 1000 | M26: 10 | N26: m2 | O26: 100 | P26: =IF(ISBLANK(M26),"",M26*O26) -> 1000 | R26: 10 | S26: m2 | T26: 100 | U26: =IF(ISBLANK(R26),"",R26*T26) -> 1000 | X26: m2 | Z26: =IF(ISBLANK(W26),"",W26*Y26) | AC26: m2 | AE26: =IF(ISBLANK(AB26),"",AB26*AD26) | AH26: m2 | AJ26: =IF(ISBLANK(AG26),"",AG26*AI26) | AM26: m2 | AO26: =IF(ISBLANK(AL26),"",AL26*AN26)
A27: =IF(B27>0,IF(C27>0,MAX($A$5:A26)+1," ")," ")
A28: =IF(B28>0,IF(C28>0,MAX($A$5:A27)+1," ")," ") -> 11 | B28: External Windows: Aluminium Framaed, small (<1.5m2) | C28: 10 | D28: m2 | E28: 100 | F28: =IF(ISBLANK(C28),"",C28*E28) -> 1000 | H28: 10 | I28: m2 | J28: 100 | K28: =IF(ISBLANK(H28),"",H28*J28) -> 1000 | M28: 10 | N28: m2 | O28: 100 | P28: =IF(ISBLANK(M28),"",M28*O28) -> 1000 | R28: 10 | S28: m2 | T28: 100 | U28: =IF(ISBLANK(R28),"",R28*T28) -> 1000 | X28: m2 | Z28: =IF(ISBLANK(W28),"",W28*Y28) | AC28: m2 | AE28: =IF(ISBLANK(AB28),"",AB28*AD28) | AH28: m2 | AJ28: =IF(ISBLANK(AG28),"",AG28*AI28) | AM28: m2 | AO28: =IF(ISBLANK(AL28),"",AL28*AN28)
A29: =IF(B29>0,IF(C29>0,MAX($A$5:A28)+1," ")," ")
A30: =IF(B30>0,IF(C30>0,MAX($A$5:A29)+1," ")," ") -> 12 | B30: External Windows: UPVC Framed, Medium (<1.5-3m2) | C30: 10 | D30: m2 | E30: 100 | F30: =IF(ISBLANK(C30),"",C30*E30) -> 1000 | H30: 10 | I30: m2 | J30: 100 | K30: =IF(ISBLANK(H30),"",H30*J30) -> 1000 | M30: 10 | N30: m2 | O30: 100 | P30: =IF(ISBLANK(M30),"",M30*O30) -> 1000 | R30: 10 | S30: m2 | T30: 100 | U30: =IF(ISBLANK(R30),"",R30*T30) -> 1000 | X30: m2 | Z30: =IF(ISBLANK(W30),"",W30*Y30) | AC30: m2 | AE30: =IF(ISBLANK(AB30),"",AB30*AD30) | AH30: m2 | AJ30: =IF(ISBLANK(AG30),"",AG30*AI30) | AM30: m2 | AO30: =IF(ISBLANK(AL30),"",AL30*AN30)
A31: =IF(B31>0,IF(C31>0,MAX($A$5:A30)+1," ")," ")
A32: =IF(B32>0,IF(C32>0,MAX($A$5:A31)+1," ")," ") -> 13 | B32: External Windows: UPVC Framed, small (>3m2) | C32: 10 | D32: m2 | E32: 100 | F32: =IF(ISBLANK(C32),"",C32*E32) -> 1000 | H32: 10 | I32: m2 | J32: 100 | K32: =IF(ISBLANK(H32),"",H32*J32) -> 1000 | M32: 10 | N32: m2 | O32: 100 | P32: =IF(ISBLANK(M32),"",M32*O32) -> 1000 | R32: 10 | S32: m2 | T32: 100 | U32: =IF(ISBLANK(R32),"",R32*T32) -> 1000 | X32: m2 | Z32: =IF(ISBLANK(W32),"",W32*Y32) | AC32: m2 | AE32: =IF(ISBLANK(AB32),"",AB32*AD32) | AH32: m2 | AJ32: =IF(ISBLANK(AG32),"",AG32*AI32) | AM32: m2 | AO32: =IF(ISBLANK(AL32),"",AL32*AN32)
A33: =IF(B33>0,IF(C33>0,MAX($A$5:A32)+1," ")," ")
A34: =IF(B34>0,IF(C34>0,MAX($A$5:A33)+1," ")," ") -> 14 | B34: External Windows: UPVC Framaed, small (<1.5m2) | C34: 10 | D34: m2 | E34: 100 | F34: =IF(ISBLANK(C34),"",C34*E34) -> 1000 | H34: 10 | I34: m2 | J34: 100 | K34: =IF(ISBLANK(H34),"",H34*J34) -> 1000 | M34: 10 | N34: m2 | O34: 100 | P34: =IF(ISBLANK(M34),"",M34*O34) -> 1000 | R34: 10 | S34: m2 | T34: 100 | U34: =IF(ISBLANK(R34),"",R34*T34) -> 1000 | X34: m2 | Z34: =IF(ISBLANK(W34),"",W34*Y34) | AC34: m2 | AE34: =IF(ISBLANK(AB34),"",AB34*AD34) | AH34: m2 | AJ34: =IF(ISBLANK(AG34),"",AG34*AI34) | AM34: m2 | AO34: =IF(ISBLANK(AL34),"",AL34*AN34)
A35: =IF(B35>0,IF(C35>0,MAX($A$5:A34)+1," ")," ")
A36: =IF(B36>0,IF(C36>0,MAX($A$5:A35)+1," ")," ") -> 15 | B36: Timber Windows: All Sizes (note size here) | C36: 10 | D36: m2 | E36: 100 | F36: =IF(ISBLANK(C36),"",C36*E36) -> 1000 | H36: 10 | I36: m2 | J36: 100 | K36: =IF(ISBLANK(H36),"",H36*J36) -> 1000 | M36: 10 | N36: m2 | O36: 100 | P36: =IF(ISBLANK(M36),"",M36*O36) -> 1000 | R36: 10 | S36: m2 | T36: 100 | U36: =IF(ISBLANK(R36),"",R36*T36) -> 1000 | X36: m2 | Z36: =IF(ISBLANK(W36),"",W36*Y36) | AC36: m2 | AE36: =IF(ISBLANK(AB36),"",AB36*AD36) | AH36: m2 | AJ36: =IF(ISBLANK(AG36),"",AG36*AI36) | AM36: m2 | AO36: =IF(ISBLANK(AL36),"",AL36*AN36)
A37: =IF(B37>0,IF(C37>0,MAX($A$5:A36)+1," ")," ")
A38: =IF(B38>0,IF(C38>0,MAX($A$5:A37)+1," ")," ") -> 16 | B38: Curtain wall glazed panels / feature glazing | C38: 10 | D38: m2 | E38: 100 | F38: =IF(ISBLANK(C38),"",C38*E38) -> 1000 | H38: 10 | I38: m2 | J38: 100 | K38: =IF(ISBLANK(H38),"",H38*J38) -> 1000 | M38: 10 | N38: m2 | O38: 100 | P38: =IF(ISBLANK(M38),"",M38*O38) -> 1000 | R38: 10 | S38: m2 | T38: 100 | U38: =IF(ISBLANK(R38),"",R38*T38) -> 1000 | X38: m2 | Z38: =IF(ISBLANK(W38),"",W38*Y38) | AC38: m2 | AE38: =IF(ISBLANK(AB38),"",AB38*AD38) | AH38: m2 | AJ38: =IF(ISBLANK(AG38),"",AG38*AI38) | AM38: m2 | AO38: =IF(ISBLANK(AL38),"",AL38*AN38)
A39: =IF(B39>0,IF(C39>0,MAX($A$5:A38)+1," ")," ")
A40: =IF(B40>0,IF(C40>0,MAX($A$5:A39)+1," ")," ") -> 17 | B40: E/O: External Windows - Obscure | C40: 10 | D40: m2 | E40: 100 | F40: =IF(ISBLANK(C40),"",C40*E40) -> 1000 | H40: 10 | I40: m2 | J40: 100 | K40: =IF(ISBLANK(H40),"",H40*J40) -> 1000 | M40: 10 | N40: m2 | O40: 100 | P40: =IF(ISBLANK(M40),"",M40*O40) -> 1000 | R40: 10 | S40: m2 | T40: 100 | U40: =IF(ISBLANK(R40),"",R40*T40) -> 1000 | X40: m2 | Z40: =IF(ISBLANK(W40),"",W40*Y40) | AC40: m2 | AE40: =IF(ISBLANK(AB40),"",AB40*AD40) | AH40: m2 | AJ40: =IF(ISBLANK(AG40),"",AG40*AI40) | AM40: m2 | AO40: =IF(ISBLANK(AL40),"",AL40*AN40)
A41: =IF(B41>0,IF(C41>0,MAX($A$5:A40)+1," ")," ") | F41: =IF(ISBLANK(C41),"",C41*E41) | K41: =IF(ISBLANK(H41),"",H41*J41) | P41: =IF(ISBLANK(M41),"",M41*O41) | U41: =IF(ISBLANK(R41),"",R41*T41) | Z41: =IF(ISBLANK(W41),"",W41*Y41) | AE41: =IF(ISBLANK(AB41),"",AB41*AD41) | AJ41: =IF(ISBLANK(AG41),"",AG41*AI41) | AO41: =IF(ISBLANK(AL41),"",AL41*AN41)
A42: =IF(B42>0,IF(C42>0,MAX($A$5:A41)+1," ")," ") -> 18 | B42: Ironmongery, locks and door furniture | C42: 10 | D42: nr | E42: 55 | F42: =IF(ISBLANK(C42),"",C42*E42) -> 550 | H42: 10 | I42: nr | J42: 55 | K42: =IF(ISBLANK(H42),"",H42*J42) -> 550 | M42: 10 | N42: nr | O42: 55 | P42: =IF(ISBLANK(M42),"",M42*O42) -> 550 | R42: 10 | S42: nr | T42: 55 | U42: =IF(ISBLANK(R42),"",R42*T42) -> 550 | X42: nr | Z42: =IF(ISBLANK(W42),"",W42*Y42) | AC42: nr | AE42: =IF(ISBLANK(AB42),"",AB42*AD42) | AH42: nr | AJ42: =IF(ISBLANK(AG42),"",AG42*AI42) | AM42: nr | AO42: =IF(ISBLANK(AL42),"",AL42*AN42)
A43: =IF(B43>0,IF(C43>0,MAX($A$5:A42)+1," ")," ") | F43: =IF(ISBLANK(C43),"",C43*E43) | K43: =IF(ISBLANK(H43),"",H43*J43) | P43: =IF(ISBLANK(M43),"",M43*O43) | U43: =IF(ISBLANK(R43),"",R43*T43) | Z43: =IF(ISBLANK(W43),"",W43*Y43) | AE43: =IF(ISBLANK(AB43),"",AB43*AD43) | AJ43: =IF(ISBLANK(AG43),"",AG43*AI43) | AO43: =IF(ISBLANK(AL43),"",AL43*AN43)
A44: =IF(B44>0,IF(C44>0,MAX($A$5:A43)+1," ")," ") -> 19 | B44: Seals, weatherproofing and mastic joints | C44: 1 | D44: item | E44: 250 | F44: =IF(ISBLANK(C44),"",C44*E44) -> 250 | H44: 1 | I44: item | J44: 250 | K44: =IF(ISBLANK(H44),"",H44*J44) -> 250 | M44: 1 | N44: item | O44: 250 | P44: =IF(ISBLANK(M44),"",M44*O44) -> 250 | R44: 1 | S44: item | T44: 250 | U44: =IF(ISBLANK(R44),"",R44*T44) -> 250 | X44: item | Z44: =IF(ISBLANK(W44),"",W44*Y44) | AC44: item | AE44: =IF(ISBLANK(AB44),"",AB44*AD44) | AH44: item | AJ44: =IF(ISBLANK(AG44),"",AG44*AI44) | AM44: item | AO44: =IF(ISBLANK(AL44),"",AL44*AN44)
A45: =IF(B45>0,IF(C45>0,MAX($A$5:A44)+1," ")," ") | F45: =IF(ISBLANK(C45),"",C45*E45) | K45: =IF(ISBLANK(H45),"",H45*J45) | P45: =IF(ISBLANK(M45),"",M45*O45) | U45: =IF(ISBLANK(R45),"",R45*T45) | Z45: =IF(ISBLANK(W45),"",W45*Y45) | AE45: =IF(ISBLANK(AB45),"",AB45*AD45) | AJ45: =IF(ISBLANK(AG45),"",AG45*AI45) | AO45: =IF(ISBLANK(AL45),"",AL45*AN45)
A46: =IF(B46>0,IF(C46>0,MAX($A$5:A45)+1," ")," ") -> 20 | B46: Testing and commisioning | C46: 1 | D46: item | E46: 500 | F46: =IF(ISBLANK(C46),"",C46*E46) -> 500 | H46: 1 | I46: item | J46: 500 | K46: =IF(ISBLANK(H46),"",H46*J46) -> 500 | M46: 1 | N46: item | O46: 500 | P46: =IF(ISBLANK(M46),"",M46*O46) -> 500 | R46: 1 | S46: item | T46: 500 | U46: =IF(ISBLANK(R46),"",R46*T46) -> 500 | X46: item | Z46: =IF(ISBLANK(W46),"",W46*Y46) | AC46: item | AE46: =IF(ISBLANK(AB46),"",AB46*AD46) | AH46: item | AJ46: =IF(ISBLANK(AG46),"",AG46*AI46) | AM46: item | AO46: =IF(ISBLANK(AL46),"",AL46*AN46)
